Workbook

Sheet 1-50
A1: Item ID | B1: Query Type | C1: Difficulty | D1: Legal Domain | E1: Question | F1: Reference Answer | G1: Constitutional Articles | H1: Supporting Passage(s) | I1: Annotattion Type | J1: Annotation Date | K1: Reviewer IDs | L1: Reviever 1: Chathuri Madushika (LLB ousl) | Q1: Reviever 2: Rohana Dasanayaka (LLB ousl) | V1: Reviever 3: Dulani Kulasooriya (LLB ousl) | AA1: Reviever 4: Dulshan Liyanaarachchi (LLB ousl) | AF1: Reviever 5: Inoshika Kodithuwakku (LLB ousl) | AK1: Mean | AL1: Mean | AM1: Mean
L2: Reviewer ID: LEGAL_EXPERT_1 | Q2: Reviewer ID: LEGAL_EXPERT_2 | V2: Reviewer ID: LEGAL_EXPERT_3 | AA2: Reviewer ID: LEGAL_EXPERT_4 | AF2: Reviewer ID: LEGAL_EXPERT_5 | AK2: Reviewer IDs: LEGAL_EXPERT_1, LEGAL_EXPERT_2, LEGAL_EXPERT_3, LEGAL_EXPERT_4, LEGAL_EXPERT_5
L3: Correctness (1=Poor 5=Excellent) | M3: Completeness (1=Poor 5=Excellent) | N3: Clarity (1=Poor 5=Excellent) | O3: Expert Comments | P3: Review Date | Q3: Correctness (1=Poor 5=Excellent) | R3: Completeness (1=Poor 5=Excellent) | S3: Clarity (1=Poor 5=Excellent) | T3: Expert Comments | U3: Review Date | V3: Correctness (1=Poor 5=Excellent) | W3: Completeness (1=Poor 5=Excellent) | X3: Clarity (1=Poor 5=Excellent) | Y3: Expert Comments | Z3: Review Date | AA3: Correctness (1=Poor 5=Excellent) | AB3: Completeness (1=Poor 5=Excellent) | AC3: Clarity (1=Poor 5=Excellent) | AD3: Expert Comments | AE3: Review Date | AF3: Correctness (1=Poor 5=Excellent) | AG3: Completeness (1=Poor 5=Excellent) | AH3: Clarity (1=Poor 5=Excellent) | AI3: Expert Comments | AJ3: Review Date | AK3: Correctness (1=Poor 5=Excellent) | AL3: Completeness (1=Poor 5=Excellent) | AM3: Clarity (1=Poor 5=Excellent)
A4: QAC_001 | B4: Factual | C4: Easy | D4: Administrative | E4: What is the constitutional status and form of government of Sri Lanka? | F4: According to Article 1 of the Constitution, Sri Lanka (Ceylon) is a Free, Sovereign, Independent and Democratic Socialist Republic and shall be known as the Democratic Socialist Republic of Sri Lanka. Article 2 further declares that the Republic of Sri Lanka is a Unitary State. | G4: Article 1, Article 2 | H4: Art. 1: Sri Lanka (Ceylon) is a Free, Sovereign, The State Independent and Democratic Socialist Republic and shall be known as the Democratic Socialist Republic of Sri Lanka. || Art. 2: The Republic of Sri Lanka is a Unitary State. Unitary State | I4: Human Annotated | J4: =MAX(P4,U4,Z4,AE4,AJ4) -> 46170 | K4: LEGAL_EXPERT_1, LEGAL_EXPERT_2, LEGAL_EXPERT_3, LEGAL_EXPERT_4, LEGAL_EXPERT_5 | L4: 4.8 | M4: 4.5 | N4: 4.6 | P4: 2026.05.24 | Q4: 4.7 | R4: 4.6 | S4: 4.6 | U4: 46168 | V4: 4.7 | W4: 4.7 | X4: 4.6 | Z4: 46168 | AA4: 4.7 | AB4: 4.8 | AC4: 4.7 | AE4: 46170 | AF4: 4.7 | AG4: 4.6 | AH4: 4.7 | AJ4: 2026.05.28 | AK4: =AVERAGE(L4,Q4,V4,AA4,AF4) -> 4.72 | AL4: =AVERAGE(M4,R4,W4,AB4,AG4) -> 4.64 | AM4: =AVERAGE(N4,S4,X4,AC4,AH4) -> 4.64
A5: QAC_002 | B5: Factual | C5: Easy | D5: Administrative | E5: Where does sovereignty reside under the Constitution of Sri Lanka? | F5: Article 3 of the Constitution declares that in the Republic of Sri Lanka, sovereignty is in the People and is inalienable. Sovereignty includes the powers of government, fundamental rights and the franchise. | G5: Article 3 | H5: Art. 3: In the Republic of Sri Lanka sovereignty is Sovereignty in the People and is inalienable. Sovereignty includes the of the People powers of government, fundamental rights and the franchise. | I5: Human Annotated | J5: =MAX(P5,U5,Z5,AE5,AJ5) -> 46170 | K5: LEGAL_EXPERT_1, LEGAL_EXPERT_2, LEGAL_EXPERT_3, LEGAL_EXPERT_4, LEGAL_EXPERT_5 | L5: 4.8 | M5: 4.3 | N5: 4.6 | P5: 2026.05.24 | Q5: 4.8 | R5: 4.4 | S5: 4.5 | U5: 46168 | V5: 4.3 | W5: 4.4 | X5: 4.6 | Z5: 46168 | AA5: 4.4 | AB5: 4.5 | AC5: 4.6 | AE5: 46170 | AF5: 4.7 | AG5: 4.6 | AH5: 4.7 | AJ5: 2026.05.28 | AK5: =AVERAGE(L5,Q5,V5,AA5,AF5) -> 4.6 | AL5: =AVERAGE(M5,R5,W5,AB5,AG5) -> 4.44 | AM5: =AVERAGE(N5,S5,X5,AC5,AH5) -> 4.6
A6: QAC_003 | B6: Factual | C6: Easy | D6: Administrative | E6: What is the constitutional status of Buddhism in Sri Lanka? | F6: Article 9 of the Constitution gives Buddhism the foremost place in Sri Lanka. It shall be the duty of the State to protect and foster the Buddha Sasana, while assuring to all religions the rights granted by Articles 10 and 14(1)(e) of the Constitution. | G6: Article 9 | H6: Art. 9: The Republic of Sri Lanka shall give to Buddhism Buddhism the foremost place and accordingly it shall be the duty of the State to protect and foster the Buddha Sasana, while assuring to all religions | I6: Human Annotated | J6: =MAX(P6,U6,Z6,AE6,AJ6) -> 46170 | K6: LEGAL_EXPERT_1, LEGAL_EXPERT_2, LEGAL_EXPERT_3, LEGAL_EXPERT_4, LEGAL_EXPERT_5 | L6: 4.8 | M6: 4.3 | N6: 4.6 | P6: 2026.05.24 | Q6: 4.7 | R6: 4.4 | S6: 4.6 | U6: 46168 | V6: 4.6 | W6: 4.4 | X6: 4.7 | Z6: 46168 | AA6: 4.6 | AB6: 4.7 | AC6: 4.5 | AE6: 46170 | AF6: 4.7 | AG6: 4.6 | AH6: 4.7 | AJ6: 2026.05.28 | AK6: =AVERAGE(L6,Q6,V6,AA6,AF6) -> 4.68 | AL6: =AVERAGE(M6,R6,W6,AB6,AG6) -> 4.48 | AM6: =AVERAGE(N6,S6,X6,AC6,AH6) -> 4.62
A7: QAC_004 | B7: Factual | C7: Easy | D7: Administrative | E7: What is the right to freedom of thought, conscience and religion under the Constitution? | F7: Article 10 of the Constitution guarantees that every person is entitled to freedom of thought, conscience and religion, including the freedom to have or to adopt a religion or belief of his choice. | G7: Article 10 | H7: Art. 10: Every person is entitled to freedom of thought, thought, conscience and religion, including the freedom to have or conscience and religion to adopt a religion or belief of his choice. Freedom | I7: Human Annotated | J7: =MAX(P7,U7,Z7,AE7,AJ7) -> 46170 | K7: LEGAL_EXPERT_1, LEGAL_EXPERT_2, LEGAL_EXPERT_3, LEGAL_EXPERT_4, LEGAL_EXPERT_5 | L7: 4.8 | M7: 4.3 | N7: 4.6 | P7: 2026.05.24 | Q7: 4.8 | R7: 4.5 | S7: 4.5 | U7: 46168 | V7: 4.7 | W7: 4.4 | X7: 4.5 | Z7: 46168 | AA7: 4.9 | AB7: 4.8 | AC7: 4.7 | AE7: 46170 | AF7: 4.7 | AG7: 4.6 | AH7: 4.7 | AJ7: 2026.05.28 | AK7: =AVERAGE(L7,Q7,V7,AA7,AF7) -> 4.78 | AL7: =AVERAGE(M7,R7,W7,AB7,AG7) -> 4.52 | AM7: =AVERAGE(N7,S7,X7,AC7,AH7) -> 4.6
A8: QAC_005 | B8: Factual | C8: Easy | D8: Administrative | E8: What does the Constitution say about protection from torture and cruel treatment? | F8: Article 11 of the Constitution provides that no person shall be subjected to torture or to cruel, inhuman or degrading treatment or punishment. This is an absolute protection with no exceptions or qualifications. | G8: Article 11 | H8: Art. 11: No person shall be subjected to torture or to from torture cruel, inhuman or degrading treatment or punishment. Right to | I8: Human Annotated | J8: =MAX(P8,U8,Z8,AE8,AJ8) -> 46170 | K8: LEGAL_EXPERT_1, LEGAL_EXPERT_2, LEGAL_EXPERT_3, LEGAL_EXPERT_4, LEGAL_EXPERT_5 | L8: 4.8 | M8: 4.3 | N8: 4.6 | P8: 2026.05.24 | Q8: 4.7 | R8: 4.3 | S8: 4.6 | U8: 46168 | V8: 4.6 | W8: 4.4 | X8: 4.7 | Z8: 46168 | AA8: 4.5 | AB8: 4.4 | AC8: 4.8 | AE8: 46170 | AF8: 4.7 | AG8: 4.6 | AH8: 4.7 | AJ8: 2026.05.28 | AK8: =AVERAGE(L8,Q8,V8,AA8,AF8) -> 4.66 | AL8: =AVERAGE(M8,R8,W8,AB8,AG8) -> 4.4 | AM8: =AVERAGE(N8,S8,X8,AC8,AH8) -> 4.68
A9: QAC_006 | B9: Factual | C9: Medium | D9: Administrative | E9: What is the right to equality before the law in Sri Lanka? | F9: Article 12 of the Constitution provides that all persons are equal before the law and are entitled to the equal protection of the law. Under Article 12(2), no citizen shall be discriminated against on the grounds of race, religion, language, caste, sex, political opinion, place of birth or any one of such grounds. Article 12(3) further provides that no person shall, on such grounds, be subject to any disability, liability, restriction or condition with regard to access to shops, public restaurants, hotels, places of public entertainment and places of public worship of his own religion. | G9: Article 12, Article 12, Article 12 | H9: Art. 12: (1) All persons are equal before the law and are equality entitled to the equal protection of the law. (2) No citizen shall be discriminated against on the grounds of race, religion, language, caste, || Art. 12: (1) All persons are equal before the law and are equality entitled to the equal protection of the law. (2) No citizen shall be discriminated against on the grounds of race, religion, language, caste, || Art. 12: (1) All persons are equal before the law and are equality entitled to the equal protection of the law. (2) No citizen shall be discriminated against on the grounds of race, religion, language, caste, | I9: Human Annotated | J9: =MAX(P9,U9,Z9,AE9,AJ9) -> 46170 | K9: LEGAL_EXPERT_1, LEGAL_EXPERT_2, LEGAL_EXPERT_3, LEGAL_EXPERT_4, LEGAL_EXPERT_5 | L9: 4.8 | M9: 4.3 | N9: 4.6 | P9: 2026.05.24 | Q9: 4.8 | R9: 4.3 | S9: 4.6 | U9: 46168 | V9: 4.8 | W9: 4.4 | X9: 4.5 | Z9: 46168 | AA9: 4.7 | AB9: 4.5 | AC9: 4.5 | AE9: 46170 | AF9: 4.7 | AG9: 4.6 | AH9: 4.7 | AJ9: 2026.05.28 | AK9: =AVERAGE(L9,Q9,V9,AA9,AF9) -> 4.76 | AL9: =AVERAGE(M9,R9,W9,AB9,AG9) -> 4.42 | AM9: =AVERAGE(N9,S9,X9,AC9,AH9) -> 4.58
A10: QAC_007 | B10: Factual | C10: Medium | D10: Criminal | E10: What constitutional rights apply to a person who is arrested or detained? | F10: Article 13 of the Constitution provides that every person held in custody, detained or otherwise deprived of personal liberty shall be brought before the judge of the nearest competent court according to procedure established by law, and shall not be further held in custody, detained or deprived of personal liberty except upon and in terms of the order of such judge. Article 13(5) also establishes the presumption of innocence: every person shall be presumed innocent until proved guilty. | G10: Article 13, Article 13 | H10: Art. 13: (1) No person shall be arrested except according Freedom from to procedure established by law. Any person arrested shall arbitrary arrest, be informed of the reason for his arrest. detention and punis || Art. 13: (1) No person shall be arrested except according Freedom from to procedure established by law. Any person arrested shall arbitrary arrest, be informed of the reason for his arrest. detention and punis | I10: Human Annotated | J10: =MAX(P10,U10,Z10,AE10,AJ10) -> 46170 | K10: LEGAL_EXPERT_1, LEGAL_EXPERT_2, LEGAL_EXPERT_3, LEGAL_EXPERT_4, LEGAL_EXPERT_5 | L10: 4.8 | M10: 4.3 | N10: 4.6 | P10: 2026.05.24 | Q10: 4.9 | R10: 4.4 | S10: 4.6 | U10: 46168 | V10: 4.9 | W10: 4.7 | X10: 4.6 | Z10: 46168 | AA10: 4.7 | AB10: 4.7 | AC10: 4.7 | AE10: 46170 | AF10: 4.7 | AG10: 4.6 | AH10: 4.7 | AJ10: 2026.05.28 | AK10: =AVERAGE(L10,Q10,V10,AA10,AF10) -> 4.8 | AL10: =AVERAGE(M10,R10,W10,AB10,AG10) -> 4.54 | AM10: =AVERAGE(N10,S10,X10,AC10,AH10) -> 4.64
A11: QAC_008 | B11: Factual | C11: Medium | D11: Administrative | E11: What freedoms are protected under Article 14 of the Constitution? | F11: Article 14 of the Constitution protects several fundamental freedoms including: (b) the freedom of peaceful assembly; (c) the freedom of association; (d) the freedom to form and join a trade union; (e) the freedom, either by himself or in association with others, and either in public or in private, to manifest his religion or belief in worship, observance, practice and teaching; and (f) the freedom by himself or in association with others to enjoy and promote his own culture and to use his own language. | G11: Article 14 | H11: Art. 14: (1) Every citizen is entitled to speech, assembly, (a) the freedom of speech and expression association, including publication; occupation, movement, & c. (b) the freedom of peaceful assembly; (c) th | I11: Human Annotated | J11: =MAX(P11,U11,Z11,AE11,AJ11) -> 46170 | K11: LEGAL_EXPERT_1, LEGAL_EXPERT_2, LEGAL_EXPERT_3, LEGAL_EXPERT_4, LEGAL_EXPERT_5 | L11: 4.8 | M11: 4.3 | N11: 4.6 | P11: 2026.05.24 | Q11: 4.8 | R11: 4.4 | S11: 4.5 | U11: 46168 | V11: 4.8 | W11: 4.5 | X11: 4.6 | Z11: 46168 | AA11: 4.5 | AB11: 4.5 | AC11: 4.7 | AE11: 46170 | AF11: 4.7 | AG11: 4.6 | AH11: 4.7 | AJ11: 2026.05.28 | AK11: =AVERAGE(L11,Q11,V11,AA11,AF11) -> 4.72 | AL11: =AVERAGE(M11,R11,W11,AB11,AG11) -> 4.46 | AM11: =AVERAGE(N11,S11,X11,AC11,AH11) -> 4.62
A12: QAC_009 | B12: Procedural | C12: Medium | D12: Administrative | E12: How can a person enforce their fundamental rights in Sri Lanka? | F12: Under Article 17 of the Constitution, every person shall be entitled to apply to the Supreme Court, as provided by Article 126, in respect of the infringement or imminent infringement, by executive or administrative action, of a fundamental right to which such person is entitled under the provisions of Chapter III of the Constitution. | G12: Article 17 | H12: Art. 17: Every person shall be entitled to apply to the for the Supreme Court, as provided by Article 126, in respect of infringement of the infringement or imminent infringement, by executive fundamental righ | I12: Human Annotated | J12: =MAX(P12,U12,Z12,AE12,AJ12) -> 46170 | K12: LEGAL_EXPERT_1, LEGAL_EXPERT_2, LEGAL_EXPERT_3, LEGAL_EXPERT_4, LEGAL_EXPERT_5 | L12: 4.8 | M12: 4.3 | N12: 4.6 | P12: 2026.05.24 | Q12: 4.6 | R12: 4.3 | S12: 4.6 | U12: 46168 | V12: 4.5 | W12: 4.2 | X12: 4.5 | Z12: 46168 | AA12: 4.7 | AB12: 4.6 | AC12: 4.5 | AE12: 46170 | AF12: 4.7 | AG12: 4.6 | AH12: 4.7 | AJ12: 2026.05.28 | AK12: =AVERAGE(L12,Q12,V12,AA12,AF12) -> 4.66 | AL12: =AVERAGE(M12,R12,W12,AB12,AG12) -> 4.4 | AM12: =AVERAGE(N12,S12,X12,AC12,AH12) -> 4.58
A13: QAC_010 | B13: Factual | C13: Easy | D13: Administrative | E13: What are the National Languages of Sri Lanka under the Constitution? | F13: Article 19 of the Constitution provides that the National Languages of Sri Lanka shall be Sinhala and Tamil. Article 20 further provides that a Member of Parliament or a member of a Provincial Council or a Local Authority shall be entitled to perform his duties and discharge his functions in Parliament in either National Language. | G13: Article 19 | H13: Art. 19: The National Languages of Sri Lanka shall be National Languages Sinhala and Tamil. | I13: Human Annotated | J13: =MAX(P13,U13,Z13,AE13,AJ13) -> 46170 | K13: LEGAL_EXPERT_1, LEGAL_EXPERT_2, LEGAL_EXPERT_3, LEGAL_EXPERT_4, LEGAL_EXPERT_5 | L13: 4.8 | M13: 4.3 | N13: 4.6 | P13: 2026.05.24 | Q13: 4.7 | R13: 4.4 | S13: 4.6 | U13: 46168 | V13: 4.6 | W13: 4.5 | X13: 4.6 | Z13: 46168 | AA13: 4.5 | AB13: 4.5 | AC13: 4.5 | AE13: 46170 | AF13: 4.7 | AG13: 4.6 | AH13: 4.7 | AJ13: 2026.05.28 | AK13: =AVERAGE(L13,Q13,V13,AA13,AF13) -> 4.66 | AL13: =AVERAGE(M13,R13,W13,AB13,AG13) -> 4.46 | AM13: =AVERAGE(N13,S13,X13,AC13,AH13) -> 4.6
A14: QAC_011 | B14: Factual | C14: Medium | D14: Administrative | E14: What are the Directive Principles of State Policy and who are they binding on? | F14: Article 27(1) of the Constitution provides that the Directive Principles of State Policy shall guide Parliament, the President and the Cabinet of Ministers in the enactment of laws and the governance of Sri Lanka for the establishment of a just and free society. However, Article 29 makes clear that these provisions do not confer or impose legal rights or obligations and are not enforceable in any court or tribunal. | G14: Article 27, Article 29 | H14: Art. 27: (1) The Directive Principles of State Policy Directive Principles herein contained shall guide Parliament, the President of State and the Cabinet of Ministers in the enactment of laws and Policy the g || Art. 29: The provisions of this Chapter do not confer or Principles of State impose legal rights or obligations and are not enforceable Policy and in any court or tribunal. No question of inconsistency fundame | I14: Human Annotated | J14: =MAX(P14,U14,Z14,AE14,AJ14) -> 46170 | K14: LEGAL_EXPERT_1, LEGAL_EXPERT_2, LEGAL_EXPERT_3, LEGAL_EXPERT_4, LEGAL_EXPERT_5 | L14: 4.8 | M14: 4.3 | N14: 4.6 | P14: 2026.05.24 | Q14: 4.7 | R14: 4.4 | S14: 4.6 | U14: 46168 | V14: 4.5 | W14: 4.4 | X14: 4.6 | Z14: 46168 | AA14: 4.4 | AB14: 4.6 | AC14: 4.6 | AE14: 46170 | AF14: 4.7 | AG14: 4.6 | AH14: 4.7 | AJ14: 2026.05.28 | AK14: =AVERAGE(L14,Q14,V14,AA14,AF14) -> 4.62 | AL14: =AVERAGE(M14,R14,W14,AB14,AG14) -> 4.46 | AM14: =AVERAGE(N14,S14,X14,AC14,AH14) -> 4.62
A15: QAC_012 | B15: Factual | C15: Medium | D15: Administrative | E15: What does the Constitution say about the State's obligation to establish a democratic socialist society? | F15: Article 27(2) of the Constitution provides that the State is pledged to establish in Sri Lanka a Democratic Socialist Society, the objectives of which include: (a) the full realization of the fundamental rights and freedoms of all persons; (b) the promotion of the welfare of the People by securing and protecting as effectively as may be a social order in which justice (social, economic and political) shall guide all the institutions of the national life. | G15: Article 27 | H15: Art. 27: (2) The State is pledged to establish in Sri Lanka a Democratic Socialist Society, the objectives of which include (a) the full realization of the fundamental rights and freedoms of all persons; (b) | I15: Human Annotated | J15: =MAX(P15,U15,Z15,AE15,AJ15) -> 46170 | K15: LEGAL_EXPERT_1, LEGAL_EXPERT_2, LEGAL_EXPERT_3, LEGAL_EXPERT_4, LEGAL_EXPERT_5 | L15: 4.8 | M15: 4.3 | N15: 4.6 | P15: 2026.05.24 | Q15: 4.7 | R15: 4.4 | S15: 4.6 | U15: 46168 | V15: 4.6 | W15: 4.5 | X15: 4.7 | Z15: 46168 | AA15: 4.7 | AB15: 4.6 | AC15: 4.5 | AE15: 46170 | AF15: 4.7 | AG15: 4.6 | AH15: 4.7 | AJ15: 2026.05.28 | AK15: =AVERAGE(L15,Q15,V15,AA15,AF15) -> 4.7 | AL15: =AVERAGE(M15,R15,W15,AB15,AG15) -> 4.48 | AM15: =AVERAGE(N15,S15,X15,AC15,AH15) -> 4.62
... A18: QAC_015 | B18: Factual | C18: Medium | D18: Administrative | E18: What constitutional obligations does Sri Lanka have regarding environmental protection? | F18: Article 27(14) of the Constitution provides that the State shall protect, preserve and improve the environment for the benefit of the community. This is a directive principle of state policy under Chapter VI of the Constitution, meaning it guides legislation and governance but is not directly enforceable in courts under Article 29. | G18: Article 27, Article 29 | H18: Art. 27: (11) The State shall create the necessary economic and social environment to enable people of all religious faiths to make a reality of their religious principles. (12) The State shall recognize and p || Art. 29: The provisions of this Chapter do not confer or Principles of State impose legal rights or obligations and are not enforceable Policy and in any court or tribunal. No question of inconsistency fundame | I18: Human Annotated | J18: =MAX(P18,U18,Z18,AE18,AJ18) -> 46170 | K18: LEGAL_EXPERT_1, LEGAL_EXPERT_2, LEGAL_EXPERT_3, LEGAL_EXPERT_4, LEGAL_EXPERT_5 | L18: 4.8 | M18: 4.3 | N18: 4.6 | P18: 2026.05.24 | Q18: 4.7 | R18: 4.4 | S18: 4.5 | U18: 46168 | V18: 4.5 | W18: 4.4 | X18: 4.5 | Z18: 46168 | AA18: 4.4 | AB18: 4.5 | AC18: 4.4 | AE18: 46170 | AF18: 4.7 | AG18: 4.6 | AH18: 4.7 | AJ18: 2026.05.28 | AK18: =AVERAGE(L18,Q18,V18,AA18,AF18) -> 4.62 | AL18: =AVERAGE(M18,R18,W18,AB18,AG18) -> 4.44 | AM18: =AVERAGE(N18,S18,X18,AC18,AH18) -> 4.54
A19: QAC_016 | B19: Factual | C19: Medium | D19: Administrative | E19: What does the Constitution say about Sri Lanka's obligations regarding international peace and cooperation? | F19: Article 27(15) of the Constitution states that the State shall promote international peace, security and co-operation, and the establishment of a just and equitable international economic and social order and shall endeavour to foster respect for international law and treaty obligations in dealings among nations. | G19: Article 27 | H19: Art. 27: (11) The State shall create the necessary economic and social environment to enable people of all religious faiths to make a reality of their religious principles. (12) The State shall recognize and p | I19: Human Annotated | J19: =MAX(P19,U19,Z19,AE19,AJ19) -> 46170 | K19: LEGAL_EXPERT_1, LEGAL_EXPERT_2, LEGAL_EXPERT_3, LEGAL_EXPERT_4, LEGAL_EXPERT_5 | L19: 4.8 | M19: 4.3 | N19: 4.6 | P19: 2026.05.24 | Q19: 4.7 | R19: 4.3 | S19: 4.6 | U19: 46168 | V19: .4.7 | W19: 4.3 | X19: 4.6 | Z19: 46168 | AA19: 4.8 | AB19: 4.5 | AC19: 4.5 | AE19: 46170 | AF19: 4.7 | AG19: 4.6 | AH19: 4.7 | AJ19: 2026.05.28 | AK19: =AVERAGE(L19,Q19,V19,AA19,AF19) -> 4.75 | AL19: =AVERAGE(M19,R19,W19,AB19,AG19) -> 4.4 | AM19: =AVERAGE(N19,S19,X19,AC19,AH19) -> 4.6
A20: QAC_017 | B20: Factual | C20: Medium | D20: Administrative | E20: What are the fundamental duties of citizens under the Constitution of Sri Lanka? | F20: Article 28 of the Constitution provides that the exercise and enjoyment of rights and freedoms are inseparable from the performance of duties and obligations. It is accordingly the duty of every person in Sri Lanka: (a) to uphold and defend the Constitution and the law; (b) to further the national interest and to foster national unity; (c) to work conscientiously in his chosen occupation. These fundamental duties apply alongside the fundamental rights guaranteed in Chapter III. | G20: Article 28, Article 28 | H20: Art. 28: The exercise and enjoyment of rights and Fundamental freedoms are inseparable from the performance of duties duties and obligations and accordingly it is the duty of every person in Sri Lanka (a) to || Art. 28: The exercise and enjoyment of rights and Fundamental freedoms are inseparable from the performance of duties duties and obligations and accordingly it is the duty of every person in Sri Lanka (a) to | I20: Human Annotated | J20: =MAX(P20,U20,Z20,AE20,AJ20) -> 46170 | K20: LEGAL_EXPERT_1, LEGAL_EXPERT_2, LEGAL_EXPERT_3, LEGAL_EXPERT_4, LEGAL_EXPERT_5 | L20: 4.8 | M20: 4.3 | N20: 4.6 | P20: 2026.05.24 | Q20: 4.8 | R20: 4.4 | S20: 4.6 | U20: 46168 | V20: 4.8 | W20: 4.4 | X20: 4.6 | Z20: 46168 | AA20: 4.6 | AB20: 4.5 | AC20: 4.4 | AE20: 46170 | AF20: 4.7 | AG20: 4.6 | AH20: 4.7 | AJ20: 2026.05.28 | AK20: =AVERAGE(L20,Q20,V20,AA20,AF20) -> 4.74 | AL20: =AVERAGE(M20,R20,W20,AB20,AG20) -> 4.44 | AM20: =AVERAGE(N20,S20,X20,AC20,AH20) -> 4.58
A21: QAC_018 | B21: Interpretive | C21: Medium | D21: Administrative | E21: Are the Directive Principles of State Policy legally enforceable in court? | F21: No. Article 29 of the Constitution expressly provides that the provisions of Chapter VI (Directive Principles of State Policy and Fundamental Duties) do not confer or impose legal rights or obligations and are not enforceable in any court or tribunal. No question of inconsistency with such provisions shall be raised in any court or justiciable tribunal. The Directive Principles serve as guides for Parliament, the President and the Cabinet of Ministers in governance, but cannot be directly relied upon in litigation. | G21: Article 29 | H21: Art. 29: The provisions of this Chapter do not confer or Principles of State impose legal rights or obligations and are not enforceable Policy and in any court or tribunal. No question of inconsistency fundame | I21: Human Annotated | J21: =MAX(P21,U21,Z21,AE21,AJ21) -> 46170 | K21: LEGAL_EXPERT_1, LEGAL_EXPERT_2, LEGAL_EXPERT_3, LEGAL_EXPERT_4, LEGAL_EXPERT_5 | L21: 4.8 | M21: 4.3 | N21: 4.6 | P21: 2026.05.24 | Q21: 4.8 | R21: 4.4 | S21: 4.7 | U21: 46168 | V21: 4.7 | W21: 4.4 | X21: 4.7 | Z21: 46168 | AA21: 4.7 | AB21: 4.7 | AC21: 4.7 | AE21: 46170 | AF21: 4.7 | AG21: 4.6 | AH21: 4.7 | AJ21: 2026.05.28 | AK21: =AVERAGE(L21,Q21,V21,AA21,AF21) -> 4.74 | AL21: =AVERAGE(M21,R21,W21,AB21,AG21) -> 4.48 | AM21: =AVERAGE(N21,S21,X21,AC21,AH21) -> 4.68
A22: QAC_019 | B22: Factual | C22: Easy | D22: Criminal | E22: What is the presumption of innocence under Sri Lankan constitutional law? | F22: Article 13(5) of the Constitution provides that every person shall be presumed innocent until he is proved guilty. The burden of proving particular facts may, by law, be placed on an accused person, but this does not negate the general presumption of innocence. | G22: Article 13 | H22: Art. 13: (1) No person shall be arrested except according Freedom from to procedure established by law. Any person arrested shall arbitrary arrest, be informed of the reason for his arrest. detention and punis | I22: Human Annotated | J22: =MAX(P22,U22,Z22,AE22,AJ22) -> 46170 | K22: LEGAL_EXPERT_1, LEGAL_EXPERT_2, LEGAL_EXPERT_3, LEGAL_EXPERT_4, LEGAL_EXPERT_5 | L22: 4.8 | M22: 4.3 | N22: 4.6 | P22: 2026.05.24 | Q22: 4.7 | R22: 4.4 | S22: 4.6 | U22: 46168 | V22: 4.6 | W22: 4.5 | X22: 4.6 | Z22: 46168 | AA22: 4.5 | AB22: 4.4 | AC22: 4.5 | AE22: 46170 | AF22: 4.7 | AG22: 4.6 | AH22: 4.7 | AJ22: 2026.05.28 | AK22: =AVERAGE(L22,Q22,V22,AA22,AF22) -> 4.66 | AL22: =AVERAGE(M22,R22,W22,AB22,AG22) -> 4.44 | AM22: =AVERAGE(N22,S22,X22,AC22,AH22) -> 4.6
A23: QAC_020 | B23: Factual | C23: Easy | D23: Labor | E23: What does the Constitution say about the right to freedom of association and forming trade unions? | F23: Article 14 of the Constitution guarantees the freedom of association and the freedom to form and join a trade union. These rights are protected as fundamental rights under Chapter III of the Constitution. | G23: Article 14 | H23: Art. 14: (1) Every citizen is entitled to speech, assembly, (a) the freedom of speech and expression association, including publication; occupation, movement, & c. (b) the freedom of peaceful assembly; (c) th | I23: Human Annotated | J23: =MAX(P23,U23,Z23,AE23,AJ23) -> 46170 | K23: LEGAL_EXPERT_1, LEGAL_EXPERT_2, LEGAL_EXPERT_3, LEGAL_EXPERT_4, LEGAL_EXPERT_5 | L23: 4.8 | M23: 4.3 | N23: 4.6 | P23: 2026.05.24 | Q23: 4.7 | R23: 4.4 | S23: 4.6 | U23: 46168 | V23: 4.7 | W23: 4.3 | X23: 4.5 | Z23: 46168 | AA23: 4.4 | AB23: 4.3 | AC23: 4.3 | AE23: 46170 | AF23: 4.7 | AG23: 4.6 | AH23: 4.7 | AJ23: 2026.05.28 | AK23: =AVERAGE(L23,Q23,V23,AA23,AF23) -> 4.66 | AL23: =AVERAGE(M23,R23,W23,AB23,AG23) -> 4.38 | AM23: =AVERAGE(N23,S23,X23,AC23,AH23) -> 4.54
A24: QAC_021 | B24: Procedural | C24: Hard | D24: Administrative | E24: How is the Constitution of Sri Lanka amended? | F24: Article 82 of the Constitution provides that no Bill for the amendment of any provision of the Constitution shall be placed on the Order Paper of Parliament, unless the provision to be repealed, altered or added, and consequential amendments, if any, are expressly specified in the Bill and it is described in the long title thereof as being an Act for the amendment of the Constitution. | G24: Article 82 | H24: Art. 82: (1) No Bill for the amendment of any provision Amendment or of the Constitution shall be placed on the Order Paper of repeal of the Constitution Parliament, unless the provision to be repealed, altere | I24: Human Annotated | J24: =MAX(P24,U24,Z24,AE24,AJ24) -> 46170 | K24: LEGAL_EXPERT_1, LEGAL_EXPERT_2, LEGAL_EXPERT_3, LEGAL_EXPERT_4, LEGAL_EXPERT_5 | L24: 4.8 | M24: 4.3 | N24: 4.6 | P24: 2026.05.24 | Q24: 4.8 | R24: 4.4 | S24: 4.6 | U24: 46168 | V24: 4.8 | W24: 4.3 | X24: 4.5 | Z24: 46168 | AA24: 4.5 | AB24: 4.5 | AC24: 4.5 | AE24: 46170 | AF24: 4.7 | AG24: 4.6 | AH24: 4.7 | AJ24: 2026.05.28 | AK24: =AVERAGE(L24,Q24,V24,AA24,AF24) -> 4.72 | AL24: =AVERAGE(M24,R24,W24,AB24,AG24) -> 4.42 | AM24: =AVERAGE(N24,S24,X24,AC24,AH24) -> 4.58
A25: QAC_022 | B25: Factual | C25: Easy | D25: Administrative | E25: What is the National Day and National Anthem of Sri Lanka under the Constitution? | F25: Article 8 of the Constitution provides that the National Day of the Republic of Sri Lanka shall be the fourth day of February. Article 7 provides that the National Anthem of the Republic of Sri Lanka shall be Sri Lanka Matha, the words and music of which are set out in the Third Schedule to the Constitution. | G25: Article 8, Article 7 | H25: Art. 8: The National Day of the Republic of Sri Lanka Day shall be the fourth day of February 1 - Substituted by the Seventh Amendment to the Constitution Sec. 2(a). 2 - Substituted by the Seventh Amendment t || Art. 7: The National Anthem of the Republic of Sri Anthem Lanka shall be Sri Lanka Matha, the words and music of which are set out in the Third Schedule. The National | I25: Human Annotated | J25: =MAX(P25,U25,Z25,AE25,AJ25) -> 46170 | K25: LEGAL_EXPERT_1, LEGAL_EXPERT_2, LEGAL_EXPERT_3, LEGAL_EXPERT_4, LEGAL_EXPERT_5 | L25: 4.8 | M25: 4.3 | N25: 4.6 | P25: 2026.05.24 | Q25: 4.8 | R25: 4.4 | S25: 4.6 | U25: 46168 | V25: 4.8 | W25: 4.4 | X25: 4.6 | Z25: 46168 | AA25: 4.6 | AB25: 4.6 | AC25: 4.7 | AE25: 46170 | AF25: 4.7 | AG25: 4.6 | AH25: 4.7 | AJ25: 2026.05.28 | AK25: =AVERAGE(L25,Q25,V25,AA25,AF25) -> 4.74 | AL25: =AVERAGE(M25,R25,W25,AB25,AG25) -> 4.46 | AM25: =AVERAGE(N25,S25,X25,AC25,AH25) -> 4.64
A26: QAC_023 | B26: Cross_referenced | C26: Hard | D26: Administrative | E26: How does Article 9 on Buddhism relate to the right to freedom of religion under Article 10? | F26: Article 9 gives Buddhism the foremost place and imposes a duty on the State to protect and foster the Buddha Sasana. However, Article 9 itself qualifies this by stating it is done 'while assuring to all religions the rights granted by Articles 10 and 14(1)(e)'. Article 10 guarantees every person freedom of thought, conscience and religion, including the freedom to have or adopt a religion of their choice. Therefore, the constitutional primacy of Buddhism under Article 9 does not override the individual right to freedom of religion guaranteed under Article 10. | G26: Article 9, Article 10 | H26: Art. 9: The Republic of Sri Lanka shall give to Buddhism Buddhism the foremost place and accordingly it shall be the duty of the State to protect and foster the Buddha Sasana, while assuring to all religions || Art. 10: Every person is entitled to freedom of thought, thought, conscience and religion, including the freedom to have or conscience and religion to adopt a religion or belief of his choice. Freedom | I26: Human Annotated | J26: =MAX(P26,U26,Z26,AE26,AJ26) -> 46170 | K26: LEGAL_EXPERT_1, LEGAL_EXPERT_2, LEGAL_EXPERT_3, LEGAL_EXPERT_4, LEGAL_EXPERT_5 | L26: 4.8 | M26: 4.3 | N26: 4.6 | P26: 2026.05.24 | Q26: 4.8 | R26: 4.4 | S26: 4.6 | U26: 46168 | V26: 4.7 | W26: 4.4 | X26: 4.6 | Z26: 46168 | AA26: 4.5 | AB26: 4.6 | AC26: 4.6 | AE26: 46170 | AF26: 4.7 | AG26: 4.6 | AH26: 4.7 | AJ26: 2026.05.28 | AK26: =AVERAGE(L26,Q26,V26,AA26,AF26) -> 4.7 | AL26: =AVERAGE(M26,R26,W26,AB26,AG26) -> 4.46 | AM26: =AVERAGE(N26,S26,X26,AC26,AH26) -> 4.62
A27: QAC_024 | B27: Interpretive | C27: Hard | D27: Administrative | E27: Do the fundamental duties under Article 28 limit the exercise of fundamental rights? | F27: Article 28 of the Constitution provides that the exercise and enjoyment of rights and freedoms are inseparable from the performance of duties and obligations. The duties listed include upholding the Constitution and law, furthering national interest, and working conscientiously. However, Article 29 makes clear that the provisions of Chapter VI (which includes Article 28) do not confer or impose legally enforceable rights or obligations. Therefore, while Article 28 links rights and duties conceptually, it does not operate as a legal restriction that courts can use to limit the exercise of fundamental rights guaranteed in Chapter III. | G27: Article 28, Article 29 | H27: Art. 28: The exercise and enjoyment of rights and Fundamental freedoms are inseparable from the performance of duties duties and obligations and accordingly it is the duty of every person in Sri Lanka (a) to || Art. 29: The provisions of this Chapter do not confer or Principles of State impose legal rights or obligations and are not enforceable Policy and in any court or tribunal. No question of inconsistency fundame | I27: Human Annotated | J27: =MAX(P27,U27,Z27,AE27,AJ27) -> 46170 | K27: LEGAL_EXPERT_1, LEGAL_EXPERT_2, LEGAL_EXPERT_3, LEGAL_EXPERT_4, LEGAL_EXPERT_5 | L27: 4.8 | M27: 4.3 | N27: 4.6 | P27: 2026.05.24 | Q27: 4.8 | R27: 4.4 | S27: 4.6 | U27: 46168 | V27: 4.7 | W27: 4.4 | X27: 4.6 | Z27: 46168 | AA27: 4.5 | AB27: 4.5 | AC27: 4.5 | AE27: 46170 | AF27: 4.7 | AG27: 4.6 | AH27: 4.7 | AJ27: 2026.05.28 | AK27: =AVERAGE(L27,Q27,V27,AA27,AF27) -> 4.7 | AL27: =AVERAGE(M27,R27,W27,AB27,AG27) -> 4.44 | AM27: =AVERAGE(N27,S27,X27,AC27,AH27) -> 4.6
A28: QAC_025 | B28: Factual | C28: Medium | D28: Criminal | E28: Does the Constitution protect against retrospective criminal penalties? | F28: Yes. Article 13(6) of the Constitution provides that no person shall be held guilty of an offence on account of any act or omission which did not, at the time of such act or omission, constitute such an offence, and no penalty shall be imposed for any offence more severe than the penalty applicable at the time the offence was committed. This prohibition on retrospective penal legislation is a fundamental right under Chapter III. | G28: Article 13 | H28: Art. 13: (1) No person shall be arrested except according Freedom from to procedure established by law. Any person arrested shall arbitrary arrest, be informed of the reason for his arrest. detention and punis | I28: Human Annotated | J28: =MAX(P28,U28,Z28,AE28,AJ28) -> 46170 | K28: LEGAL_EXPERT_1, LEGAL_EXPERT_2, LEGAL_EXPERT_3, LEGAL_EXPERT_4, LEGAL_EXPERT_5 | L28: 4.8 | M28: 4.3 | N28: 4.6 | P28: 2026.05.24 | Q28: 4.8 | R28: 4.4 | S28: 4.6 | U28: 46168 | V28: 4.7 | W28: 4.3 | X28: 4.6 | Z28: 46168 | AA28: 4.7 | AB28: 4.5 | AC28: 4.7 | AE28: 46170 | AF28: 4.7 | AG28: 4.6 | AH28: 4.7 | AJ28: 2026.05.28 | AK28: =AVERAGE(L28,Q28,V28,AA28,AF28) -> 4.74 | AL28: =AVERAGE(M28,R28,W28,AB28,AG28) -> 4.42 | AM28: =AVERAGE(N28,S28,X28,AC28,AH28) -> 4.64
A29: QAC_026 | B29: Factual | C29: Medium | D29: Administrative | E29: What does the Constitution say about Sri Lanka's obligation to ensure social security? | F29: Article 27(9) of the Constitution provides that the State shall ensure social security and welfare. Article 27(2) further pledges the State to promote the welfare of the People by securing and protecting a social order in which justice shall guide all institutions of national life. These are Directive Principles of State Policy under Chapter VI, meaning they guide governance but are not directly enforceable in courts. | G29: Article 27, Article 27 | H29: Art. 27: (3) The State shall safeguard the independence, sovereignty, unity and the territorial integrity of Sri Lanka. (4) The State shall strengthen and broaden the democratic structure of government and the || Art. 27: (3) The State shall safeguard the independence, sovereignty, unity and the territorial integrity of Sri Lanka. (4) The State shall strengthen and broaden the democratic structure of government and the | I29: Human Annotated | J29: =MAX(P29,U29,Z29,AE29,AJ29) -> 46170 | K29: LEGAL_EXPERT_1, LEGAL_EXPERT_2, LEGAL_EXPERT_3, LEGAL_EXPERT_4, LEGAL_EXPERT_5 | L29: 4.8 | M29: 4.3 | N29: 4.6 | P29: 2026.05.24 | Q29: 4.8 | R29: 4.5 | S29: 4.5 | U29: 46168 | V29: 4.8 | W29: 4.5 | X29: 4.5 | Z29: 46168 | AA29: 4.4 | AB29: 4.5 | AC29: 4.6 | AE29: 46170 | AF29: 4.7 | AG29: 4.6 | AH29: 4.7 | AJ29: 2026.05.28 | AK29: =AVERAGE(L29,Q29,V29,AA29,AF29) -> 4.7 | AL29: =AVERAGE(M29,R29,W29,AB29,AG29) -> 4.48 | AM29: =AVERAGE(N29,S29,X29,AC29,AH29) -> 4.58
A30: QAC_027 | B30: Factual | C30: Easy | D30: Constitutional | E30: What is the national flag of Sri Lanka as defined by the Constitution? | F30: Article 6 of the Constitution establishes the National Flag of Sri Lanka as the Lion Flag. | G30: Article 6 | H30: Art. 6: The National Flag of the Republic of Sri Lanka Flag shall be the Lion Flag depicted in the Second Schedule. The National | I30: Human Annotated | J30: =MAX(P30,U30,Z30,AE30,AJ30) -> 46170 | K30: LEGAL_EXPERT_1, LEGAL_EXPERT_2, LEGAL_EXPERT_3, LEGAL_EXPERT_4, LEGAL_EXPERT_5 | L30: 4.8 | M30: 4.3 | N30: 4.6 | P30: 2026.05.24 | Q30: 4.7 | R30: 4.4 | S30: 4.6 | U30: 46168 | V30: 4.6 | W30: 4.3 | X30: 4.5 | Z30: 46168 | AA30: 4.5 | AB30: 4.5 | AC30: 4.5 | AE30: 46170 | AF30: 4.7 | AG30: 4.6 | AH30: 4.7 | AJ30: 2026.05.28 | AK30: =AVERAGE(L30,Q30,V30,AA30,AF30) -> 4.66 | AL30: =AVERAGE(M30,R30,W30,AB30,AG30) -> 4.42 | AM30: =AVERAGE(N30,S30,X30,AC30,AH30) -> 4.58
A31: QAC_028 | B31: Factual | C31: Easy | D31: Constitutional | E31: What is the national anthem of Sri Lanka under the Constitution? | F31: Article 7 of the Constitution declares that the National Anthem of the Republic of Sri Lanka shall be 'Sri Lanka Matha'. | G31: Article 7 | H31: Art. 7: The National Anthem of the Republic of Sri Anthem Lanka shall be Sri Lanka Matha, the words and music of which are set out in the Third Schedule. The National | I31: Human Annotated | J31: =MAX(P31,U31,Z31,AE31,AJ31) -> 46170 | K31: LEGAL_EXPERT_1, LEGAL_EXPERT_2, LEGAL_EXPERT_3, LEGAL_EXPERT_4, LEGAL_EXPERT_5 | L31: 4.8 | M31: 4.3 | N31: 4.6 | P31: 2026.05.24 | Q31: 4.8 | R31: 4.4 | S31: 4.5 | U31: 46168 | V31: 4.8 | W31: 4.4 | X31: 4.6 | Z31: 46168 | AA31: 4.7 | AB31: 4.6 | AC31: 4.7 | AE31: 46170 | AF31: 4.7 | AG31: 4.6 | AH31: 4.7 | AJ31: 2026.05.28 | AK31: =AVERAGE(L31,Q31,V31,AA31,AF31) -> 4.76 | AL31: =AVERAGE(M31,R31,W31,AB31,AG31) -> 4.46 | AM31: =AVERAGE(N31,S31,X31,AC31,AH31) -> 4.62
... A53: QAC_050 | B53: Procedural | C53: Hard | D53: Constitutional | E53: How is the Constitution amended and what special requirements apply to certain provisions? | F53: Article 82 provides the general procedure: a Bill for amendment requires a two-thirds majority of all members of Parliament. Article 83 lists entrenched provisions — including those relating to sovereignty, unitary status, Buddhism (Article 9), and fundamental rights (Articles 10-14) — which additionally require approval by the People at a Referendum after passing with a two-thirds majority in Parliament. | G53: Article 82 | H53: Art. 82: (1) No Bill for the amendment of any provision Amendment or of the Constitution shall be placed on the Order Paper of repeal of the Constitution Parliament, unless the provision to be repealed, altere | I53: Human Annotated | J53: =MAX(P53,U53,Z53,AE53,AJ53) -> 46170 | K53: LEGAL_EXPERT_1, LEGAL_EXPERT_2, LEGAL_EXPERT_3, LEGAL_EXPERT_4, LEGAL_EXPERT_5 | L53: 4.7 | M53: 4.5 | N53: 4.6 | P53: 2026.05.24 | Q53: 4.7 | R53: 4.4 | S53: 4.6 | U53: 46168 | V53: 4.7 | W53: 4.6 | X53: 4.6 | Z53: 46168 | AA53: 4.5 | AB53: 4.5 | AC53: 4.5 | AE53: 46170 | AF53: 4.7 | AG53: 4.6 | AH53: 4.7 | AJ53: 2026.05.28 | AK53: =AVERAGE(L53,Q53,V53,AA53,AF53) -> 4.66 | AL53: =AVERAGE(M53,R53,W53,AB53,AG53) -> 4.52 | AM53: =AVERAGE(N53,S53,X53,AC53,AH53) -> 4.6

Sheet 51-100
A1: Item ID | B1: Query Type | C1: Difficulty | D1: Legal Domain | E1: Question | F1: Reference Answer | G1: Constitutional Articles | H1: Supporting Passage(s) | I1: Annotattion Type | J1: Annotation Date | K1: Reviewer IDs | L1: Reviever 1: Chathuri Madushika (LLB ousl) | Q1: Reviever 2:Rohana Dasanayaka (LLB ousl) | V1: Reviever 3: Dulani Kulasooriya (LLB ousl) | AA1: Reviever 4: Dulshan Liyanaarachchi (LLB ousl) | AF1: Reviever 5: Inoshika Kodithuwakku (LLB ousl) | AK1: Mean | AL1: Mean | AM1: Mean
L2: Reviewer ID: LEGAL_EXPERT_1 | Q2: Reviewer ID: LEGAL_EXPERT_2 | V2: Reviewer ID: LEGAL_EXPERT_3 | AA2: Reviewer ID: LEGAL_EXPERT_4 | AF2: Reviewer ID: LEGAL_EXPERT_5 | AK2: Reviewer IDs: LEGAL_EXPERT_1, LEGAL_EXPERT_2, LEGAL_EXPERT_3, LEGAL_EXPERT_4, LEGAL_EXPERT_5
L3: Correctness (1=Poor 5=Excellent) | M3: Completeness (1=Poor 5=Excellent) | N3: Clarity (1=Poor 5=Excellent) | O3: Expert Comments | P3: Review Date | Q3: Correctness (1=Poor 5=Excellent) | R3: Completeness (1=Poor 5=Excellent) | S3: Clarity (1=Poor 5=Excellent) | T3: Expert Comments | U3: Review Date | V3: Correctness (1=Poor 5=Excellent) | W3: Completeness (1=Poor 5=Excellent) | X3: Clarity (1=Poor 5=Excellent) | Y3: Expert Comments | Z3: Review Date | AA3: Correctness (1=Poor 5=Excellent) | AB3: Completeness (1=Poor 5=Excellent) | AC3: Clarity (1=Poor 5=Excellent) | AD3: Expert Comments | AE3: Review Date | AF3: Correctness (1=Poor 5=Excellent) | AG3: Completeness (1=Poor 5=Excellent) | AH3: Clarity (1=Poor 5=Excellent) | AI3: Expert Comments | AJ3: Review Date | AK3: Correctness (1=Poor 5=Excellent) | AL3: Completeness (1=Poor 5=Excellent) | AM3: Clarity (1=Poor 5=Excellent)
A4: QAC_051 | B4: Factual | C4: Medium | D4: Constitutional | E4: What courts constitute the judicial system of Sri Lanka under the Constitution? | F4: Article 105 of the Constitution establishes the judicial system comprising: the Supreme Court of the Republic of Sri Lanka, the Court of Appeal, the High Court, and such other courts as Parliament may provide. The Supreme Court is the highest and final court. | G4: Article 105 | H4: Art. 105: (1) Subject to the provisions of the E s t a b lishment of Courts, & c. Constitution, the institutions for the administration of justice which protect, vindicate and enforce the rights of the People s | I4: Human Annotated | J4: =MAX(P4,U4,Z4,AE4,AJ4) -> 46170 | K4: LEGAL_EXPERT_1, LEGAL_EXPERT_2, LEGAL_EXPERT_3, LEGAL_EXPERT_4, LEGAL_EXPERT_5 | L4: 4.5 | M4: 4.3 | N4: 4.8 | P4: 2026.05.25 | Q4: 4.5 | R4: 4.3 | S4: 4.8 | U4: 2026.05.27 | V4: 4.7 | W4: 4.7 | X4: 4.6 | Z4: 46168 | AA4: 4.7 | AB4: 4.8 | AC4: 4.7 | AE4: 46170 | AF4: 4.7 | AG4: 4.8 | AH4: 4.7 | AJ4: 2026.05.28 | AK4: =AVERAGE(L4,Q4,V4,AA4,AF4) -> 4.62 | AL4: =AVERAGE(M4,R4,W4,AB4,AG4) -> 4.58 | AM4: =AVERAGE(N4,S4,X4,AC4,AH4) -> 4.72
A5: QAC_052 | B5: Factual | C5: Medium | D5: Constitutional | E5: What is the jurisdiction of the Supreme Court of Sri Lanka? | F5: Article 118 of the Constitution confers on the Supreme Court jurisdiction in respect of: constitutional matters; protection of fundamental rights; final appellate jurisdiction; consultative jurisdiction; jurisdiction in election petitions; jurisdiction in respect of breaches of Parliamentary privileges; and such other jurisdiction as Parliament may provide. | G5: Article 118 | H5: Art. 118: The Supreme Court of the Republic of Sri jurisdiction of Supreme Lanka shall be the highest and final superior Court of Court record in the Republic and shall subject to the provisions of the Constitu | I5: Human Annotated | J5: =MAX(P5,U5,Z5,AE5,AJ5) -> 46170 | K5: LEGAL_EXPERT_1, LEGAL_EXPERT_2, LEGAL_EXPERT_3, LEGAL_EXPERT_4, LEGAL_EXPERT_5 | L5: 4.5 | M5: 4.3 | N5: 4.8 | P5: 2026.05.25 | Q5: 4.5 | R5: 4.3 | S5: 4.7 | U5: 2026.05.27 | V5: 4.3 | W5: 4.4 | X5: 4.6 | Z5: 46168 | AA5: 4.4 | AB5: 4.5 | AC5: 4.6 | AE5: 46170 | AF5: 4.4 | AG5: 4.5 | AH5: 4.6 | AJ5: 2026.05.28 | AK5: =AVERAGE(L5,Q5,V5,AA5,AF5) -> 4.42 | AL5: =AVERAGE(M5,R5,W5,AB5,AG5) -> 4.4 | AM5: =AVERAGE(N5,S5,X5,AC5,AH5) -> 4.66
A6: QAC_053 | B6: Factual | C6: Medium | D6: Constitutional | E6: Who has exclusive jurisdiction to interpret the Constitution? | F6: Article 125 of the Constitution confers on the Supreme Court sole and exclusive jurisdiction to hear and determine any question relating to the interpretation of the Constitution. Any such question arising in the course of proceedings in any other court or tribunal shall be referred to the Supreme Court for determination. | G6: Article 125 | H6: Art. 125: (1) The Supreme Court shall have sole and Constitutional exclusive jurisdiction to hear and determine any question jurisdiction in the relating to the interpretation of the Constitution and interpreta | I6: Human Annotated | J6: =MAX(P6,U6,Z6,AE6,AJ6) -> 46170 | K6: LEGAL_EXPERT_1, LEGAL_EXPERT_2, LEGAL_EXPERT_3, LEGAL_EXPERT_4, LEGAL_EXPERT_5 | L6: 4.5 | M6: 4.3 | N6: 4.8 | P6: 2026.05.25 | Q6: 4.5 | R6: 4.2 | S6: 4.8 | U6: 2026.05.27 | V6: 4.6 | W6: 4.4 | X6: 4.7 | Z6: 46168 | AA6: 4.6 | AB6: 4.7 | AC6: 4.5 | AE6: 46170 | AF6: 4.6 | AG6: 4.7 | AH6: 4.5 | AJ6: 2026.05.28 | AK6: =AVERAGE(L6,Q6,V6,AA6,AF6) -> 4.56 | AL6: =AVERAGE(M6,R6,W6,AB6,AG6) -> 4.46 | AM6: =AVERAGE(N6,S6,X6,AC6,AH6) -> 4.66
A7: QAC_054 | B7: Procedural | C7: Hard | D7: Constitutional | E7: What is the process for enforcing fundamental rights in the Supreme Court? | F7: Article 126 of the Constitution provides that every person shall have the right to apply directly to the Supreme Court for relief or redress in respect of the infringement or imminent infringement of a fundamental right guaranteed by Chapter III. The Supreme Court shall have the power to grant such relief or make such directions as it deems appropriate. | G7: Article 126 | H7: Art. 126: (1) The Supreme Court shall have sole and rights exclusive jurisdiction to hear and determine any question jurisdiction and its relating to the infringement or imminent infringement by exercise execut | I7: Human Annotated | J7: =MAX(P7,U7,Z7,AE7,AJ7) -> 46170 | K7: LEGAL_EXPERT_1, LEGAL_EXPERT_2, LEGAL_EXPERT_3, LEGAL_EXPERT_4, LEGAL_EXPERT_5 | L7: 4.5 | M7: 4.3 | N7: 4.8 | P7: 2026.05.25 | Q7: 4.4 | R7: 4.3 | S7: 4.8 | U7: 2026.05.27 | V7: 4.7 | W7: 4.4 | X7: 4.5 | Z7: 46168 | AA7: 4.9 | AB7: 4.8 | AC7: 4.7 | AE7: 46170 | AF7: 4.7 | AG7: 4.8 | AH7: 4.7 | AJ7: 2026.05.28 | AK7: =AVERAGE(L7,Q7,V7,AA7,AF7) -> 4.64 | AL7: =AVERAGE(M7,R7,W7,AB7,AG7) -> 4.52 | AM7: =AVERAGE(N7,S7,X7,AC7,AH7) -> 4.7
A8: QAC_055 | B8: Factual | C8: Medium | D8: Constitutional | E8: What is the appellate jurisdiction of the Court of Appeal? | F8: Article 138 of the Constitution confers on the Court of Appeal appellate jurisdiction for the correction of errors in fact or law committed by all courts of first instance. The Court of Appeal may affirm, reverse or vary any judgment, decree, order or sentence of the court from which the appeal is taken. | G8: Article 138 | H8: Art. 138: Jurisdiction 138. (1) The Court of Appeal shall have and of the Court exercise subject to the provisions of the Constitution or of Appeal of any law, an appellate jurisdiction for the correction of al | I8: Human Annotated | J8: =MAX(P8,U8,Z8,AE8,AJ8) -> 46170 | K8: LEGAL_EXPERT_1, LEGAL_EXPERT_2, LEGAL_EXPERT_3, LEGAL_EXPERT_4, LEGAL_EXPERT_5 | L8: 4.5 | M8: 4.3 | N8: 4.8 | P8: 2026.05.25 | Q8: 4.5 | R8: 4.3 | S8: 4.8 | U8: 2026.05.27 | V8: 4.6 | W8: 4.4 | X8: 4.7 | Z8: 46168 | AA8: 4.5 | AB8: 4.4 | AC8: 4.8 | AE8: 46170 | AF8: 4.4 | AG8: 4.5 | AH8: 4.6 | AJ8: 2026.05.28 | AK8: =AVERAGE(L8,Q8,V8,AA8,AF8) -> 4.5 | AL8: =AVERAGE(M8,R8,W8,AB8,AG8) -> 4.38 | AM8: =AVERAGE(N8,S8,X8,AC8,AH8) -> 4.74
A9: QAC_056 | B9: Factual | C9: Medium | D9: Constitutional | E9: What is the Consolidated Fund and how are withdrawals controlled? | F9: Article 148 of the Constitution establishes Parliament's control over public finance: all revenues, grants and other moneys shall form the Consolidated Fund. Article 150 provides that no sum shall be withdrawn from the Consolidated Fund except under the authority of a warrant signed by the Minister of Finance, and only where Parliament has appropriated the sum for specified public services. | G9: Article 148 | H9: Art. 148: Parliament shall have full control over public Control of finance. No tax, rate or any other levy shall be imposed by Parliament over public any local authority or any other public authority, except f | I9: Human Annotated | J9: =MAX(P9,U9,Z9,AE9,AJ9) -> 46170 | K9: LEGAL_EXPERT_1, LEGAL_EXPERT_2, LEGAL_EXPERT_3, LEGAL_EXPERT_4, LEGAL_EXPERT_5 | L9: 4.5 | M9: 4.3 | N9: 4.8 | P9: 2026.05.25 | Q9: 4.5 | R9: 4.3 | S9: 4.7 | U9: 2026.05.27 | V9: 4.8 | W9: 4.4 | X9: 4.5 | Z9: 46168 | AA9: 4.7 | AB9: 4.5 | AC9: 4.5 | AE9: 46170 | AF9: 4.6 | AG9: 4.7 | AH9: 4.5 | AJ9: 2026.05.28 | AK9: =AVERAGE(L9,Q9,V9,AA9,AF9) -> 4.62 | AL9: =AVERAGE(M9,R9,W9,AB9,AG9) -> 4.44 | AM9: =AVERAGE(N9,S9,X9,AC9,AH9) -> 4.6
A10: QAC_057 | B10: Factual | C10: Medium | D10: Constitutional | E10: What is the Appropriation Bill and when must it be presented to Parliament? | F10: Under Article 152 of the Constitution, no Bill or motion authorizing the disposal of funds from the Consolidated Fund or the imposition, repeal, or reduction of any tax may be introduced in Parliament except by a Minister, and only if the Bill has been approved by the Cabinet of Ministers. The Appropriation Bill, which authorizes annual government expenditure, must accordingly be presented by the Minister in charge of Finance. Parliament must approve the Appropriation Bill before funds can be drawn from the Consolidated Fund under Articles 149 and 150. | G10: Article 152 | H10: Art. 152: No Bill or motion, authorizing the disposal of, or provisions the imposition of charges upon, the Consolidated Fund or a | I10: Human Annotated | J10: =MAX(P10,U10,Z10,AE10,AJ10) -> 46170 | K10: LEGAL_EXPERT_1, LEGAL_EXPERT_2, LEGAL_EXPERT_3, LEGAL_EXPERT_4, LEGAL_EXPERT_5 | L10: 4.5 | M10: 4.3 | N10: 4.8 | P10: 2026.05.25 | Q10: 4.5 | R10: 4.4 | S10: 4.8 | U10: 2026.05.27 | V10: 4.9 | W10: 4.7 | X10: 4.6 | Z10: 46168 | AA10: 4.7 | AB10: 4.7 | AC10: 4.7 | AE10: 46170 | AF10: 4.7 | AG10: 4.8 | AH10: 4.7 | AJ10: 2026.05.28 | AK10: =AVERAGE(L10,Q10,V10,AA10,AF10) -> 4.66 | AL10: =AVERAGE(M10,R10,W10,AB10,AG10) -> 4.58 | AM10: =AVERAGE(N10,S10,X10,AC10,AH10) -> 4.72
A11: QAC_058 | B11: Factual | C11: Medium | D11: Constitutional | E11: What is the role of the Auditor General under the Constitution? | F11: Article 154 of the Constitution requires the Auditor-General to audit the accounts of all departments of Government, the Office of the Secretary to the President, the Office of the Secretary to the Prime Minister, and all public corporations and local authorities. The Auditor-General is required to report to Parliament on the accounts audited. | G11: Article 154 | H11: Art. 153H: 154. [(1) The Auditor-General shall audit all Duties and departments of the Government, the Office of the Secretary to t | I11: Human Annotated | J11: =MAX(P11,U11,Z11,AE11,AJ11) -> 46170 | K11: LEGAL_EXPERT_1, LEGAL_EXPERT_2, LEGAL_EXPERT_3, LEGAL_EXPERT_4, LEGAL_EXPERT_5 | L11: 4.5 | M11: 4.3 | N11: 4.8 | P11: 2026.05.25 | Q11: 4.5 | R11: 4.3 | S11: 4.8 | U11: 2026.05.27 | V11: 4.8 | W11: 4.5 | X11: 4.6 | Z11: 46168 | AA11: 4.5 | AB11: 4.5 | AC11: 4.7 | AE11: 46170 | AF11: 4.4 | AG11: 4.5 | AH11: 4.6 | AJ11: 2026.05.28 | AK11: =AVERAGE(L11,Q11,V11,AA11,AF11) -> 4.54 | AL11: =AVERAGE(M11,R11,W11,AB11,AG11) -> 4.42 | AM11: =AVERAGE(N11,S11,X11,AC11,AH11) -> 4.7
A12: QAC_059 | B12: Procedural | C12: Hard | D12: Constitutional | E12: Under what circumstances may a state of emergency be declared? | F12: Article 155 of the Constitution provides that the President may by Proclamation declare a state of emergency when the President is of opinion that a public emergency exists. Emergency regulations made thereunder must be laid before Parliament and cease to be in force after 30 days unless Parliament approves them by resolution. | G12: Article 155 | H12: Art. 155: (1) The Public Security Ordinance as amended Public Security and in force immediately prior to the commencement of the Constitution shall be deemed to be a law enacted by Parliament. (2) The power to | I12: Human Annotated | J12: =MAX(P12,U12,Z12,AE12,AJ12) -> 46170 | K12: LEGAL_EXPERT_1, LEGAL_EXPERT_2, LEGAL_EXPERT_3, LEGAL_EXPERT_4, LEGAL_EXPERT_5 | L12: 4.5 | M12: 4.3 | N12: 4.8 | P12: 2026.05.25 | Q12: 4.6 | R12: 4.3 | S12: 4.8 | U12: 2026.05.27 | V12: 4.5 | W12: 4.2 | X12: 4.5 | Z12: 46168 | AA12: 4.7 | AB12: 4.6 | AC12: 4.5 | AE12: 46170 | AF12: 4.6 | AG12: 4.7 | AH12: 4.5 | AJ12: 2026.05.28 | AK12: =AVERAGE(L12,Q12,V12,AA12,AF12) -> 4.58 | AL12: =AVERAGE(M12,R12,W12,AB12,AG12) -> 4.42 | AM12: =AVERAGE(N12,S12,X12,AC12,AH12) -> 4.62
A13: QAC_060 | B13: Factual | C13: Hard | D13: Constitutional | E13: What is the Finance Commission and what is its role? | F13: Article 154R of the Constitution establishes the Finance Commission, which is responsible for making recommendations to the President regarding the allocation of funds from the Annual Budget to meet the needs of the Provinces and ensuring equitable distribution of financial resources among the Provinces. | G13: Article 154R | H13: Art. 154R: (1) There shall be a Finance Commission Commission consisting of (a) the Governor of the Central Bank of Sri Lanka; The Constitution of the Democratic Socialist Republic of Sri Lanka 177 (b) the Secr | I13: Human Annotated | J13: =MAX(P13,U13,Z13,AE13,AJ13) -> 46170 | K13: LEGAL_EXPERT_1, LEGAL_EXPERT_2, LEGAL_EXPERT_3, LEGAL_EXPERT_4, LEGAL_EXPERT_5 | L13: 4.5 | M13: 4.3 | N13: 4.8 | P13: 2026.05.25 | Q13: 4.5 | R13: 4.3 | S13: 4.8 | U13: 2026.05.27 | V13: 4.6 | W13: 4.5 | X13: 4.6 | Z13: 46168 | AA13: 4.5 | AB13: 4.5 | AC13: 4.5 | AE13: 46170 | AF13: 4.7 | AG13: 4.8 | AH13: 4.7 | AJ13: 2026.05.28 | AK13: =AVERAGE(L13,Q13,V13,AA13,AF13) -> 4.56 | AL13: =AVERAGE(M13,R13,W13,AB13,AG13) -> 4.48 | AM13: =AVERAGE(N13,S13,X13,AC13,AH13) -> 4.68
A14: QAC_061 | B14: Factual | C14: Medium | D14: Constitutional | E14: What are the qualifications to be registered as an elector? | F14: Article 88 provides that every person, unless disqualified as provided, shall be qualified to be an elector at the election of the President and Members of Parliament and to vote at any Referendum, provided that their name is entered in the appropriate register of electors. Article 89(b) further provides that no person shall be qualified to be an elector if they have not attained the age of eighteen years on the qualifying date specified by law. Article 88 thus sets the general entitlement and Article 89 sets the disqualifications, including the minimum voting age. | G14: Article 88, Article 89 | H14: Art. 88: Every person shall, unless disqualified as elector hereinafter provided, be qualified to be an elector at the election of the President and of the Members of Parliament or to vote at any Referendum: P || Art. 89: No person shall be qualified to be an elector to be an elector at an election of the President, or of the Members of Parliament or to vote at any Referendum, if he is subject to any of the following d | I14: Human Annotated | J14: =MAX(P14,U14,Z14,AE14,AJ14) -> 46170 | K14: LEGAL_EXPERT_1, LEGAL_EXPERT_2, LEGAL_EXPERT_3, LEGAL_EXPERT_4, LEGAL_EXPERT_5 | L14: 4.5 | M14: 4.3 | N14: 4.8 | P14: 2026.05.25 | Q14: 4.5 | R14: 4.3 | S14: 4.7 | U14: 2026.05.27 | V14: 4.5 | W14: 4.4 | X14: 4.6 | Z14: 46168 | AA14: 4.4 | AB14: 4.6 | AC14: 4.6 | AE14: 46170 | AF14: 4.4 | AG14: 4.5 | AH14: 4.6 | AJ14: 2026.05.28 | AK14: =AVERAGE(L14,Q14,V14,AA14,AF14) -> 4.46 | AL14: =AVERAGE(M14,R14,W14,AB14,AG14) -> 4.42 | AM14: =AVERAGE(N14,S14,X14,AC14,AH14) -> 4.66
A15: QAC_062 | B15: Factual | C15: Medium | D15: Constitutional | E15: What disqualifies a person from being elected as a Member of Parliament? | F15: Article 91 of the Constitution lists the disqualifications for membership of Parliament, including: being a citizen of another country, being an undischarged bankrupt, having been sentenced to imprisonment for two years or more, holding a disqualifying office of profit, and such other grounds as Parliament may provide. | G15: Article 91 | H15: Art. 91: (1) No person shall be qualified to be elected as a for election as Member of Parliament or to sit and vote in Parliament a Member of Parliament (a) if he is or becomes subject to any of the disquali | I15: Human Annotated | J15: =MAX(P15,U15,Z15,AE15,AJ15) -> 46170 | K15: LEGAL_EXPERT_1, LEGAL_EXPERT_2, LEGAL_EXPERT_3, LEGAL_EXPERT_4, LEGAL_EXPERT_5 | L15: 4.5 | M15: 4.3 | N15: 4.8 | P15: 2026.05.25 | Q15: 4.5 | R15: 4.3 | S15: 4.8 | U15: 2026.05.27 | V15: 4.6 | W15: 4.5 | X15: 4.7 | Z15: 46168 | AA15: 4.7 | AB15: 4.6 | AC15: 4.5 | AE15: 46170 | AF15: 4.6 | AG15: 4.7 | AH15: 4.5 | AJ15: 2026.05.28 | AK15: =AVERAGE(L15,Q15,V15,AA15,AF15) -> 4.58 | AL15: =AVERAGE(M15,R15,W15,AB15,AG15) -> 4.48 | AM15: =AVERAGE(N15,S15,X15,AC15,AH15) -> 4.66
... A18: QAC_065 | B18: Interpretive | C18: Hard | D18: Constitutional | E18: What are the directive principles of state policy in the Constitution? | F18: Article 27 of the Constitution sets out the Directive Principles of State Policy. These are not legally enforceable rights but are principles guiding legislation. They include: establishing a democratic socialist society; ensuring the right to work; equal rights for women; protection of the family; free education; and adequate standard of living. | G18: Article 27 | H18: Art. 27: (1) The Directive Principles of State Policy Directive Principles herein contained shall guide Parliament, the President of State and the Cabinet of Ministers in the enactment of laws and Policy the g | I18: Human Annotated | J18: =MAX(P18,U18,Z18,AE18,AJ18) -> 46170 | K18: LEGAL_EXPERT_1, LEGAL_EXPERT_2, LEGAL_EXPERT_3, LEGAL_EXPERT_4, LEGAL_EXPERT_5 | L18: 4.5 | M18: 4.3 | N18: 4.8 | P18: 2026.05.25 | Q18: 4.5 | R18: 4.3 | S18: 4.8 | U18: 2026.05.27 | V18: 4.5 | W18: 4.4 | X18: 4.5 | Z18: 46168 | AA18: 4.4 | AB18: 4.5 | AC18: 4.4 | AE18: 46170 | AF18: 4.6 | AG18: 4.7 | AH18: 4.5 | AJ18: 2026.05.28 | AK18: =AVERAGE(L18,Q18,V18,AA18,AF18) -> 4.5 | AL18: =AVERAGE(M18,R18,W18,AB18,AG18) -> 4.44 | AM18: =AVERAGE(N18,S18,X18,AC18,AH18) -> 4.6
A19: QAC_066 | B19: Interpretive | C19: Hard | D19: Constitutional | E19: What restrictions can be placed on fundamental rights under the Constitution? | F19: Article 15 of the Constitution permits restrictions on the exercise of fundamental rights. The rights guaranteed by Articles 13 and 14 may be restricted by law in the interests of: national security, public order, the protection of public health or morality, or for the purpose of securing due recognition of the rights and freedoms of others. | G19: Article 15 | H19: Art. 15: (1) The exercise and operation of the fundamental fundamental rights declared and recognized by Articles rights 13(5) and 13(6) shall be subject only to such restrictions as may be prescribed by law i | I19: Human Annotated | J19: =MAX(P19,U19,Z19,AE19,AJ19) -> 46170 | K19: LEGAL_EXPERT_1, LEGAL_EXPERT_2, LEGAL_EXPERT_3, LEGAL_EXPERT_4, LEGAL_EXPERT_5 | L19: 4.5 | M19: 4.3 | N19: 4.8 | P19: 2026.05.25 | Q19: 4.3 | R19: 4.4 | S19: 4.8 | U19: 2026.05.27 | V19: .4.7 | W19: 4.3 | X19: 4.6 | Z19: 46168 | AA19: 4.8 | AB19: 4.5 | AC19: 4.5 | AE19: 46170 | AF19: 4.7 | AG19: 4.8 | AH19: 4.7 | AJ19: 2026.05.28 | AK19: =AVERAGE(L19,Q19,V19,AA19,AF19) -> 4.575 | AL19: =AVERAGE(M19,R19,W19,AB19,AG19) -> 4.46 | AM19: =AVERAGE(N19,S19,X19,AC19,AH19) -> 4.68
A20: QAC_067 | B20: Interpretive | C20: Hard | D20: Constitutional | E20: Can Parliament delegate its legislative power to another body? | F20: Article 76(1) of the Constitution provides that Parliament shall not abdicate or in any manner alienate its legislative power, and shall not set up any authority with any legislative power. However, Parliament may delegate to subordinate bodies the power to make regulations, rules, by-laws and other subordinate legislation in accordance with law. | G20: Article 76 | H20: Art. 76: (1) Parliament shall not abdicate or in any legislative manner alienate its legislative power and shall not set up power any authority with any legislative power. (2) It shall not be a contravention o | I20: Human Annotated | J20: =MAX(P20,U20,Z20,AE20,AJ20) -> 46170 | K20: LEGAL_EXPERT_1, LEGAL_EXPERT_2, LEGAL_EXPERT_3, LEGAL_EXPERT_4, LEGAL_EXPERT_5 | L20: 4.5 | M20: 4.3 | N20: 4.8 | P20: 2026.05.25 | Q20: 4.5 | R20: 4.3 | S20: 4.8 | U20: 2026.05.27 | V20: 4.8 | W20: 4.4 | X20: 4.6 | Z20: 46168 | AA20: 4.6 | AB20: 4.5 | AC20: 4.4 | AE20: 46170 | AF20: 4.4 | AG20: 4.5 | AH20: 4.6 | AJ20: 2026.05.28 | AK20: =AVERAGE(L20,Q20,V20,AA20,AF20) -> 4.56 | AL20: =AVERAGE(M20,R20,W20,AB20,AG20) -> 4.4 | AM20: =AVERAGE(N20,S20,X20,AC20,AH20) -> 4.64
A21: QAC_068 | B21: Factual | C21: Easy | D21: Constitutional | E21: What freedom of movement rights does the Constitution guarantee? | F21: Article 14(1)(h) and (i) of the Constitution guarantee that every citizen is entitled to the freedom of movement and of choosing his residence within Sri Lanka, and the freedom to return to Sri Lanka. | G21: Article 14 | H21: Art. 14: (1) Every citizen is entitled to speech, assembly, (a) the freedom of speech and expression association, including publication; occupation, movement, & c. (b) the freedom of peaceful assembly; (c) th | I21: Human Annotated | J21: =MAX(P21,U21,Z21,AE21,AJ21) -> 46170 | K21: LEGAL_EXPERT_1, LEGAL_EXPERT_2, LEGAL_EXPERT_3, LEGAL_EXPERT_4, LEGAL_EXPERT_5 | L21: 4.5 | M21: 4.3 | N21: 4.8 | P21: 2026.05.25 | Q21: 4.4 | R21: 4.3 | S21: 4.8 | U21: 2026.05.27 | V21: 4.7 | W21: 4.4 | X21: 4.7 | Z21: 46168 | AA21: 4.7 | AB21: 4.7 | AC21: 4.7 | AE21: 46170 | AF21: 4.6 | AG21: 4.7 | AH21: 4.5 | AJ21: 2026.05.28 | AK21: =AVERAGE(L21,Q21,V21,AA21,AF21) -> 4.58 | AL21: =AVERAGE(M21,R21,W21,AB21,AG21) -> 4.48 | AM21: =AVERAGE(N21,S21,X21,AC21,AH21) -> 4.7
A22: QAC_069 | B22: Factual | C22: Easy | D22: Constitutional | E22: Does the Constitution guarantee the right to engage in any occupation? | F22: Article 14(1)(g) of the Constitution guarantees every citizen the freedom to engage in any lawful occupation, profession, trade, business or enterprise. | G22: Article 14 | H22: Art. 14: (1) Every citizen is entitled to speech, assembly, (a) the freedom of speech and expression association, including publication; occupation, movement, & c. (b) the freedom of peaceful assembly; (c) th | I22: Human Annotated | J22: =MAX(P22,U22,Z22,AE22,AJ22) -> 46170 | K22: LEGAL_EXPERT_1, LEGAL_EXPERT_2, LEGAL_EXPERT_3, LEGAL_EXPERT_4, LEGAL_EXPERT_5 | L22: 4.5 | M22: 4.3 | N22: 4.8 | P22: 2026.05.25 | Q22: 4.5 | R22: 4.3 | S22: 4.7 | U22: 2026.05.27 | V22: 4.6 | W22: 4.5 | X22: 4.6 | Z22: 46168 | AA22: 4.5 | AB22: 4.4 | AC22: 4.5 | AE22: 46170 | AF22: 4.7 | AG22: 4.8 | AH22: 4.7 | AJ22: 2026.05.28 | AK22: =AVERAGE(L22,Q22,V22,AA22,AF22) -> 4.56 | AL22: =AVERAGE(M22,R22,W22,AB22,AG22) -> 4.46 | AM22: =AVERAGE(N22,S22,X22,AC22,AH22) -> 4.66
A23: QAC_070 | B23: Factual | C23: Medium | D23: Constitutional | E23: What constitutional provisions govern taxation? | F23: Article 148 of the Constitution provides that no taxation shall be imposed by any authority other than Parliament. All taxes and revenues shall be paid into the Consolidated Fund and no expenditure shall be incurred except under the authority of Parliament. | G23: Article 148 | H23: Art. 148: Parliament shall have full control over public Control of finance. No tax, rate or any other levy shall be imposed by Parliament over public any local authority or any other public authority, except f | I23: Human Annotated | J23: =MAX(P23,U23,Z23,AE23,AJ23) -> 46170 | K23: LEGAL_EXPERT_1, LEGAL_EXPERT_2, LEGAL_EXPERT_3, LEGAL_EXPERT_4, LEGAL_EXPERT_5 | L23: 4.5 | M23: 4.3 | N23: 4.8 | P23: 2026.05.25 | Q23: 4.5 | R23: 4.3 | S23: 4.8 | U23: 2026.05.27 | V23: 4.7 | W23: 4.3 | X23: 4.5 | Z23: 46168 | AA23: 4.4 | AB23: 4.3 | AC23: 4.3 | AE23: 46170 | AF23: 4.4 | AG23: 4.5 | AH23: 4.6 | AJ23: 2026.05.28 | AK23: =AVERAGE(L23,Q23,V23,AA23,AF23) -> 4.5 | AL23: =AVERAGE(M23,R23,W23,AB23,AG23) -> 4.34 | AM23: =AVERAGE(N23,S23,X23,AC23,AH23) -> 4.6
A24: QAC_071 | B24: Factual | C24: Medium | D24: Constitutional | E24: What is the constitutional basis for the Attorney General's role? | F24: Article 61E provides that the President shall appoint the Attorney-General on the approval of the Constitutional Council. Article 134(1) provides that the Attorney-General shall be noticed and shall have the right to be heard in all proceedings in the Supreme Court in the exercise of its jurisdiction under Articles 120, 121, 122, 125, 126, and 129(1). These provisions establish the constitutional basis for the appointment of the Attorney-General and the right of audience before the Supreme Court. | G24: Article 61E, Article 134 | H24: Art. 61E: The President shall appoint - by the President (a) the Heads of the Army, the Navy and the Air Force; and (b) 46[on the approval at the Constitutional Council,] the Attorney-General and the Inspector- || Art. 134: (1) The Attorney-General shall be noticed and Right to be have the right to be heard in all proceedings in the heard by the Supreme Supreme Court in the exercise of its jurisdiction under Court Articl | I24: Human Annotated | J24: =MAX(P24,U24,Z24,AE24,AJ24) -> 46170 | K24: LEGAL_EXPERT_1, LEGAL_EXPERT_2, LEGAL_EXPERT_3, LEGAL_EXPERT_4, LEGAL_EXPERT_5 | L24: 4.5 | M24: 4.3 | N24: 4.8 | P24: 2026.05.25 | Q24: 4.6 | R24: 4.3 | S24: 4.8 | U24: 2026.05.27 | V24: 4.8 | W24: 4.3 | X24: 4.5 | Z24: 46168 | AA24: 4.5 | AB24: 4.5 | AC24: 4.5 | AE24: 46170 | AF24: 4.6 | AG24: 4.7 | AH24: 4.5 | AJ24: 2026.05.28 | AK24: =AVERAGE(L24,Q24,V24,AA24,AF24) -> 4.6 | AL24: =AVERAGE(M24,R24,W24,AB24,AG24) -> 4.42 | AM24: =AVERAGE(N24,S24,X24,AC24,AH24) -> 4.62
A25: QAC_072 | B25: Factual | C25: Hard | D25: Constitutional | E25: What is the Constitutional Council and what is its function? | F25: Article 41A of the Constitution establishes the Constitutional Council, which is responsible for making recommendations to the President on appointments to independent commissions and certain key constitutional offices. Its purpose is to ensure the independence of key institutions including the Elections Commission, Public Service Commission, and National Police Commission. | G25: Article 41A | H25: Art. 41A: (1) There shall be a Constitutional Council C onstitution of the (in this Chapter referred to as the Council) which shall Constitutional consist of the following members: Council (a) the Prime Ministe | I25: Human Annotated | J25: =MAX(P25,U25,Z25,AE25,AJ25) -> 46170 | K25: LEGAL_EXPERT_1, LEGAL_EXPERT_2, LEGAL_EXPERT_3, LEGAL_EXPERT_4, LEGAL_EXPERT_5 | L25: 4.5 | M25: 4.3 | N25: 4.8 | P25: 2026.05.25 | Q25: 4.5 | R25: 4.3 | S25: 4.8 | U25: 2026.05.27 | V25: 4.8 | W25: 4.4 | X25: 4.6 | Z25: 46168 | AA25: 4.6 | AB25: 4.6 | AC25: 4.7 | AE25: 46170 | AF25: 4.7 | AG25: 4.8 | AH25: 4.7 | AJ25: 2026.05.28 | AK25: =AVERAGE(L25,Q25,V25,AA25,AF25) -> 4.62 | AL25: =AVERAGE(M25,R25,W25,AB25,AG25) -> 4.48 | AM25: =AVERAGE(N25,S25,X25,AC25,AH25) -> 4.72
A26: QAC_073 | B26: Factual | C26: Easy | D26: Constitutional | E26: What does the Constitution say about the freedom of speech and expression? | F26: Article 14(1)(a) of the Constitution guarantees every citizen the freedom of speech and expression including publication. This right is subject to the restrictions prescribed by Article 15 in the interests of national security, public order, and protection of public health or morality. | G26: Article 14 | H26: Art. 14: (1) Every citizen is entitled to speech, assembly, (a) the freedom of speech and expression association, including publication; occupation, movement, & c. (b) the freedom of peaceful assembly; (c) th | I26: Human Annotated | J26: =MAX(P26,U26,Z26,AE26,AJ26) -> 46170 | K26: LEGAL_EXPERT_1, LEGAL_EXPERT_2, LEGAL_EXPERT_3, LEGAL_EXPERT_4, LEGAL_EXPERT_5 | L26: 4.5 | M26: 4.3 | N26: 4.8 | P26: 2026.05.25 | Q26: 4.5 | R26: 4.4 | S26: 4.8 | U26: 2026.05.27 | V26: 4.7 | W26: 4.4 | X26: 4.6 | Z26: 46168 | AA26: 4.5 | AB26: 4.6 | AC26: 4.6 | AE26: 46170 | AF26: 4.4 | AG26: 4.5 | AH26: 4.6 | AJ26: 2026.05.28 | AK26: =AVERAGE(L26,Q26,V26,AA26,AF26) -> 4.52 | AL26: =AVERAGE(M26,R26,W26,AB26,AG26) -> 4.44 | AM26: =AVERAGE(N26,S26,X26,AC26,AH26) -> 4.68
A27: QAC_074 | B27: Factual | C27: Easy | D27: Constitutional | E27: What territory comprises the Republic of Sri Lanka under the Constitution? | F27: Article 5 of the Constitution provides that the territory of the Republic of Sri Lanka consists of the twenty-five administrative districts, the names of which are set out in the First Schedule, together with its territorial waters. The administrative districts may be subdivided or amalgamated. | G27: Article 5 | H27: Art. 5: The territory of the Republic of Sri Lanka shall Territory of the Republic consist of the 1[twenty-five] administrative districts, the names of which are set out in the First Schedule and its 2[territ | I27: Human Annotated | J27: =MAX(P27,U27,Z27,AE27,AJ27) -> 46170 | K27: LEGAL_EXPERT_1, LEGAL_EXPERT_2, LEGAL_EXPERT_3, LEGAL_EXPERT_4, LEGAL_EXPERT_5 | L27: 4.5 | M27: 4.3 | N27: 4.8 | P27: 2026.05.25 | Q27: 4.5 | R27: 4.3 | S27: 4.8 | U27: 2026.05.27 | V27: 4.7 | W27: 4.4 | X27: 4.6 | Z27: 46168 | AA27: 4.5 | AB27: 4.5 | AC27: 4.5 | AE27: 46170 | AF27: 4.6 | AG27: 4.7 | AH27: 4.5 | AJ27: 2026.05.28 | AK27: =AVERAGE(L27,Q27,V27,AA27,AF27) -> 4.56 | AL27: =AVERAGE(M27,R27,W27,AB27,AG27) -> 4.44 | AM27: =AVERAGE(N27,S27,X27,AC27,AH27) -> 4.64
A28: QAC_075 | B28: Factual | C28: Medium | D28: Constitutional | E28: What is the right of access to information under the Constitution? | F28: Article 14A grants every citizen the right of access to any information as provided for by law, being information required for the exercise or protection of a citizen's right held by the State, a Ministry, any Government Department, or any statutory body established by law. | G28: Article 14A | H28: Art. 14A: (1) Every citizen shall have the right of Right of access to access to any information as provided for by law, being information information that is required for the exercise or protection of a citize | I28: Human Annotated | J28: =MAX(P28,U28,Z28,AE28,AJ28) -> 46170 | K28: LEGAL_EXPERT_1, LEGAL_EXPERT_2, LEGAL_EXPERT_3, LEGAL_EXPERT_4, LEGAL_EXPERT_5 | L28: 4.5 | M28: 4.3 | N28: 4.8 | P28: 2026.05.25 | Q28: 4.5 | R28: 4.5 | S28: 4.8 | U28: 2026.05.27 | V28: 4.7 | W28: 4.3 | X28: 4.6 | Z28: 46168 | AA28: 4.7 | AB28: 4.5 | AC28: 4.7 | AE28: 46170 | AF28: 4.7 | AG28: 4.8 | AH28: 4.7 | AJ28: 2026.05.28 | AK28: =AVERAGE(L28,Q28,V28,AA28,AF28) -> 4.62 | AL28: =AVERAGE(M28,R28,W28,AB28,AG28) -> 4.48 | AM28: =AVERAGE(N28,S28,X28,AC28,AH28) -> 4.72
A29: QAC_076 | B29: Interpretive | C29: Hard | D29: Constitutional | E29: How does the Constitution treat existing written and unwritten law in relation to fundamental rights? | F29: Article 16 provides that all existing written law and unwritten law shall remain valid and operative notwithstanding any inconsistency with the preceding provisions of Chapter III on Fundamental Rights. This means pre-existing law is preserved even where it may conflict with the fundamental rights provisions. | G29: Article 16 | H29: Art. 16: (1) All existing written law and unwritten written law law shall be valid and operative notwithstanding any and inconsistency with the preceding provisions of this unwritten law to Chapter. continue i | I29: Human Annotated | J29: =MAX(P29,U29,Z29,AE29,AJ29) -> 46170 | K29: LEGAL_EXPERT_1, LEGAL_EXPERT_2, LEGAL_EXPERT_3, LEGAL_EXPERT_4, LEGAL_EXPERT_5 | L29: 4.5 | M29: 4.3 | N29: 4.8 | P29: 2026.05.25 | Q29: 4.5 | R29: 4.3 | S29: 4.8 | U29: 2026.05.27 | V29: 4.8 | W29: 4.5 | X29: 4.5 | Z29: 46168 | AA29: 4.4 | AB29: 4.5 | AC29: 4.6 | AE29: 46170 | AF29: 4.4 | AG29: 4.5 | AH29: 4.6 | AJ29: 2026.05.28 | AK29: =AVERAGE(L29,Q29,V29,AA29,AF29) -> 4.52 | AL29: =AVERAGE(M29,R29,W29,AB29,AG29) -> 4.42 | AM29: =AVERAGE(N29,S29,X29,AC29,AH29) -> 4.66
A30: QAC_077 | B30: Factual | C30: Easy | D30: Constitutional | E30: What language may a person choose for their education in Sri Lanka? | F30: Article 21 of the Constitution provides that a person shall be entitled to be educated through the medium of either of the National Languages (Sinhala or Tamil). This right does not apply to institutions of higher education where the medium of instruction is a language other than a National Language. | G30: Article 21 | H30: Art. 21: (1) A person shall be entitled to be educated Medium of through the medium of either of the National Languages: instruction Provided that the provisions of this paragraph shall not apply to an institu | I30: Human Annotated | J30: =MAX(P30,U30,Z30,AE30,AJ30) -> 46170 | K30: LEGAL_EXPERT_1, LEGAL_EXPERT_2, LEGAL_EXPERT_3, LEGAL_EXPERT_4, LEGAL_EXPERT_5 | L30: 4.5 | M30: 4.3 | N30: 4.8 | P30: 2026.05.25 | Q30: 4.6 | R30: 4.3 | S30: 4.8 | U30: 2026.05.27 | V30: 4.6 | W30: 4.3 | X30: 4.5 | Z30: 46168 | AA30: 4.5 | AB30: 4.5 | AC30: 4.5 | AE30: 46170 | AF30: 4.6 | AG30: 4.7 | AH30: 4.5 | AJ30: 2026.05.28 | AK30: =AVERAGE(L30,Q30,V30,AA30,AF30) -> 4.56 | AL30: =AVERAGE(M30,R30,W30,AB30,AG30) -> 4.42 | AM30: =AVERAGE(N30,S30,X30,AC30,AH30) -> 4.62
A31: QAC_078 | B31: Factual | C31: Easy | D31: Constitutional | E31: What are the official languages of administration in Sri Lanka? | F31: Article 22 provides that Sinhala and Tamil shall be the languages of administration throughout Sri Lanka. Sinhala shall be the language of administration and be used for the maintenance of public records and the transaction of all business by public institutions of all Provinces of Sri Lanka, except the Northern and Eastern Provinces where Tamil shall be so used. | G31: Article 22 | H31: Art. 22: (1) Sinhala and Tamil shall be the languages 8[Languages of Administration of administration throughout Sri Lanka and Sinhala shall be the language of administration and be used for the maintenance of | I31: Human Annotated | J31: =MAX(P31,U31,Z31,AE31,AJ31) -> 46170 | K31: LEGAL_EXPERT_1, LEGAL_EXPERT_2, LEGAL_EXPERT_3, LEGAL_EXPERT_4, LEGAL_EXPERT_5 | L31: 4.5 | M31: 4.3 | N31: 4.8 | P31: 2026.05.25 | Q31: 4.5 | R31: 4.3 | S31: 4.7 | U31: 2026.05.27 | V31: 4.8 | W31: 4.4 | X31: 4.6 | Z31: 46168 | AA31: 4.7 | AB31: 4.6 | AC31: 4.7 | AE31: 46170 | AF31: 4.7 | AG31: 4.8 | AH31: 4.7 | AJ31: 2026.05.28 | AK31: =AVERAGE(L31,Q31,V31,AA31,AF31) -> 4.64 | AL31: =AVERAGE(M31,R31,W31,AB31,AG31) -> 4.48 | AM31: =AVERAGE(N31,S31,X31,AC31,AH31) -> 4.7
... A53: QAC_100 | B53: Factual | C53: Medium | D53: Constitutional | E53: What are the functions of the Secretary to the Prime Minister? | F53: Article 51 provides that there shall be a Secretary to the Prime Minister appointed by the President. The Secretary shall have charge of the office of the Prime Minister and shall perform and discharge the duties and functions of his office, subject to the directions of the Prime Minister. | G53: Article 51 | H53: Art. 51: (1) (a) There shall be a Secretary to the Prime the Prime Minister who shall be appointed by the President. Minister and Secretary to (b) The Secretary shall have charge of the the Cabinet of Minister | I53: Human Annotated | J53: =MAX(P53,U53,Z53,AE53,AJ53) -> 46170 | K53: LEGAL_EXPERT_1, LEGAL_EXPERT_2, LEGAL_EXPERT_3, LEGAL_EXPERT_4, LEGAL_EXPERT_5 | L53: 4.5 | M53: 4.3 | N53: 4.8 | P53: 2026.05.25 | Q53: 4.5 | R53: 4.3 | S53: 4.8 | U53: 2026.05.27 | V53: 4.7 | W53: 4.6 | X53: 4.6 | Z53: 46168 | AA53: 4.5 | AB53: 4.5 | AC53: 4.5 | AE53: 46170 | AF53: 4.6 | AG53: 4.7 | AH53: 4.8 | AJ53: 2026.05.28 | AK53: =AVERAGE(L53,Q53,V53,AA53,AF53) -> 4.56 | AL53: =AVERAGE(M53,R53,W53,AB53,AG53) -> 4.48 | AM53: =AVERAGE(N53,S53,X53,AC53,AH53) -> 4.7

Sheet 101-150
A1: Item ID | B1: Query Type | C1: Difficulty | D1: Legal Domain | E1: Question | F1: Reference Answer | G1: Constitutional Articles | H1: Supporting Passage(s) | I1: Annotattion Type | J1: Annotation Date | K1: Reviewer IDs | L1: Reviever 1: Chathuri Madushika (LLB ousl) | Q1: Reviever 2:Rohana Dasanayaka (LLB ousl) | V1: Reviever 3: Dulani Kulasooriya (LLB ousl) | AA1: Reviever 4: Dulshan Liyanaarachchi (LLB ousl) | AF1: Reviever 5: Inoshika Kodithuwakku (LLB ousl) | AK1: Mean | AL1: Mean | AM1: Mean
L2: Reviewer ID: LEGAL_EXPERT_1 | Q2: Reviewer ID: LEGAL_EXPERT_2 | V2: Reviewer ID: LEGAL_EXPERT_3 | AA2: Reviewer ID: LEGAL_EXPERT_4 | AF2: Reviewer ID: LEGAL_EXPERT_5 | AK2: Reviewer IDs: LEGAL_EXPERT_1, LEGAL_EXPERT_2, LEGAL_EXPERT_3, LEGAL_EXPERT_4, LEGAL_EXPERT_5
L3: Correctness (1=Poor 5=Excellent) | M3: Completeness (1=Poor 5=Excellent) | N3: Clarity (1=Poor 5=Excellent) | O3: Expert Comments | P3: Review Date | Q3: Correctness (1=Poor 5=Excellent) | R3: Completeness (1=Poor 5=Excellent) | S3: Clarity (1=Poor 5=Excellent) | T3: Expert Comments | U3: Review Date | V3: Correctness (1=Poor 5=Excellent) | W3: Completeness (1=Poor 5=Excellent) | X3: Clarity (1=Poor 5=Excellent) | Y3: Expert Comments | Z3: Review Date | AA3: Correctness (1=Poor 5=Excellent) | AB3: Completeness (1=Poor 5=Excellent) | AC3: Clarity (1=Poor 5=Excellent) | AD3: Expert Comments | AE3: Review Date | AF3: Correctness (1=Poor 5=Excellent) | AG3: Completeness (1=Poor 5=Excellent) | AH3: Clarity (1=Poor 5=Excellent) | AI3: Expert Comments | AJ3: Review Date | AK3: Correctness (1=Poor 5=Excellent) | AL3: Completeness (1=Poor 5=Excellent) | AM3: Clarity (1=Poor 5=Excellent)
A4: QAC_101 | B4: Factual | C4: Medium | D4: Constitutional | E4: What are the responsibilities of the Secretary to each Ministry? | F4: Article 52 provides that there shall be a Secretary for every Ministry of a Minister of the Cabinet of Ministers, appointed by the President. The Secretary to a Ministry shall, subject to the direction and control of his Minister, exercise supervision over the departments of Government and other institutions in charge of the Minister. Notwithstanding the dissolution of the Cabinet of Ministers, the Secretary to a Ministry shall continue to hold office until a new Secretary is appointed. | G4: Article 52 | H4: Art. 52: (1) There shall be a Secretary for every Ministry Ministries of a Minister of the Cabinet of Ministers, who shall be appointed by the President. (2) The Secretary to a Ministry shall, subject to the d | I4: Human Annotated | J4: =MAX(P4,U4,Z4,AE4,AJ4) -> 46170 | K4: LEGAL_EXPERT_1, LEGAL_EXPERT_2, LEGAL_EXPERT_3, LEGAL_EXPERT_4, LEGAL_EXPERT_5 | L4: 4.5 | M4: 4.3 | N4: 4.8 | P4: 2026.05.25 | Q4: 4.5 | R4: 4.3 | S4: 4.7 | U4: 2026.05.27 | V4: 4.7 | W4: 4.7 | X4: 4.6 | Z4: 46168 | AA4: 4.7 | AB4: 4.8 | AC4: 4.7 | AE4: 46170 | AF4: 4.5 | AG4: 4.7 | AH4: 4.6 | AJ4: 2026.05.28 | AK4: =AVERAGE(L4,Q4,V4,AA4,AF4) -> 4.58 | AL4: =AVERAGE(M4,R4,W4,AB4,AG4) -> 4.56 | AM4: =AVERAGE(N4,S4,X4,AC4,AH4) -> 4.68
A5: QAC_102 | B5: Procedural | C5: Medium | D5: Constitutional | E5: What oath or affirmation must a person take before assuming office in the executive branch? | F5: Article 53 requires that a person appointed to any office referred to in Chapter VIII on the Cabinet of Ministers shall not enter upon the duties of that office until they take and subscribe the official oath or make and subscribe the official affirmation as set out in the Fourth Schedule and Seventh Schedule of the Constitution. | G5: 1 | H5: Art. 53: A person appointed to any office referred to in Official this Chapter shall not enter upon the duties of his office oath or affirmation until such person takes and subscribes the oath or makes and sub | I5: Human Annotated | J5: =MAX(P5,U5,Z5,AE5,AJ5) -> 46170 | K5: LEGAL_EXPERT_1, LEGAL_EXPERT_2, LEGAL_EXPERT_3, LEGAL_EXPERT_4, LEGAL_EXPERT_5 | L5: 4.5 | M5: 4.3 | N5: 4.8 | P5: 2026.05.25 | Q5: 4.6 | R5: 4.3 | S5: 4.7 | U5: 2026.05.27 | V5: 4.3 | W5: 4.4 | X5: 4.6 | Z5: 46168 | AA5: 4.4 | AB5: 4.5 | AC5: 4.6 | AE5: 46170 | AF5: 4.6 | AG5: 4.7 | AH5: 4.8 | AJ5: 2026.05.28 | AK5: =AVERAGE(L5,Q5,V5,AA5,AF5) -> 4.48 | AL5: =AVERAGE(M5,R5,W5,AB5,AG5) -> 4.44 | AM5: =AVERAGE(N5,S5,X5,AC5,AH5) -> 4.7
A6: QAC_103 | B6: Factual | C6: Medium | D6: Constitutional | E6: What powers does the Cabinet of Ministers have over the public service? | F6: Article 55 provides that the Cabinet of Ministers shall provide for and determine all matters of policy relating to public officers, including policy relating to appointments, promotions, transfers, disciplinary control and dismissal. The appointment, promotion, transfer, disciplinary control and dismissal of public officers vests in the Cabinet of Ministers exercising its functions through the Public Service Commission. | G6: Article 55 | H6: Art. 55: (1) The Cabinet of Ministers shall provide for and functions of determine all matters of policy relating to public officers, the Cabinet of Ministers including policy relating to appointments, promoti | I6: Human Annotated | J6: =MAX(P6,U6,Z6,AE6,AJ6) -> 46170 | K6: LEGAL_EXPERT_1, LEGAL_EXPERT_2, LEGAL_EXPERT_3, LEGAL_EXPERT_4, LEGAL_EXPERT_5 | L6: 4.5 | M6: 4.3 | N6: 4.8 | P6: 2026.05.25 | Q6: 4.5 | R6: 4.3 | S6: 4.7 | U6: 2026.05.27 | V6: 4.6 | W6: 4.4 | X6: 4.7 | Z6: 46168 | AA6: 4.6 | AB6: 4.7 | AC6: 4.5 | AE6: 46170 | AF6: 4.5 | AG6: 4.8 | AH6: 4.7 | AJ6: 2026.05.28 | AK6: =AVERAGE(L6,Q6,V6,AA6,AF6) -> 4.54 | AL6: =AVERAGE(M6,R6,W6,AB6,AG6) -> 4.5 | AM6: =AVERAGE(N6,S6,X6,AC6,AH6) -> 4.68
A7: QAC_104 | B7: Factual | C7: Medium | D7: Constitutional | E7: Can the Public Service Commission delegate its powers to a committee? | F7: Article 56 provides that the Public Service Commission may delegate to a Committee consisting of three persons (not being members of the Commission) appointed by it, any of the powers of the Commission in relation to appointments, promotions, transfers, and disciplinary control of public officers. Such delegation enables efficient administration of the public service. | G7: Article 56 | H7: Art. 56: (1) The Commission may delegate to a Committee Committees consisting of three persons (not being members of the of the Commission Commission) appointed by the Commission, the powers of appointment, pr | I7: Human Annotated | J7: =MAX(P7,U7,Z7,AE7,AJ7) -> 46170 | K7: LEGAL_EXPERT_1, LEGAL_EXPERT_2, LEGAL_EXPERT_3, LEGAL_EXPERT_4, LEGAL_EXPERT_5 | L7: 4.5 | M7: 4.3 | N7: 4.8 | P7: 2026.05.25 | Q7: 4.4 | R7: 4.3 | S7: 4.8 | U7: 2026.05.27 | V7: 4.7 | W7: 4.4 | X7: 4.5 | Z7: 46168 | AA7: 4.9 | AB7: 4.8 | AC7: 4.7 | AE7: 46170 | AF7: 4.5 | AG7: 4.7 | AH7: 4.6 | AJ7: 2026.05.28 | AK7: =AVERAGE(L7,Q7,V7,AA7,AF7) -> 4.6 | AL7: =AVERAGE(M7,R7,W7,AB7,AG7) -> 4.5 | AM7: =AVERAGE(N7,S7,X7,AC7,AH7) -> 4.68
A8: QAC_105 | B8: Factual | C8: Medium | D8: Constitutional | E8: What powers may the Public Service Commission delegate to a public officer? | F8: Article 57 provides that the Commission may delegate to a public officer, subject to such conditions and procedure as may be determined by the Commission, any of the powers of the Commission in relation to the appointment, promotion, transfer, and disciplinary control of public officers subordinate to that public officer. | G8: Article 57 | H8: Art. 57: (1) The Commission may delegate to a public Delegation officer, subject to such conditions and procedure as may be of powers to a public determined by the Commission, its powers of appointment, office | I8: Human Annotated | J8: =MAX(P8,U8,Z8,AE8,AJ8) -> 46170 | K8: LEGAL_EXPERT_1, LEGAL_EXPERT_2, LEGAL_EXPERT_3, LEGAL_EXPERT_4, LEGAL_EXPERT_5 | L8: 4.5 | M8: 4.3 | N8: 4.8 | P8: 2026.05.25 | Q8: 4.5 | R8: 4.4 | S8: 4.8 | U8: 2026.05.27 | V8: 4.6 | W8: 4.4 | X8: 4.7 | Z8: 46168 | AA8: 4.5 | AB8: 4.4 | AC8: 4.8 | AE8: 46170 | AF8: 4.6 | AG8: 4.7 | AH8: 4.8 | AJ8: 2026.05.28 | AK8: =AVERAGE(L8,Q8,V8,AA8,AF8) -> 4.54 | AL8: =AVERAGE(M8,R8,W8,AB8,AG8) -> 4.44 | AM8: =AVERAGE(N8,S8,X8,AC8,AH8) -> 4.78
A9: QAC_106 | B9: Procedural | C9: Medium | D9: Constitutional | E9: What right of appeal does a public officer have against certain adverse decisions? | F9: Article 58 provides that any public officer aggrieved by an order relating to a promotion, transfer, dismissal, or disciplinary matter made by the Commission or any Committee or public officer to whom powers have been delegated, may appeal to the Public Service Commission against such order, and the Commission shall have the power to alter, vary, rescind or confirm the order. | G9: Article 58 | H9: Art. 58: (1) Any public officer aggrieved by an order Right of relating to a promotion, transfer, dismissal or an order a ppeal on a disciplinary matter made by a Committee or any public officer under Article | I9: Human Annotated | J9: =MAX(P9,U9,Z9,AE9,AJ9) -> 46170 | K9: LEGAL_EXPERT_1, LEGAL_EXPERT_2, LEGAL_EXPERT_3, LEGAL_EXPERT_4, LEGAL_EXPERT_5 | L9: 4.5 | M9: 4.3 | N9: 4.8 | P9: 2026.05.25 | Q9: 4.5 | R9: 4.3 | S9: 4.8 | U9: 2026.05.27 | V9: 4.8 | W9: 4.4 | X9: 4.5 | Z9: 46168 | AA9: 4.7 | AB9: 4.5 | AC9: 4.5 | AE9: 46170 | AF9: 4.5 | AG9: 4.8 | AH9: 4.7 | AJ9: 2026.05.28 | AK9: =AVERAGE(L9,Q9,V9,AA9,AF9) -> 4.6 | AL9: =AVERAGE(M9,R9,W9,AB9,AG9) -> 4.46 | AM9: =AVERAGE(N9,S9,X9,AC9,AH9) -> 4.66
A10: QAC_107 | B10: Factual | C10: Medium | D10: Constitutional | E10: What is the Administrative Appeals Tribunal and who appoints it? | F10: Article 59 provides for the establishment of an Administrative Appeals Tribunal appointed by the Judicial Service Commission. The Administrative Appeals Tribunal shall have the power to alter, vary or rescind any order or decision made by the Public Service Commission. The constitution, powers and procedure of the Tribunal, including time limits for preferring appeals, shall be provided for by law. | G10: Article 59 | H10: Art. 59: (1) There shall be an Administrative Appeals Appeals Tribunal appointed by the Judicial Service Commission. Tribunal (2) The Administrative Appeals Tribunal shall have the power to alter, vary or resc | I10: Human Annotated | J10: =MAX(P10,U10,Z10,AE10,AJ10) -> 46170 | K10: LEGAL_EXPERT_1, LEGAL_EXPERT_2, LEGAL_EXPERT_3, LEGAL_EXPERT_4, LEGAL_EXPERT_5 | L10: 4.5 | M10: 4.3 | N10: 4.8 | P10: 2026.05.25 | Q10: 4.6 | R10: 4.3 | S10: 4.8 | U10: 2026.05.27 | V10: 4.9 | W10: 4.7 | X10: 4.6 | Z10: 46168 | AA10: 4.7 | AB10: 4.7 | AC10: 4.7 | AE10: 46170 | AF10: 4.5 | AG10: 4.7 | AH10: 4.6 | AJ10: 2026.05.28 | AK10: =AVERAGE(L10,Q10,V10,AA10,AF10) -> 4.64 | AL10: =AVERAGE(M10,R10,W10,AB10,AG10) -> 4.54 | AM10: =AVERAGE(N10,S10,X10,AC10,AH10) -> 4.7
A11: QAC_108 | B11: Interpretive | C11: Hard | D11: Constitutional | E11: Can the Public Service Commission continue to exercise powers it has delegated? | F11: Article 60 provides that upon delegation of any of its powers to a Committee or a public officer under Articles 56 or 57, the Commission shall not itself exercise such delegated powers. The effect of delegation is therefore to transfer, not merely share, the exercise of the delegated power to the delegate. | G11: Article 60 | H11: Art. 60: Upon delegation of any of its powers to a not to Committee or a public officer appointed under Article 56 exercise or Article 57 as the case may be, the Commission shall power where there is not, whil | I11: Human Annotated | J11: =MAX(P11,U11,Z11,AE11,AJ11) -> 46170 | K11: LEGAL_EXPERT_1, LEGAL_EXPERT_2, LEGAL_EXPERT_3, LEGAL_EXPERT_4, LEGAL_EXPERT_5 | L11: 4.5 | M11: 4.3 | N11: 4.8 | P11: 2026.05.25 | Q11: 4.5 | R11: 4.3 | S11: 4.8 | U11: 2026.05.27 | V11: 4.8 | W11: 4.5 | X11: 4.6 | Z11: 46168 | AA11: 4.5 | AB11: 4.5 | AC11: 4.7 | AE11: 46170 | AF11: 4.6 | AG11: 4.7 | AH11: 4.8 | AJ11: 2026.05.28 | AK11: =AVERAGE(L11,Q11,V11,AA11,AF11) -> 4.58 | AL11: =AVERAGE(M11,R11,W11,AB11,AG11) -> 4.46 | AM11: =AVERAGE(N11,S11,X11,AC11,AH11) -> 4.74
A12: QAC_109 | B12: Procedural | C12: Easy | D12: Constitutional | E12: What oath or affirmation must a Member of Parliament take before sitting or voting? | F12: Article 63 provides that except for the purpose of electing the Speaker, no Member shall sit or vote in Parliament until they have taken and subscribed the official oath or made and subscribed the official affirmation before Parliament. The oath includes a commitment to uphold and defend the Constitution. | G12: Article 63 | H12: Art. 63: Except for the purpose of electing the Speaker, Official oath or no Member shall sit or vote in parliament until he has affirmation taken and subscribed the following oath, or made and subscribed the | I12: Human Annotated | J12: =MAX(P12,U12,Z12,AE12,AJ12) -> 46170 | K12: LEGAL_EXPERT_1, LEGAL_EXPERT_2, LEGAL_EXPERT_3, LEGAL_EXPERT_4, LEGAL_EXPERT_5 | L12: 4.5 | M12: 4.3 | N12: 4.8 | P12: 2026.05.25 | Q12: 4.5 | R12: 4.3 | S12: 4.7 | U12: 2026.05.27 | V12: 4.5 | W12: 4.2 | X12: 4.5 | Z12: 46168 | AA12: 4.7 | AB12: 4.6 | AC12: 4.5 | AE12: 46170 | AF12: 4.5 | AG12: 4.8 | AH12: 4.7 | AJ12: 2026.05.28 | AK12: =AVERAGE(L12,Q12,V12,AA12,AF12) -> 4.54 | AL12: =AVERAGE(M12,R12,W12,AB12,AG12) -> 4.44 | AM12: =AVERAGE(N12,S12,X12,AC12,AH12) -> 4.64
A13: QAC_110 | B13: Procedural | C13: Medium | D13: Constitutional | E13: How is the Speaker of Parliament elected? | F13: Article 64 provides that Parliament shall, at its first meeting after a General Election, elect three Members to be respectively the Speaker, the Deputy Speaker and the Deputy Chairman of Committees. Whenever the office of Speaker, Deputy Speaker or Deputy Chairman of Committees becomes vacant otherwise than by dissolution, Parliament shall at its first meeting elect another Member to fill the vacancy. | G13: Article 64 | H13: Art. 64: (1) Parliament shall, at its first meeting after a Speaker, Deputy General Election, elect three Members to be respectively Speaker and the Speaker, the Deputy Speaker and Chairman of Committees Deput | I13: Human Annotated | J13: =MAX(P13,U13,Z13,AE13,AJ13) -> 46170 | K13: LEGAL_EXPERT_1, LEGAL_EXPERT_2, LEGAL_EXPERT_3, LEGAL_EXPERT_4, LEGAL_EXPERT_5 | L13: 4.5 | M13: 4.3 | N13: 4.8 | P13: 2026.05.25 | Q13: 4.5 | R13: 4.3 | S13: 4.8 | U13: 2026.05.27 | V13: 4.6 | W13: 4.5 | X13: 4.6 | Z13: 46168 | AA13: 4.5 | AB13: 4.5 | AC13: 4.5 | AE13: 46170 | AF13: 4.5 | AG13: 4.7 | AH13: 4.6 | AJ13: 2026.05.28 | AK13: =AVERAGE(L13,Q13,V13,AA13,AF13) -> 4.52 | AL13: =AVERAGE(M13,R13,W13,AB13,AG13) -> 4.46 | AM13: =AVERAGE(N13,S13,X13,AC13,AH13) -> 4.66
A14: QAC_111 | B14: Factual | C14: Medium | D14: Constitutional | E14: Who is the Secretary-General of Parliament and how are they appointed? | F14: Article 65 provides that there shall be a Secretary-General of Parliament who shall, on the approval of the Constitutional Council, be appointed by the President. The Secretary-General shall hold office during good behavior and their salary shall be determined by Parliament and charged on the Consolidated Fund. | G14: Article 65 | H14: Art. 65: (1) There shall be a Secretary-General of General Parliament who shall, 51[on the approval of the Constitutional of Parliament Council,] be appointed by the President and who shall hold office during | I14: Human Annotated | J14: =MAX(P14,U14,Z14,AE14,AJ14) -> 46170 | K14: LEGAL_EXPERT_1, LEGAL_EXPERT_2, LEGAL_EXPERT_3, LEGAL_EXPERT_4, LEGAL_EXPERT_5 | L14: 4.5 | M14: 4.3 | N14: 4.8 | P14: 2026.05.25 | Q14: 4.5 | R14: 4.3 | S14: 4.7 | U14: 2026.05.27 | V14: 4.5 | W14: 4.4 | X14: 4.6 | Z14: 46168 | AA14: 4.4 | AB14: 4.6 | AC14: 4.6 | AE14: 46170 | AF14: 4.6 | AG14: 4.7 | AH14: 4.8 | AJ14: 2026.05.28 | AK14: =AVERAGE(L14,Q14,V14,AA14,AF14) -> 4.5 | AL14: =AVERAGE(M14,R14,W14,AB14,AG14) -> 4.46 | AM14: =AVERAGE(N14,S14,X14,AC14,AH14) -> 4.7
A15: QAC_112 | B15: Factual | C15: Medium | D15: Constitutional | E15: In what circumstances does the seat of a Member of Parliament become vacant? | F15: Article 66 provides that the seat of a Member shall become vacant upon: (a) the Member's death; (b) resignation by writing addressed to the Secretary-General; (c) assuming the office of President; (d) becoming subject to any disqualification specified in Article 89 or 91; (e) becoming a member of the Public Service or an employee of a public corporation without ceasing to be so before sitting in Parliament; or (f) absence from sittings for a continuous period of three months without leave of Parliament. | G15: Article 66 | H15: Art. 66: The seat of a Member shall become vacant Vacation of seats (a) upon his death; (b) If, by a writing under his hand addressed to the Secretary-General of Parliament, he resigns his seat; (c) upon his | I15: Human Annotated | J15: =MAX(P15,U15,Z15,AE15,AJ15) -> 46170 | K15: LEGAL_EXPERT_1, LEGAL_EXPERT_2, LEGAL_EXPERT_3, LEGAL_EXPERT_4, LEGAL_EXPERT_5 | L15: 4.5 | M15: 4.3 | N15: 4.8 | P15: 2026.05.25 | Q15: 4.6 | R15: 4.3 | S15: 4.8 | U15: 2026.05.27 | V15: 4.6 | W15: 4.5 | X15: 4.7 | Z15: 46168 | AA15: 4.7 | AB15: 4.6 | AC15: 4.5 | AE15: 46170 | AF15: 4.5 | AG15: 4.8 | AH15: 4.7 | AJ15: 2026.05.28 | AK15: =AVERAGE(L15,Q15,V15,AA15,AF15) -> 4.58 | AL15: =AVERAGE(M15,R15,W15,AB15,AG15) -> 4.5 | AM15: =AVERAGE(N15,S15,X15,AC15,AH15) -> 4.7
A16: QAC_113 | B16: Factual | C16: Easy | D16: Constitutional | E16: Are Members of Parliament paid for their services and how are their salaries determined? | F16: Article 68 provides that Ministers, Deputy Ministers and Members, including the Speaker, the Deputy Speaker and the Deputy Chairman of Committees, shall be paid such remuneration or allowance as may be provided by Parliament, by law or by resolution. These salaries and allowances shall be charged on the Consolidated Fund. | G16: Article 68 | H16: Art. 68: (1) Ministers, Deputy Ministers and Members, of Members including the Speaker, the Deputy Speaker and the Deputy Chairman of Committees, shall be paid such remuneration or allowance as may be provided | I16: Human Annotated | J16: =MAX(P16,U16,Z16,AE16,AJ16) -> 46170 | K16: LEGAL_EXPERT_1, LEGAL_EXPERT_2, LEGAL_EXPERT_3, LEGAL_EXPERT_4, LEGAL_EXPERT_5 | L16: 4.5 | M16: 4.3 | N16: 4.8 | P16: 2026.05.25 | Q16: 4.5 | R16: 4.3 | S16: 4.8 | U16: 2026.05.27 | V16: 4.7 | W16: 4.4 | X16: 4.5 | Z16: 46168 | AA16: 4.6 | AB16: 4.6 | AC16: 4.6 | AE16: 46170 | AF16: 4.5 | AG16: 4.7 | AH16: 4.6 | AJ16: 2026.05.28 | AK16: =AVERAGE(L16,Q16,V16,AA16,AF16) -> 4.56 | AL16: =AVERAGE(M16,R16,W16,AB16,AG16) -> 4.46 | AM16: =AVERAGE(N16,S16,X16,AC16,AH16) -> 4.66
A17: QAC_114 | B17: Factual | C17: Easy | D17: Constitutional | E17: How are questions decided in Parliament? | F17: Article 72 provides that, save as otherwise provided in the Constitution, any question proposed for decision by Parliament shall be decided by the majority of votes of the Members present and voting. The person presiding shall not vote in the first instance but shall have and exercise a casting vote in the event of an equality of votes. | G17: Article 72 | H17: Art. 72: (1) Save as otherwise provided in the Constitution any question proposed for decision by Parliament shall be decided by the majority of votes of the Members present and voting. The Constitution of the | I17: Human Annotated | J17: =MAX(P17,U17,Z17,AE17,AJ17) -> 46170 | K17: LEGAL_EXPERT_1, LEGAL_EXPERT_2, LEGAL_EXPERT_3, LEGAL_EXPERT_4, LEGAL_EXPERT_5 | L17: 4.5 | M17: 4.3 | N17: 4.8 | P17: 2026.05.25 | Q17: 4.5 | R17: 4.4 | S17: 4.8 | U17: 2026.05.27 | V17: 4.8 | W17: 4.5 | X17: 4.7 | Z17: 46168 | AA17: 4.7 | AB17: 4.6 | AC17: 4.5 | AE17: 46170 | AF17: 4.6 | AG17: 4.7 | AH17: 4.8 | AJ17: 2026.05.28 | AK17: =AVERAGE(L17,Q17,V17,AA17,AF17) -> 4.62 | AL17: =AVERAGE(M17,R17,W17,AB17,AG17) -> 4.5 | AM17: =AVERAGE(N17,S17,X17,AC17,AH17) -> 4.72
A18: QAC_115 | B18: Factual | C18: Medium | D18: Constitutional | E18: What matters can Parliament regulate through Standing Orders? | F18: Article 74 provides that, subject to the Constitution, Parliament may by resolution or Standing Order provide for: (i) the election and retirement of the Speaker, the Deputy Speaker and the Deputy Chairman of Committees; (ii) the regulation of its business and the preservation of order at its proceedings; and (iii) any other matters relating to the conduct of parliamentary proceedings. | G18: Article 74 | H18: Art. 74: (1) Subject to the provisions of the Constitution, Standing Orders Parliament may by resolution or Standing Order provide for (i) the election and retirement of the Speaker, the Deputy Speaker and th | I18: Human Annotated | J18: =MAX(P18,U18,Z18,AE18,AJ18) -> 46170 | K18: LEGAL_EXPERT_1, LEGAL_EXPERT_2, LEGAL_EXPERT_3, LEGAL_EXPERT_4, LEGAL_EXPERT_5 | L18: 4.5 | M18: 4.3 | N18: 4.8 | P18: 2026.05.25 | Q18: 4.5 | R18: 4.3 | S18: 4.8 | U18: 2026.05.27 | V18: 4.5 | W18: 4.4 | X18: 4.5 | Z18: 46168 | AA18: 4.4 | AB18: 4.5 | AC18: 4.4 | AE18: 46170 | AF18: 4.5 | AG18: 4.8 | AH18: 4.7 | AJ18: 2026.05.28 | AK18: =AVERAGE(L18,Q18,V18,AA18,AF18) -> 4.48 | AL18: =AVERAGE(M18,R18,W18,AB18,AG18) -> 4.46 | AM18: =AVERAGE(N18,S18,X18,AC18,AH18) -> 4.64
A19: QAC_116 | B19: Factual | C19: Medium | D19: Constitutional | E19: What is the legislative power of Parliament under the Constitution? | F19: Article 75 provides that Parliament shall have power to make laws, including laws having retrospective effect, and repealing or amending any provision of the Constitution, or adding any provision to the Constitution. However, Parliament shall not make any law suspending the operation of the Constitution or any part thereof. | G19: Article 75 | H19: Art. 75: Parliament shall have power to make laws, Legislative power including laws having retrospective effect and repealing or amending any provision of the Constitution, or adding any provision to the Const | I19: Human Annotated | J19: =MAX(P19,U19,Z19,AE19,AJ19) -> 46170 | K19: LEGAL_EXPERT_1, LEGAL_EXPERT_2, LEGAL_EXPERT_3, LEGAL_EXPERT_4, LEGAL_EXPERT_5 | L19: 4.5 | M19: 4.3 | N19: 4.8 | P19: 2026.05.25 | Q19: 4.5 | R19: 4.3 | S19: 4.7 | U19: 2026.05.27 | V19: .4.7 | W19: 4.3 | X19: 4.6 | Z19: 46168 | AA19: 4.8 | AB19: 4.5 | AC19: 4.5 | AE19: 46170 | AF19: 4.5 | AG19: 4.7 | AH19: 4.6 | AJ19: 2026.05.28 | AK19: =AVERAGE(L19,Q19,V19,AA19,AF19) -> 4.575 | AL19: =AVERAGE(M19,R19,W19,AB19,AG19) -> 4.42 | AM19: =AVERAGE(N19,S19,X19,AC19,AH19) -> 4.64
A20: QAC_117 | B20: Factual | C20: Medium | D20: Constitutional | E20: What duty does the Attorney-General have in relation to Bills presented to Parliament? | F20: Article 77 places a duty on the Attorney-General to examine every Bill for any contravention of the requirements of paragraphs (1) and (2) of Article 82 and for any provision which cannot be validly passed except by the special majority prescribed by the Constitution. If the Attorney-General is of the opinion that a Bill contravenes any such requirements, he shall communicate such opinion to the President (or, in the case of an amendment to a Bill, to the Speaker). | G20: Article 77 | H20: Art. 77: (1) It shall be the duty of the Attorney-General Attorney- to examine every Bill for any contravention of the General in requirements of paragraphs (1) and (2) of Article 82 and regard to published fo | I20: Human Annotated | J20: =MAX(P20,U20,Z20,AE20,AJ20) -> 46170 | K20: LEGAL_EXPERT_1, LEGAL_EXPERT_2, LEGAL_EXPERT_3, LEGAL_EXPERT_4, LEGAL_EXPERT_5 | L20: 4.5 | M20: 4.3 | N20: 4.8 | P20: 2026.05.25 | Q20: 4.5 | R20: 4.3 | S20: 4.8 | U20: 2026.05.27 | V20: 4.8 | W20: 4.4 | X20: 4.6 | Z20: 46168 | AA20: 4.6 | AB20: 4.5 | AC20: 4.4 | AE20: 46170 | AF20: 4.6 | AG20: 4.7 | AH20: 4.8 | AJ20: 2026.05.28 | AK20: =AVERAGE(L20,Q20,V20,AA20,AF20) -> 4.6 | AL20: =AVERAGE(M20,R20,W20,AB20,AG20) -> 4.44 | AM20: =AVERAGE(N20,S20,X20,AC20,AH20) -> 4.68
A21: QAC_118 | B21: Procedural | C21: Medium | D21: Constitutional | E21: How does a Bill passed by Parliament become law? | F21: Article 80 provides that, subject to the provisions of Article 80(2), a Bill passed by Parliament shall become law when the certificate of the Speaker is endorsed thereon. Where the Cabinet of Ministers has certified that a Bill is intended to be submitted for approval by the People at a Referendum, it shall not become law unless so approved. | G21: Article 80 | H21: Art. 80: (1) Subject to the provisions of paragraph (2) of becomes law this Article, a Bill passed by Parliament shall become law when the certificate of the Speaker is endorsed thereon. (2) Where the Cabinet | I21: Human Annotated | J21: =MAX(P21,U21,Z21,AE21,AJ21) -> 46170 | K21: LEGAL_EXPERT_1, LEGAL_EXPERT_2, LEGAL_EXPERT_3, LEGAL_EXPERT_4, LEGAL_EXPERT_5 | L21: 4.5 | M21: 4.3 | N21: 4.8 | P21: 2026.05.25 | Q21: 4.4 | R21: 4.3 | S21: 4.8 | U21: 2026.05.27 | V21: 4.7 | W21: 4.4 | X21: 4.7 | Z21: 46168 | AA21: 4.7 | AB21: 4.7 | AC21: 4.7 | AE21: 46170 | AF21: 4.5 | AG21: 4.8 | AH21: 4.7 | AJ21: 2026.05.28 | AK21: =AVERAGE(L21,Q21,V21,AA21,AF21) -> 4.56 | AL21: =AVERAGE(M21,R21,W21,AB21,AG21) -> 4.5 | AM21: =AVERAGE(N21,S21,X21,AC21,AH21) -> 4.74
A22: QAC_119 | B22: Factual | C22: Medium | D22: Constitutional | E22: What privileges and immunities does Parliament have under the Constitution? | F22: Article 81 provides that the privileges, immunities and powers of Parliament and of its Members may be determined and regulated by Parliament. Until such determination, the privileges, immunities and powers of Parliament and of its Members shall be those privileges, immunities and powers enjoyed by the House of Representatives and its Members on the day of commencement of the Constitution. | G22: Article 81 | H22: Art. 81: Privileges, 67. The privileges, immunities and powers of immunities Parliament and of its Members may be determined and and powers regulated by Parliament by law and until so determined of Parliament | I22: Human Annotated | J22: =MAX(P22,U22,Z22,AE22,AJ22) -> 46170 | K22: LEGAL_EXPERT_1, LEGAL_EXPERT_2, LEGAL_EXPERT_3, LEGAL_EXPERT_4, LEGAL_EXPERT_5 | L22: 4.5 | M22: 4.3 | N22: 4.8 | P22: 2026.05.25 | Q22: 4.5 | R22: 4.3 | S22: 4.8 | U22: 2026.05.27 | V22: 4.6 | W22: 4.5 | X22: 4.6 | Z22: 46168 | AA22: 4.5 | AB22: 4.4 | AC22: 4.5 | AE22: 46170 | AF22: 4.5 | AG22: 4.7 | AH22: 4.6 | AJ22: 2026.05.28 | AK22: =AVERAGE(L22,Q22,V22,AA22,AF22) -> 4.52 | AL22: =AVERAGE(M22,R22,W22,AB22,AG22) -> 4.44 | AM22: =AVERAGE(N22,S22,X22,AC22,AH22) -> 4.66
A23: QAC_120 | B23: Procedural | C23: Hard | D23: Constitutional | E23: Which Bills must be passed at a Referendum in addition to a two-thirds majority in Parliament? | F23: Article 83 provides that, notwithstanding Article 82, a Bill for the amendment or repeal and replacement of, or which is inconsistent with, Articles 1, 2, 3, 6, 7, 8, 9, 10, or 11, or Article 83 itself, shall not be presented for the Speaker's certificate unless it has been approved by the People at a Referendum, in addition to being passed by a two-thirds majority in Parliament. | G23: Article 83 | H23: Art. 83: Notwithstanding anything to the contrary in the of certain provisions of Article 82 Bills at a Referendum (a) a Bill for the amendment or for the repeal and replacement of or which is inconsistent wi | I23: Human Annotated | J23: =MAX(P23,U23,Z23,AE23,AJ23) -> 46170 | K23: LEGAL_EXPERT_1, LEGAL_EXPERT_2, LEGAL_EXPERT_3, LEGAL_EXPERT_4, LEGAL_EXPERT_5 | L23: 4.5 | M23: 4.3 | N23: 4.8 | P23: 2026.05.25 | Q23: 4.5 | R23: 4.3 | S23: 4.7 | U23: 2026.05.27 | V23: 4.7 | W23: 4.3 | X23: 4.5 | Z23: 46168 | AA23: 4.4 | AB23: 4.3 | AC23: 4.3 | AE23: 46170 | AF23: 4.6 | AG23: 4.7 | AH23: 4.8 | AJ23: 2026.05.28 | AK23: =AVERAGE(L23,Q23,V23,AA23,AF23) -> 4.54 | AL23: =AVERAGE(M23,R23,W23,AB23,AG23) -> 4.38 | AM23: =AVERAGE(N23,S23,X23,AC23,AH23) -> 4.62
A24: QAC_121 | B24: Procedural | C24: Hard | D24: Constitutional | E24: What is the procedure for the President to submit a Bill to the People at a Referendum? | F24: Article 85 provides that the President shall submit to the People by Referendum every Bill, or any provision in any Bill, which the Cabinet of Ministers has certified to be a Bill which if enacted would be consistent with the Constitution only if approved at a Referendum. The Referendum shall be conducted by the Commissioner of Elections. | G24: Article 85 | H24: Art. 85: (1) The President shall submit to the People by of Bills to Referendum every Bill or any provision in any Bill people by Referendum which the Cabinet of Ministers has certified as being intended to be | I24: Human Annotated | J24: =MAX(P24,U24,Z24,AE24,AJ24) -> 46170 | K24: LEGAL_EXPERT_1, LEGAL_EXPERT_2, LEGAL_EXPERT_3, LEGAL_EXPERT_4, LEGAL_EXPERT_5 | L24: 4.5 | M24: 4.3 | N24: 4.8 | P24: 2026.05.25 | Q24: 4.4 | R24: 4.3 | S24: 4.8 | U24: 2026.05.27 | V24: 4.8 | W24: 4.3 | X24: 4.5 | Z24: 46168 | AA24: 4.5 | AB24: 4.5 | AC24: 4.5 | AE24: 46170 | AF24: 4.5 | AG24: 4.8 | AH24: 4.7 | AJ24: 2026.05.28 | AK24: =AVERAGE(L24,Q24,V24,AA24,AF24) -> 4.54 | AL24: =AVERAGE(M24,R24,W24,AB24,AG24) -> 4.44 | AM24: =AVERAGE(N24,S24,X24,AC24,AH24) -> 4.66
A25: QAC_122 | B25: Factual | C25: Medium | D25: Constitutional | E25: Can the President submit matters of national importance to a Referendum? | F25: Article 86 provides that the President may, subject to the provisions of Article 85, submit to the People by Referendum any matter which in the opinion of the President is of national importance. This grants the President a discretionary power to consult the electorate directly on significant national questions. | G25: Article 86 | H25: Art. 86: The President may, subject to the provisions of of matters of Article 85, submit to the People by Referendum any matter national importance to which in the opinion of the President is of national peop | I25: Human Annotated | J25: =MAX(P25,U25,Z25,AE25,AJ25) -> 46170 | K25: LEGAL_EXPERT_1, LEGAL_EXPERT_2, LEGAL_EXPERT_3, LEGAL_EXPERT_4, LEGAL_EXPERT_5 | L25: 4.5 | M25: 4.3 | N25: 4.8 | P25: 2026.05.25 | Q25: 4.5 | R25: 4.3 | S25: 4.7 | U25: 2026.05.27 | V25: 4.8 | W25: 4.4 | X25: 4.6 | Z25: 46168 | AA25: 4.6 | AB25: 4.6 | AC25: 4.7 | AE25: 46170 | AF25: 4.5 | AG25: 4.7 | AH25: 4.6 | AJ25: 2026.05.28 | AK25: =AVERAGE(L25,Q25,V25,AA25,AF25) -> 4.58 | AL25: =AVERAGE(M25,R25,W25,AB25,AG25) -> 4.46 | AM25: =AVERAGE(N25,S25,X25,AC25,AH25) -> 4.68
A26: QAC_123 | B26: Procedural | C26: Medium | D26: Constitutional | E26: How must a Referendum be conducted and its result communicated? | F26: Article 87 provides that every Referendum shall be conducted by the Commissioner of Elections, who shall communicate the result thereof to the President. Parliament shall by law make provision for the procedure for the conduct of any Referendum held under the Constitution, including the qualifications of voters and the manner of voting. | G26: Article 87 | H26: Art. 87: (1) Every Referendum shall be conducted by the Parliament to provide for Commissioner of Elections who shall communicate the procedure result thereof to the President. (2) Parliament shall by law prov | I26: Human Annotated | J26: =MAX(P26,U26,Z26,AE26,AJ26) -> 46170 | K26: LEGAL_EXPERT_1, LEGAL_EXPERT_2, LEGAL_EXPERT_3, LEGAL_EXPERT_4, LEGAL_EXPERT_5 | L26: 4.5 | M26: 4.3 | N26: 4.8 | P26: 2026.05.25 | Q26: 4.5 | R26: 4.4 | S26: 4.8 | U26: 2026.05.27 | V26: 4.7 | W26: 4.4 | X26: 4.6 | Z26: 46168 | AA26: 4.5 | AB26: 4.6 | AC26: 4.6 | AE26: 46170 | AF26: 4.6 | AG26: 4.7 | AH26: 4.8 | AJ26: 2026.05.28 | AK26: =AVERAGE(L26,Q26,V26,AA26,AF26) -> 4.56 | AL26: =AVERAGE(M26,R26,W26,AB26,AG26) -> 4.48 | AM26: =AVERAGE(N26,S26,X26,AC26,AH26) -> 4.72
A27: QAC_124 | B27: Factual | C27: Easy | D27: Constitutional | E27: What are the qualifications to be an elector in Sri Lanka? | F27: Article 88 provides that every person shall, unless disqualified, be qualified to be an elector at the election of the President and of the Members of Parliament or to vote at any Referendum. However, no such person shall be entitled to vote unless their name is entered in the appropriate register of electors. | G27: Article 88 | H27: Art. 88: Every person shall, unless disqualified as elector hereinafter provided, be qualified to be an elector at the election of the President and of the Members of Parliament or to vote at any Referendum: P | I27: Human Annotated | J27: =MAX(P27,U27,Z27,AE27,AJ27) -> 46170 | K27: LEGAL_EXPERT_1, LEGAL_EXPERT_2, LEGAL_EXPERT_3, LEGAL_EXPERT_4, LEGAL_EXPERT_5 | L27: 4.5 | M27: 4.3 | N27: 4.8 | P27: 2026.05.25 | Q27: 4.5 | R27: 4.3 | S27: 4.8 | U27: 2026.05.27 | V27: 4.7 | W27: 4.4 | X27: 4.6 | Z27: 46168 | AA27: 4.5 | AB27: 4.5 | AC27: 4.5 | AE27: 46170 | AF27: 4.5 | AG27: 4.8 | AH27: 4.7 | AJ27: 2026.05.28 | AK27: =AVERAGE(L27,Q27,V27,AA27,AF27) -> 4.54 | AL27: =AVERAGE(M27,R27,W27,AB27,AG27) -> 4.46 | AM27: =AVERAGE(N27,S27,X27,AC27,AH27) -> 4.68
A28: QAC_125 | B28: Factual | C28: Medium | D28: Constitutional | E28: What grounds disqualify a person from being an elector? | F28: Article 89 provides that no person shall be qualified to be an elector at an election of the President or Members of Parliament, or to vote at any Referendum, if they are not a citizen of Sri Lanka, are detained as unsound of mind, have been convicted of certain offences, or are otherwise disqualified under the law relating to elections. | G28: Article 89 | H28: Art. 89: No person shall be qualified to be an elector to be an elector at an election of the President, or of the Members of Parliament or to vote at any Referendum, if he is subject to any of the following d | I28: Human Annotated | J28: =MAX(P28,U28,Z28,AE28,AJ28) -> 46170 | K28: LEGAL_EXPERT_1, LEGAL_EXPERT_2, LEGAL_EXPERT_3, LEGAL_EXPERT_4, LEGAL_EXPERT_5 | L28: 4.5 | M28: 4.3 | N28: 4.8 | P28: 2026.05.25 | Q28: 4.4 | R28: 4.3 | S28: 4.8 | U28: 2026.05.27 | V28: 4.7 | W28: 4.3 | X28: 4.6 | Z28: 46168 | AA28: 4.7 | AB28: 4.5 | AC28: 4.7 | AE28: 46170 | AF28: 4.5 | AG28: 4.7 | AH28: 4.6 | AJ28: 2026.05.28 | AK28: =AVERAGE(L28,Q28,V28,AA28,AF28) -> 4.56 | AL28: =AVERAGE(M28,R28,W28,AB28,AG28) -> 4.42 | AM28: =AVERAGE(N28,S28,X28,AC28,AH28) -> 4.7
A29: QAC_126 | B29: Factual | C29: Medium | D29: Constitutional | E29: What are the qualifications required to be elected as a Member of Parliament? | F29: Article 90 provides that every person who is qualified to be an elector shall be qualified to be elected as a Member of Parliament unless they are subject to any of the disqualifications specified in Article 91. The basic qualification therefore derives from the right to vote, subject to additional specific disqualifications. | G29: Article 90 | H29: Art. 90: Every person who is qualified to be an for election as elector shall be qualified to be elected as a Member of a Member of Parliament unless he is disqualified under the provisions Parliament of Artic | I29: Human Annotated | J29: =MAX(P29,U29,Z29,AE29,AJ29) -> 46170 | K29: LEGAL_EXPERT_1, LEGAL_EXPERT_2, LEGAL_EXPERT_3, LEGAL_EXPERT_4, LEGAL_EXPERT_5 | L29: 4.5 | M29: 4.3 | N29: 4.8 | P29: 2026.05.25 | Q29: 4.5 | R29: 4.3 | S29: 4.8 | U29: 2026.05.27 | V29: 4.8 | W29: 4.5 | X29: 4.5 | Z29: 46168 | AA29: 4.4 | AB29: 4.5 | AC29: 4.6 | AE29: 46170 | AF29: 4.6 | AG29: 4.7 | AH29: 4.8 | AJ29: 2026.05.28 | AK29: =AVERAGE(L29,Q29,V29,AA29,AF29) -> 4.56 | AL29: =AVERAGE(M29,R29,W29,AB29,AG29) -> 4.46 | AM29: =AVERAGE(N29,S29,X29,AC29,AH29) -> 4.7
A30: QAC_127 | B30: Factual | C30: Medium | D30: Constitutional | E30: What are the qualifications required to be elected President of Sri Lanka? | F30: Article 92 provides that every person who is qualified to be an elector shall be qualified to be elected to the office of President unless they are subject to certain disqualifications, including: not having attained the age of thirty years; not being qualified to be elected as a Member of Parliament; or having been twice elected to the office of President. | G30: Article 92 | H30: Art. 92: Every person who is qualified to be an President elector shall be qualified to be elected to the office of President unless he is subject to any of the following disqualifications (a) if he has not a | I30: Human Annotated | J30: =MAX(P30,U30,Z30,AE30,AJ30) -> 46170 | K30: LEGAL_EXPERT_1, LEGAL_EXPERT_2, LEGAL_EXPERT_3, LEGAL_EXPERT_4, LEGAL_EXPERT_5 | L30: 4.5 | M30: 4.3 | N30: 4.8 | P30: 2026.05.25 | Q30: 4.5 | R30: 4.3 | S30: 4.7 | U30: 2026.05.27 | V30: 4.6 | W30: 4.3 | X30: 4.5 | Z30: 46168 | AA30: 4.5 | AB30: 4.5 | AC30: 4.5 | AE30: 46170 | AF30: 4.5 | AG30: 4.8 | AH30: 4.7 | AJ30: 2026.05.28 | AK30: =AVERAGE(L30,Q30,V30,AA30,AF30) -> 4.52 | AL30: =AVERAGE(M30,R30,W30,AB30,AG30) -> 4.44 | AM30: =AVERAGE(N30,S30,X30,AC30,AH30) -> 4.64
A31: QAC_128 | B31: Factual | C31: Easy | D31: Constitutional | E31: What principles govern the voting process for the election of the President and Members of Parliament? | F31: Article 93 provides that the voting for the election of the President and of Members of Parliament and at any Referendum shall be free, equal and secret. This guarantees universal suffrage conducted by secret ballot, consistent with the fundamental democratic principles of the Constitution. | G31: Article 93 | H31: Art. 93: The voting for the election of the President of the free, equal and secret Republic and of the Members of Parliament and at any Referendum shall be free, equal and by secret ballot. Election | I31: Human Annotated | J31: =MAX(P31,U31,Z31,AE31,AJ31) -> 46170 | K31: LEGAL_EXPERT_1, LEGAL_EXPERT_2, LEGAL_EXPERT_3, LEGAL_EXPERT_4, LEGAL_EXPERT_5 | L31: 4.5 | M31: 4.3 | N31: 4.8 | P31: 2026.05.25 | Q31: 4.5 | R31: 4.3 | S31: 4.8 | U31: 2026.05.27 | V31: 4.8 | W31: 4.4 | X31: 4.6 | Z31: 46168 | AA31: 4.7 | AB31: 4.6 | AC31: 4.7 | AE31: 46170 | AF31: 4.5 | AG31: 4.7 | AH31: 4.6 | AJ31: 2026.05.28 | AK31: =AVERAGE(L31,Q31,V31,AA31,AF31) -> 4.6 | AL31: =AVERAGE(M31,R31,W31,AB31,AG31) -> 4.46 | AM31: =AVERAGE(N31,S31,X31,AC31,AH31) -> 4.7
... A53: QAC_150 | B53: Factual | C53: Medium | D53: Constitutional | E53: What jurisdiction does the Supreme Court have in the interpretation of the Constitution? | F53: Article 125 grants the Supreme Court sole and exclusive jurisdiction to hear and determine any question relating to the interpretation of the Constitution. Whenever any such question arises in the course of any proceedings in any court or tribunal, that court or tribunal shall refer the question to the Supreme Court for determination. | G53: Article 125 | H53: Art. 125: (1) The Supreme Court shall have sole and Constitutional exclusive jurisdiction to hear and determine any question jurisdiction in the relating to the interpretation of the Constitution and interpreta | I53: Human Annotated | J53: =MAX(P53,U53,Z53,AE53,AJ53) -> 46170 | K53: LEGAL_EXPERT_1, LEGAL_EXPERT_2, LEGAL_EXPERT_3, LEGAL_EXPERT_4, LEGAL_EXPERT_5 | L53: 4.5 | M53: 4.3 | N53: 4.8 | P53: 2026.05.25 | Q53: 4.5 | R53: 4.3 | S53: 4.8 | U53: 2026.05.27 | V53: 4.7 | W53: 4.6 | X53: 4.6 | Z53: 46168 | AA53: 4.5 | AB53: 4.5 | AC53: 4.5 | AE53: 46170 | AF53: 4.6 | AG53: 4.7 | AH53: 4.8 | AJ53: 2026.05.28 | AK53: =AVERAGE(L53,Q53,V53,AA53,AF53) -> 4.56 | AL53: =AVERAGE(M53,R53,W53,AB53,AG53) -> 4.48 | AM53: =AVERAGE(N53,S53,X53,AC53,AH53) -> 4.7

Sheet 151-200
A1: Item ID | B1: Query Type | C1: Difficulty | D1: Legal Domain | E1: Question | F1: Reference Answer | G1: Constitutional Articles | H1: Supporting Passage(s) | I1: Annotattion Type | J1: Annotation Date | K1: Reviewer IDs | L1: Reviever 1: Chathuri Madushika (LLB ousl) | Q1: Reviever 2: Rohana Dasanayaka (LLB ousl) | V1: Reviever 3: Dulani Kulasooriya (LLB ousl) | AA1: Reviever 4: Dulshan Liyanaarachchi (LLB ousl) | AF1: Reviever 5: Inoshika Kodithuwakku (LLB ousl) | AK1: Mean | AL1: Mean | AM1: Mean
L2: Reviewer ID: LEGAL_EXPERT_1 | Q2: Reviewer ID: LEGAL_EXPERT_2 | V2: Reviewer ID: LEGAL_EXPERT_3 | AA2: Reviewer ID: LEGAL_EXPERT_4 | AF2: Reviewer ID: LEGAL_EXPERT_5 | AK2: Reviewer IDs: LEGAL_EXPERT_1, LEGAL_EXPERT_2, LEGAL_EXPERT_3, LEGAL_EXPERT_4, LEGAL_EXPERT_5
L3: Correctness (1=Poor 5=Excellent) | M3: Completeness (1=Poor 5=Excellent) | N3: Clarity (1=Poor 5=Excellent) | O3: Expert Comments | P3: Review Date | Q3: Correctness (1=Poor 5=Excellent) | R3: Completeness (1=Poor 5=Excellent) | S3: Clarity (1=Poor 5=Excellent) | T3: Expert Comments | U3: Review Date | V3: Correctness (1=Poor 5=Excellent) | W3: Completeness (1=Poor 5=Excellent) | X3: Clarity (1=Poor 5=Excellent) | Y3: Expert Comments | Z3: Review Date | AA3: Correctness (1=Poor 5=Excellent) | AB3: Completeness (1=Poor 5=Excellent) | AC3: Clarity (1=Poor 5=Excellent) | AD3: Expert Comments | AE3: Review Date | AF3: Correctness (1=Poor 5=Excellent) | AG3: Completeness (1=Poor 5=Excellent) | AH3: Clarity (1=Poor 5=Excellent) | AI3: Expert Comments | AJ3: Review Date | AK3: Correctness (1=Poor 5=Excellent) | AL3: Completeness (1=Poor 5=Excellent) | AM3: Clarity (1=Poor 5=Excellent)
A4: QAC_151 | B4: Procedural | C4: Medium | D4: Constitutional | E4: How does a citizen invoke the Supreme Court's fundamental rights jurisdiction? | F4: Article 126 provides that the Supreme Court shall have sole and exclusive jurisdiction to hear and determine any question relating to the infringement or imminent infringement by executive or administrative action of any fundamental right or language right. Any person may petition the Supreme Court for relief within one month of such infringement. | G4: Article 126 | H4: Art. 126: (1) The Supreme Court shall have sole and rights exclusive jurisdiction to hear and determine any question jurisdiction and its relating to the infringement or imminent infringement by exercise execut | I4: Human Annotated | J4: =MAX(P4,U4,Z4,AE4,AJ4) -> 46170 | K4: LEGAL_EXPERT_1, LEGAL_EXPERT_2, LEGAL_EXPERT_3, LEGAL_EXPERT_4, LEGAL_EXPERT_5 | L4: 4.5 | M4: 4.1 | N4: 4.7 | P4: 2026.05.25 | Q4: 4.6 | R4: 4.3 | S4: 4.7 | U4: 2025.05.27 | V4: 4.7 | W4: 4.7 | X4: 4.6 | Z4: 46168 | AA4: 4.7 | AB4: 4.8 | AC4: 4.7 | AE4: 46170 | AF4: 4.5 | AG4: 4.7 | AH4: 4.6 | AJ4: 2026.05.28 | AK4: =AVERAGE(L4,Q4,V4,AA4,AF4) -> 4.6 | AL4: =AVERAGE(M4,R4,W4,AB4,AG4) -> 4.52 | AM4: =AVERAGE(N4,S4,X4,AC4,AH4) -> 4.66
A5: QAC_152 | B5: Factual | C5: Medium | D5: Constitutional | E5: What is the appellate jurisdiction of the Supreme Court? | F5: Article 127 provides that the Supreme Court shall, subject to the Constitution, be the final court of civil and criminal appellate jurisdiction for and within the Republic of Sri Lanka. The Court hears appeals from the Court of Appeal and such other appeals as may be prescribed by law. | G5: Article 127 | H5: Art. 127: (1) The Supreme Court shall, subject to the Appellate jurisdiction Constitution, be the final Court of civil and criminal appellate jurisdiction for and within the Republic of Sri Lanka for the correc | I5: Human Annotated | J5: =MAX(P5,U5,Z5,AE5,AJ5) -> 46170 | K5: LEGAL_EXPERT_1, LEGAL_EXPERT_2, LEGAL_EXPERT_3, LEGAL_EXPERT_4, LEGAL_EXPERT_5 | L5: 4.5 | M5: 4.1 | N5: 4.7 | P5: 2026.05.25 | Q5: 4.7 | R5: 4.3 | S5: 4.8 | U5: 2025.05.27 | V5: 4.3 | W5: 4.4 | X5: 4.6 | Z5: 46168 | AA5: 4.4 | AB5: 4.5 | AC5: 4.6 | AE5: 46170 | AF5: 4.6 | AG5: 4.5 | AH5: 4.5 | AJ5: 2026.05.28 | AK5: =AVERAGE(L5,Q5,V5,AA5,AF5) -> 4.5 | AL5: =AVERAGE(M5,R5,W5,AB5,AG5) -> 4.36 | AM5: =AVERAGE(N5,S5,X5,AC5,AH5) -> 4.64
A6: QAC_153 | B6: Factual | C6: Medium | D6: Constitutional | E6: Can the President seek an advisory opinion from the Supreme Court? | F6: Article 129 provides that if at any time it appears to the President that a question of law or fact has arisen or is likely to arise which is of such nature and of such public importance that it is expedient to obtain the opinion of the Supreme Court upon it, the President may refer that question to the Court for its opinion. | G6: Article 129 | H6: Art. 129: (1) If at any time it appears to the President of jurisdiction the Republic that a question of law or fact has arisen or is likely to arise which is of such nature and of such public importance that i | I6: Human Annotated | J6: =MAX(P6,U6,Z6,AE6,AJ6) -> 46170 | K6: LEGAL_EXPERT_1, LEGAL_EXPERT_2, LEGAL_EXPERT_3, LEGAL_EXPERT_4, LEGAL_EXPERT_5 | L6: 4.5 | M6: 4.1 | N6: 4.7 | P6: 2026.05.25 | Q6: 4.5 | R6: 4.4 | S6: 4.6 | U6: 2025.05.27 | V6: 4.6 | W6: 4.4 | X6: 4.7 | Z6: 46168 | AA6: 4.6 | AB6: 4.7 | AC6: 4.5 | AE6: 46170 | AF6: 4.7 | AG6: 4.5 | AH6: 4.6 | AJ6: 2026.05.28 | AK6: =AVERAGE(L6,Q6,V6,AA6,AF6) -> 4.58 | AL6: =AVERAGE(M6,R6,W6,AB6,AG6) -> 4.42 | AM6: =AVERAGE(N6,S6,X6,AC6,AH6) -> 4.62
A7: QAC_154 | B7: Factual | C7: Medium | D7: Constitutional | E7: What jurisdiction does the Supreme Court have over election and referendum petitions? | F7: Article 130 provides that the Supreme Court shall have the power to hear and determine and make such orders as provided by law on: (a) any legal proceeding relating to the election of the President or the validity of a Referendum; (b) any appeal from an order or judgment of the Court of Appeal in an election petition case. The hearing of a proceeding relating to the election of the President or the validity of a referendum shall be by at least five Judges of the Supreme Court. | G7: Article 130 | H7: Art. 130: The Supreme Court shall have the power to Jurisdiction in 122 [election hear and determine and make such orders as provided for and by law on referendum petitions] (a) any legal proceeding relating t | I7: Human Annotated | J7: =MAX(P7,U7,Z7,AE7,AJ7) -> 46170 | K7: LEGAL_EXPERT_1, LEGAL_EXPERT_2, LEGAL_EXPERT_3, LEGAL_EXPERT_4, LEGAL_EXPERT_5 | L7: 4.5 | M7: 4.1 | N7: 4.7 | P7: 2026.05.25 | Q7: 4.4 | R7: 4.3 | S7: 4.7 | U7: 2025.05.27 | V7: 4.7 | W7: 4.4 | X7: 4.5 | Z7: 46168 | AA7: 4.9 | AB7: 4.8 | AC7: 4.7 | AE7: 46170 | AF7: 4.5 | AG7: 4.7 | AH7: 4.6 | AJ7: 2026.05.28 | AK7: =AVERAGE(L7,Q7,V7,AA7,AF7) -> 4.6 | AL7: =AVERAGE(M7,R7,W7,AB7,AG7) -> 4.46 | AM7: =AVERAGE(N7,S7,X7,AC7,AH7) -> 4.64
A8: QAC_155 | B8: Factual | C8: Medium | D8: Constitutional | E8: What jurisdiction does the Supreme Court have in contempt proceedings? | F8: Article 131 provides that the Supreme Court shall have, according to law, the power to take cognizance of and punish any person for breaches of the privileges of Parliament, and for contempt of court in respect of any court, tribunal or institution referred to in Article 105. | G8: Article 131 | H8: Art. 131: The Supreme Court shall have according to law Jurisdiction in respect of the power to take cognizance of and punish any person for breaches of the breach of the privileges of Parliament. Parliamentary | I8: Human Annotated | J8: =MAX(P8,U8,Z8,AE8,AJ8) -> 46170 | K8: LEGAL_EXPERT_1, LEGAL_EXPERT_2, LEGAL_EXPERT_3, LEGAL_EXPERT_4, LEGAL_EXPERT_5 | L8: 4.5 | M8: 4.1 | N8: 4.7 | P8: 2026.05.25 | Q8: 4.5 | R8: 4.6 | S8: 4.7 | U8: 2025.05.27 | V8: 4.6 | W8: 4.4 | X8: 4.7 | Z8: 46168 | AA8: 4.5 | AB8: 4.4 | AC8: 4.8 | AE8: 46170 | AF8: 4.6 | AG8: 4.5 | AH8: 4.5 | AJ8: 2026.05.28 | AK8: =AVERAGE(L8,Q8,V8,AA8,AF8) -> 4.54 | AL8: =AVERAGE(M8,R8,W8,AB8,AG8) -> 4.4 | AM8: =AVERAGE(N8,S8,X8,AC8,AH8) -> 4.68
A9: QAC_156 | B9: Factual | C9: Easy | D9: Constitutional | E9: Where does the Supreme Court ordinarily exercise its jurisdiction? | F9: Article 132 provides that the several jurisdictions of the Supreme Court shall be ordinarily exercised at Colombo unless the Chief Justice otherwise directs. The jurisdiction of the Supreme Court may be exercised in different matters at the same time by the several Judges of the Court sitting apart. | G9: Article 132 | H9: Art. 132: (1) The several jurisdictions of the Supreme the Supreme Court shall be ordinarily exercised at Colombo unless the Court Chief Justice otherwise directs. (2) The jurisdiction of the Supreme Court may | I9: Human Annotated | J9: =MAX(P9,U9,Z9,AE9,AJ9) -> 46170 | K9: LEGAL_EXPERT_1, LEGAL_EXPERT_2, LEGAL_EXPERT_3, LEGAL_EXPERT_4, LEGAL_EXPERT_5 | L9: 4.5 | M9: 4.1 | N9: 4.7 | P9: 2026.05.25 | Q9: 4.7 | R9: 4.3 | S9: 4.8 | U9: 2025.05.27 | V9: 4.8 | W9: 4.4 | X9: 4.5 | Z9: 46168 | AA9: 4.7 | AB9: 4.5 | AC9: 4.5 | AE9: 46170 | AF9: 4.7 | AG9: 4.5 | AH9: 4.6 | AJ9: 2026.05.28 | AK9: =AVERAGE(L9,Q9,V9,AA9,AF9) -> 4.68 | AL9: =AVERAGE(M9,R9,W9,AB9,AG9) -> 4.36 | AM9: =AVERAGE(N9,S9,X9,AC9,AH9) -> 4.62
A10: QAC_157 | B10: Procedural | C10: Hard | D10: Constitutional | E10: What is the procedure when there is no quorum of Judges available for Supreme Court proceedings? | F10: Article 133 provides that if at any time there is no quorum of Judges of the Supreme Court available to hold or continue any sittings, the Chief Justice may with the previous consent of the President request in writing the attendance at the sittings of the Court as an ad hoc Judge of any Judge of the Court of Appeal. | G10: Article 133 | H10: Art. 133: (1) If at any time there should not be a quorum of ad hoc of the Judges of the Supreme Court available to hold or Judges continue any sittings of the Court, the Chief Justice may with the previous con | I10: Human Annotated | J10: =MAX(P10,U10,Z10,AE10,AJ10) -> 46170 | K10: LEGAL_EXPERT_1, LEGAL_EXPERT_2, LEGAL_EXPERT_3, LEGAL_EXPERT_4, LEGAL_EXPERT_5 | L10: 4.5 | M10: 4.1 | N10: 4.7 | P10: 2026.05.25 | Q10: 4.5 | R10: 4.3 | S10: 4.7 | U10: 2025.05.27 | V10: 4.9 | W10: 4.7 | X10: 4.6 | Z10: 46168 | AA10: 4.7 | AB10: 4.7 | AC10: 4.7 | AE10: 46170 | AF10: 4.5 | AG10: 4.7 | AH10: 4.6 | AJ10: 2026.05.28 | AK10: =AVERAGE(L10,Q10,V10,AA10,AF10) -> 4.62 | AL10: =AVERAGE(M10,R10,W10,AB10,AG10) -> 4.5 | AM10: =AVERAGE(N10,S10,X10,AC10,AH10) -> 4.66
A11: QAC_158 | B11: Factual | C11: Medium | D11: Constitutional | E11: What is the right of the Attorney-General to be heard in Supreme Court proceedings? | F11: Article 134 provides that the Attorney-General shall be noticed and shall have the right to be heard in all proceedings in the Supreme Court in the exercise of its jurisdiction under Articles 120, 121, 122, 125, 126, 129(1), and 130. This ensures the State's interests are represented in proceedings involving constitutional and electoral matters. | G11: Article 134 | H11: Art. 134: (1) The Attorney-General shall be noticed and Right to be have the right to be heard in all proceedings in the heard by the Supreme Supreme Court in the exercise of its jurisdiction under Court Articl | I11: Human Annotated | J11: =MAX(P11,U11,Z11,AE11,AJ11) -> 46170 | K11: LEGAL_EXPERT_1, LEGAL_EXPERT_2, LEGAL_EXPERT_3, LEGAL_EXPERT_4, LEGAL_EXPERT_5 | L11: 4.5 | M11: 4.3 | N11: 4.7 | P11: 2026.05.25 | Q11: 4.5 | R11: 4.3 | S11: 4.7 | U11: 2025.05.27 | V11: 4.8 | W11: 4.5 | X11: 4.6 | Z11: 46168 | AA11: 4.5 | AB11: 4.5 | AC11: 4.7 | AE11: 46170 | AF11: 4.6 | AG11: 4.5 | AH11: 4.5 | AJ11: 2026.05.28 | AK11: =AVERAGE(L11,Q11,V11,AA11,AF11) -> 4.58 | AL11: =AVERAGE(M11,R11,W11,AB11,AG11) -> 4.42 | AM11: =AVERAGE(N11,S11,X11,AC11,AH11) -> 4.64
A12: QAC_159 | B12: Factual | C12: Easy | D12: Constitutional | E12: Who is in charge of the Registry of the Supreme Court? | F12: Article 135 provides that the Registry of the Supreme Court shall be in charge of an officer designated the Registrar of the Supreme Court who shall be subject to the supervision, direction and control of the Chief Justice. The Registrar is responsible for the administration of the Court's registry functions. | G12: Article 135 | H12: Art. 135: The Registry of the Supreme Court shall be in Registry of the Supreme charge of an officer designated the Registrar of the Court and Supreme Court who shall be subject to the supervision, office of di | I12: Human Annotated | J12: =MAX(P12,U12,Z12,AE12,AJ12) -> 46170 | K12: LEGAL_EXPERT_1, LEGAL_EXPERT_2, LEGAL_EXPERT_3, LEGAL_EXPERT_4, LEGAL_EXPERT_5 | L12: 4.5 | M12: 4.3 | N12: 4.7 | P12: 2026.05.25 | Q12: 4.5 | R12: 4.4 | S12: 4.7 | U12: 2025.05.27 | V12: 4.5 | W12: 4.2 | X12: 4.5 | Z12: 46168 | AA12: 4.7 | AB12: 4.6 | AC12: 4.5 | AE12: 46170 | AF12: 4.7 | AG12: 4.5 | AH12: 4.6 | AJ12: 2026.05.28 | AK12: =AVERAGE(L12,Q12,V12,AA12,AF12) -> 4.58 | AL12: =AVERAGE(M12,R12,W12,AB12,AG12) -> 4.4 | AM12: =AVERAGE(N12,S12,X12,AC12,AH12) -> 4.6
A13: QAC_160 | B13: Procedural | C13: Medium | D13: Constitutional | E13: How are the Rules of the Supreme Court made? | F13: Article 136 provides that, subject to the provisions of the Constitution and of any law, the Chief Justice with any three Judges of the Supreme Court may make rules regulating the exercise by the Court of its jurisdiction and the practice and procedure of the Court. | G13: Article 136 | H13: Art. 136: (1) Subject to the provisions of the R u l es of the Supreme Constitution and of any law the Chief Justice with any Court three Judges of the Supreme Court nominated by him, may, from time to time, ma | I13: Human Annotated | J13: =MAX(P13,U13,Z13,AE13,AJ13) -> 46170 | K13: LEGAL_EXPERT_1, LEGAL_EXPERT_2, LEGAL_EXPERT_3, LEGAL_EXPERT_4, LEGAL_EXPERT_5 | L13: 4.5 | M13: 4.3 | N13: 4.7 | P13: 2026.05.25 | Q13: 4.5 | R13: 4.3 | S13: 4.7 | U13: 2025.05.27 | V13: 4.6 | W13: 4.5 | X13: 4.6 | Z13: 46168 | AA13: 4.5 | AB13: 4.5 | AC13: 4.5 | AE13: 46170 | AF13: 4.5 | AG13: 4.7 | AH13: 4.6 | AJ13: 2026.05.28 | AK13: =AVERAGE(L13,Q13,V13,AA13,AF13) -> 4.52 | AL13: =AVERAGE(M13,R13,W13,AB13,AG13) -> 4.46 | AM13: =AVERAGE(N13,S13,X13,AC13,AH13) -> 4.62
A14: QAC_161 | B14: Factual | C14: Easy | D14: Constitutional | E14: How many Judges compose the Court of Appeal? | F14: Article 137 provides that the Court of Appeal shall consist of the President of the Court of Appeal and not less than six and not more than nineteen other Judges who shall be appointed by the President of the Republic. The President of the Court of Appeal shall preside over its proceedings. | G14: Article 137 | H14: Art. 137: The Court of Appeal shall consist of the Appeal President of the Court of Appeal and not less than six and not more than 127[nineteen] other Judges who shall be appointed as provided in Article | I14: Human Annotated | J14: =MAX(P14,U14,Z14,AE14,AJ14) -> 46170 | K14: LEGAL_EXPERT_1, LEGAL_EXPERT_2, LEGAL_EXPERT_3, LEGAL_EXPERT_4, LEGAL_EXPERT_5 | L14: 4.5 | M14: 4.3 | N14: 4.7 | P14: 2026.05.25 | Q14: 4.6 | R14: 4.3 | S14: 4.8 | U14: 2025.05.27 | V14: 4.5 | W14: 4.4 | X14: 4.6 | Z14: 46168 | AA14: 4.4 | AB14: 4.6 | AC14: 4.6 | AE14: 46170 | AF14: 4.6 | AG14: 4.5 | AH14: 4.5 | AJ14: 2026.05.28 | AK14: =AVERAGE(L14,Q14,V14,AA14,AF14) -> 4.52 | AL14: =AVERAGE(M14,R14,W14,AB14,AG14) -> 4.42 | AM14: =AVERAGE(N14,S14,X14,AC14,AH14) -> 4.64
A15: QAC_162 | B15: Factual | C15: Medium | D15: Constitutional | E15: What powers does the Court of Appeal have to examine records of lower courts? | F15: Article 140 provides that the Court of Appeal shall have full power and authority to inspect and examine the records of any Court of First Instance or tribunal or other institution and grant and issue, according to law, orders in the nature of writs of certiorari, prohibition, mandamus, quo warranto and procedendo, except writs of habeas corpus. | G15: Article 140 | H15: Art. 140: Subject to the provisions of the Constitution, the Power to issue writs, other Court of Appeal shall have full power and authority to than writs of inspect and examine the records of any Court of Firs | I15: Human Annotated | J15: =MAX(P15,U15,Z15,AE15,AJ15) -> 46170 | K15: LEGAL_EXPERT_1, LEGAL_EXPERT_2, LEGAL_EXPERT_3, LEGAL_EXPERT_4, LEGAL_EXPERT_5 | L15: 4.5 | M15: 4.3 | N15: 4.7 | P15: 2026.05.25 | Q15: 4.5 | R15: 4.3 | S15: 4.7 | U15: 2025.05.27 | V15: 4.6 | W15: 4.5 | X15: 4.7 | Z15: 46168 | AA15: 4.7 | AB15: 4.6 | AC15: 4.5 | AE15: 46170 | AF15: 4.7 | AG15: 4.5 | AH15: 4.6 | AJ15: 2026.05.28 | AK15: =AVERAGE(L15,Q15,V15,AA15,AF15) -> 4.6 | AL15: =AVERAGE(M15,R15,W15,AB15,AG15) -> 4.44 | AM15: =AVERAGE(N15,S15,X15,AC15,AH15) -> 4.64
... A18: QAC_165 | B18: Factual | C18: Medium | D18: Constitutional | E18: Can the Court of Appeal grant injunctions to prevent irreparable harm? | F18: Article 143 provides that the Court of Appeal shall have the power to grant and issue injunctions to prevent any irremediable mischief which might ensue before a party making an application for such injunction could prevent the same by bringing an action in any Court of First Instance. This jurisdiction protects parties from irreversible harm pending substantive proceedings. | G18: Article 143 | H18: Art. 143: The Court of Appeal shall have the power to grant grant and issue injunctions to prevent any irremediable injunction mischief which might ensure before a party making an application for such injunctio | I18: Human Annotated | J18: =MAX(P18,U18,Z18,AE18,AJ18) -> 46170 | K18: LEGAL_EXPERT_1, LEGAL_EXPERT_2, LEGAL_EXPERT_3, LEGAL_EXPERT_4, LEGAL_EXPERT_5 | L18: 4.5 | M18: 4.3 | N18: 4.7 | P18: 2026.05.25 | Q18: 4.7 | R18: 4.3 | S18: 4.7 | U18: 2025.05.27 | V18: 4.5 | W18: 4.4 | X18: 4.5 | Z18: 46168 | AA18: 4.4 | AB18: 4.5 | AC18: 4.4 | AE18: 46170 | AF18: 4.7 | AG18: 4.5 | AH18: 4.6 | AJ18: 2026.05.28 | AK18: =AVERAGE(L18,Q18,V18,AA18,AF18) -> 4.56 | AL18: =AVERAGE(M18,R18,W18,AB18,AG18) -> 4.4 | AM18: =AVERAGE(N18,S18,X18,AC18,AH18) -> 4.58
A19: QAC_166 | B19: Factual | C19: Medium | D19: Constitutional | E19: What jurisdiction does the Court of Appeal have over parliamentary election petitions? | F19: Article 144 provides that the Court of Appeal shall have and exercise jurisdiction to try election petitions in respect of elections to Parliament. The Court shall have the power to make such orders as provided by law to determine the validity of elections and grant appropriate relief. | G19: Article 144 | H19: Art. 144: The Court of Appeal shall have and exercise Parliamentary jurisdiction to try election petitions in respect of the election petitions election to the membership of Parliament in terms of any law for t | I19: Human Annotated | J19: =MAX(P19,U19,Z19,AE19,AJ19) -> 46170 | K19: LEGAL_EXPERT_1, LEGAL_EXPERT_2, LEGAL_EXPERT_3, LEGAL_EXPERT_4, LEGAL_EXPERT_5 | L19: 4.5 | M19: 4.3 | N19: 4.7 | P19: 2026.05.25 | Q19: 4.5 | R19: 4.3 | S19: 4.8 | U19: 2025.05.27 | V19: .4.7 | W19: 4.3 | X19: 4.6 | Z19: 46168 | AA19: 4.8 | AB19: 4.5 | AC19: 4.5 | AE19: 46170 | AF19: 4.5 | AG19: 4.7 | AH19: 4.6 | AJ19: 2026.05.28 | AK19: =AVERAGE(L19,Q19,V19,AA19,AF19) -> 4.575 | AL19: =AVERAGE(M19,R19,W19,AB19,AG19) -> 4.42 | AM19: =AVERAGE(N19,S19,X19,AC19,AH19) -> 4.64
A20: QAC_167 | B20: Factual | C20: Medium | D20: Constitutional | E20: Can the Court of Appeal inspect records of lower courts on its own motion? | F20: Article 145 provides that the Court of Appeal may, ex mero motu or on any application made, call for, inspect and examine any record of any Court of First Instance and in the exercise of its revisionary powers may make any order thereon as the interests of justice may require. This gives the Court broad supervisory jurisdiction. | G20: Article 145 | H20: Art. 145: The Court of Appeal may, ex mero motu or on Inspection of any application made, call for, inspect and examine any records record of any Court of First Instance and in the exercise of its revisionary p | I20: Human Annotated | J20: =MAX(P20,U20,Z20,AE20,AJ20) -> 46170 | K20: LEGAL_EXPERT_1, LEGAL_EXPERT_2, LEGAL_EXPERT_3, LEGAL_EXPERT_4, LEGAL_EXPERT_5 | L20: 4.5 | M20: 4.3 | N20: 4.7 | P20: 2026.05.25 | Q20: 4.5 | R20: 4.3 | S20: 4.7 | U20: 2025.05.27 | V20: 4.8 | W20: 4.4 | X20: 4.6 | Z20: 46168 | AA20: 4.6 | AB20: 4.5 | AC20: 4.4 | AE20: 46170 | AF20: 4.6 | AG20: 4.5 | AH20: 4.5 | AJ20: 2026.05.28 | AK20: =AVERAGE(L20,Q20,V20,AA20,AF20) -> 4.6 | AL20: =AVERAGE(M20,R20,W20,AB20,AG20) -> 4.4 | AM20: =AVERAGE(N20,S20,X20,AC20,AH20) -> 4.58
A21: QAC_168 | B21: Factual | C21: Easy | D21: Constitutional | E21: Who manages the Registry of the Court of Appeal? | F21: Article 147 provides that the Registry of the Court of Appeal shall be in charge of an officer designated as the Registrar of the Court of Appeal. The Registrar shall be subject to the supervision, direction and control of the President of the Court of Appeal and is responsible for the administration of the Court's registry. | G21: Article 147 | H21: Art. 147: The Registry of the Court of Appeal shall be the Court of in charge of an officer designated as the Registrar of the Appeal and office of Court of Appeal who shall be subject to the supervision, Regis | I21: Human Annotated | J21: =MAX(P21,U21,Z21,AE21,AJ21) -> 46170 | K21: LEGAL_EXPERT_1, LEGAL_EXPERT_2, LEGAL_EXPERT_3, LEGAL_EXPERT_4, LEGAL_EXPERT_5 | L21: 4.5 | M21: 4.3 | N21: 4.7 | P21: 2026.05.25 | Q21: 4.6 | R21: 4.3 | S21: 4.7 | U21: 2025.05.27 | V21: 4.7 | W21: 4.4 | X21: 4.7 | Z21: 46168 | AA21: 4.7 | AB21: 4.7 | AC21: 4.7 | AE21: 46170 | AF21: 4.7 | AG21: 4.5 | AH21: 4.6 | AJ21: 2026.05.28 | AK21: =AVERAGE(L21,Q21,V21,AA21,AF21) -> 4.64 | AL21: =AVERAGE(M21,R21,W21,AB21,AG21) -> 4.44 | AM21: =AVERAGE(N21,S21,X21,AC21,AH21) -> 4.68
A22: QAC_169 | B22: Factual | C22: Medium | D22: Constitutional | E22: What must Parliament provide for in relation to Provincial Councils? | F22: Article 154Q provides that Parliament shall by law provide for: (a) the election of members of Provincial Councils and the qualifications for membership; (b) the procedure for transaction of business by every such Council; (c) the salaries and allowances of members; and (d) such other matters as Parliament may consider necessary for the proper functioning of Provincial Councils. | G22: Article 154Q | H22: Art. 154Q: Functions, 154Q. Parliament shall by law provide for powers, election, & c. of Provincial (a) the election of members of Provincial Councils Councils and the qualifications for membership of such Cou | I22: Human Annotated | J22: =MAX(P22,U22,Z22,AE22,AJ22) -> 46170 | K22: LEGAL_EXPERT_1, LEGAL_EXPERT_2, LEGAL_EXPERT_3, LEGAL_EXPERT_4, LEGAL_EXPERT_5 | L22: 4.5 | M22: 4.3 | N22: 4.7 | P22: 2026.05.25 | Q22: 4.5 | R22: 4.3 | S22: 4.7 | U22: 2025.05.27 | V22: 4.6 | W22: 4.5 | X22: 4.6 | Z22: 46168 | AA22: 4.5 | AB22: 4.4 | AC22: 4.5 | AE22: 46170 | AF22: 4.5 | AG22: 4.7 | AH22: 4.6 | AJ22: 2026.05.28 | AK22: =AVERAGE(L22,Q22,V22,AA22,AF22) -> 4.52 | AL22: =AVERAGE(M22,R22,W22,AB22,AG22) -> 4.44 | AM22: =AVERAGE(N22,S22,X22,AC22,AH22) -> 4.62
A23: QAC_170 | B23: Factual | C23: Medium | D23: Constitutional | E23: What is the Contingencies Fund and for what purpose may it be used? | F23: Article 151 provides that, notwithstanding any provision of Article 149, Parliament may by law create a Contingencies Fund for the purpose of providing for urgent and unforeseen expenditure. The Minister in charge of Finance, if satisfied that there is need for such expenditure and that no provision exists for it, may, with the consent of the President, authorise advances from the Contingencies Fund. Such advances must be followed by provision being made for such expenditure by Parliament at the earliest opportunity. | G23: Article 151 | H23: Art. 151: (1) Notwithstanding any of the provisions of Fund Article 149, Parliament may by law create a Contingencies Fund for the purpose of providing for urgent and unforeseen expenditure. (2) The Minister in | I23: Human Annotated | J23: =MAX(P23,U23,Z23,AE23,AJ23) -> 46170 | K23: LEGAL_EXPERT_1, LEGAL_EXPERT_2, LEGAL_EXPERT_3, LEGAL_EXPERT_4, LEGAL_EXPERT_5 | L23: 4.5 | M23: 4.3 | N23: 4.7 | P23: 2026.05.25 | Q23: 4.5 | R23: 4.3 | S23: 4.8 | U23: 2025.05.27 | V23: 4.7 | W23: 4.3 | X23: 4.5 | Z23: 46168 | AA23: 4.4 | AB23: 4.3 | AC23: 4.3 | AE23: 46170 | AF23: 4.6 | AG23: 4.5 | AH23: 4.5 | AJ23: 2026.05.28 | AK23: =AVERAGE(L23,Q23,V23,AA23,AF23) -> 4.54 | AL23: =AVERAGE(M23,R23,W23,AB23,AG23) -> 4.34 | AM23: =AVERAGE(N23,S23,X23,AC23,AH23) -> 4.56
A24: QAC_171 | B24: Procedural | C24: Medium | D24: Constitutional | E24: What special procedure applies to Bills authorising expenditure from the Consolidated Fund? | F24: Article 152 provides that no Bill or motion authorising the disposal of or the imposition of charges upon the Consolidated Fund or other funds of the Republic, or the imposition of any tax or the repeal, augmentation or reduction of any tax for the time being in force, shall be introduced in Parliament except by a Minister, and unless such Bill or motion has been approved by the Cabinet of Ministers. | G24: Article 152 | H24: Art. 152: No Bill or motion, authorizing the disposal of, or provisions the imposition of charges upon, the Consolidated Fund or as to Bills other funds of the Republic, or the imposition of any tax or affectin | I24: Human Annotated | J24: =MAX(P24,U24,Z24,AE24,AJ24) -> 46170 | K24: LEGAL_EXPERT_1, LEGAL_EXPERT_2, LEGAL_EXPERT_3, LEGAL_EXPERT_4, LEGAL_EXPERT_5 | L24: 4.5 | M24: 4.3 | N24: 4.7 | P24: 2026.05.25 | Q24: 4.5 | R24: 4.3 | S24: 4.7 | U24: 2025.05.27 | V24: 4.8 | W24: 4.3 | X24: 4.5 | Z24: 46168 | AA24: 4.5 | AB24: 4.5 | AC24: 4.5 | AE24: 46170 | AF24: 4.7 | AG24: 4.5 | AH24: 4.6 | AJ24: 2026.05.28 | AK24: =AVERAGE(L24,Q24,V24,AA24,AF24) -> 4.6 | AL24: =AVERAGE(M24,R24,W24,AB24,AG24) -> 4.38 | AM24: =AVERAGE(N24,S24,X24,AC24,AH24) -> 4.6
A25: QAC_172 | B25: Factual | C25: Medium | D25: Constitutional | E25: How are Provincial Councils established under the Constitution? | F25: Article 154A provides that, subject to the provisions of the Constitution, a Provincial Council shall be established for every Province specified in the Eighth Schedule with effect from such date or dates as the President may appoint by Order published in the Gazette. Different dates may be appointed for different Provinces. | G25: Article 154A | H25: Art. 154A: (1) Subject to the provisions of the E s tablishment Constitution, a Provincial Council shall be established for of Provincial Councils every Province specified in the Eighth Schedule with effect from | I25: Human Annotated | J25: =MAX(P25,U25,Z25,AE25,AJ25) -> 46170 | K25: LEGAL_EXPERT_1, LEGAL_EXPERT_2, LEGAL_EXPERT_3, LEGAL_EXPERT_4, LEGAL_EXPERT_5 | L25: 4.5 | M25: 4.3 | N25: 4.7 | P25: 2026.05.25 | Q25: 4.4 | R25: 4.3 | S25: 4.7 | U25: 2025.05.27 | V25: 4.8 | W25: 4.4 | X25: 4.6 | Z25: 46168 | AA25: 4.6 | AB25: 4.6 | AC25: 4.7 | AE25: 46170 | AF25: 4.5 | AG25: 4.7 | AH25: 4.6 | AJ25: 2026.05.28 | AK25: =AVERAGE(L25,Q25,V25,AA25,AF25) -> 4.56 | AL25: =AVERAGE(M25,R25,W25,AB25,AG25) -> 4.46 | AM25: =AVERAGE(N25,S25,X25,AC25,AH25) -> 4.66
A26: QAC_173 | B26: Factual | C26: Medium | D26: Constitutional | E26: What is the role of the Governor of a Province? | F26: Article 154B provides that there shall be a Governor for each Province for which a Provincial Council has been established. The Governor shall be appointed by the President and shall hold office during the pleasure of the President. The Governor is the representative of the President in the Province and exercises executive powers on the President's behalf. | G26: Article 154B | H26: Art. 154B: (1) There shall be a Governor for each Governor Province for which a Provincial Council has been established in accordance with Article | I26: Human Annotated | J26: =MAX(P26,U26,Z26,AE26,AJ26) -> 46170 | K26: LEGAL_EXPERT_1, LEGAL_EXPERT_2, LEGAL_EXPERT_3, LEGAL_EXPERT_4, LEGAL_EXPERT_5 | L26: 4.5 | M26: 4.3 | N26: 4.7 | P26: 2026.05.25 | Q26: 4.5 | R26: 4.3 | S26: 4.7 | U26: 2025.05.27 | V26: 4.7 | W26: 4.4 | X26: 4.6 | Z26: 46168 | AA26: 4.5 | AB26: 4.6 | AC26: 4.6 | AE26: 46170 | AF26: 4.6 | AG26: 4.5 | AH26: 4.5 | AJ26: 2026.05.28 | AK26: =AVERAGE(L26,Q26,V26,AA26,AF26) -> 4.56 | AL26: =AVERAGE(M26,R26,W26,AB26,AG26) -> 4.42 | AM26: =AVERAGE(N26,S26,X26,AC26,AH26) -> 4.62
A27: QAC_174 | B27: Factual | C27: Hard | D27: Constitutional | E27: What is the constitutional basis for public security and emergency regulations? | F27: Article 155 provides that the Public Security Ordinance as amended and in force immediately prior to the commencement of the Constitution shall be deemed to be a law enacted by Parliament. The power to make emergency regulations under the Public Security Ordinance or the law for the time being in force relating to public security shall include the power to make regulations having the legal effect of overriding, suspending or amending any law. | G27: Article 155 | H27: Art. 155: (1) The Public Security Ordinance as amended Public Security and in force immediately prior to the commencement of the Constitution shall be deemed to be a law enacted by Parliament. (2) The power to | I27: Human Annotated | J27: =MAX(P27,U27,Z27,AE27,AJ27) -> 46170 | K27: LEGAL_EXPERT_1, LEGAL_EXPERT_2, LEGAL_EXPERT_3, LEGAL_EXPERT_4, LEGAL_EXPERT_5 | L27: 4.5 | M27: 4.3 | N27: 4.7 | P27: 2026.05.25 | Q27: 4.5 | R27: 4.4 | S27: 4.7 | U27: 2025.05.27 | V27: 4.7 | W27: 4.4 | X27: 4.6 | Z27: 46168 | AA27: 4.5 | AB27: 4.5 | AC27: 4.5 | AE27: 46170 | AF27: 4.7 | AG27: 4.5 | AH27: 4.6 | AJ27: 2026.05.28 | AK27: =AVERAGE(L27,Q27,V27,AA27,AF27) -> 4.58 | AL27: =AVERAGE(M27,R27,W27,AB27,AG27) -> 4.42 | AM27: =AVERAGE(N27,S27,X27,AC27,AH27) -> 4.62
A28: QAC_175 | B28: Factual | C28: Medium | D28: Constitutional | E28: What is the Parliamentary Commissioner for Administration (Ombudsman)? | F28: Article 156 provides that Parliament shall by law provide for the establishment of the office of the Parliamentary Commissioner for Administration (Ombudsman), charged with the duty of investigating and reporting upon complaints or allegations of the infringement of fundamental rights and other injustices by officers and authorities of the Government. | G28: Article 156 | H28: Art. 156: (1) Parliament shall by law provide for the Commissioner establishment of the office of the Parliamentary for Administration Commissioner for Administration (Ombudsman) charged with the duty of invest | I28: Human Annotated | J28: =MAX(P28,U28,Z28,AE28,AJ28) -> 46170 | K28: LEGAL_EXPERT_1, LEGAL_EXPERT_2, LEGAL_EXPERT_3, LEGAL_EXPERT_4, LEGAL_EXPERT_5 | L28: 4.5 | M28: 4.3 | N28: 4.7 | P28: 2026.05.25 | Q28: 4.5 | R28: 4.3 | S28: 4.7 | U28: 2025.05.27 | V28: 4.7 | W28: 4.3 | X28: 4.6 | Z28: 46168 | AA28: 4.7 | AB28: 4.5 | AC28: 4.7 | AE28: 46170 | AF28: 4.5 | AG28: 4.7 | AH28: 4.6 | AJ28: 2026.05.28 | AK28: =AVERAGE(L28,Q28,V28,AA28,AF28) -> 4.58 | AL28: =AVERAGE(M28,R28,W28,AB28,AG28) -> 4.42 | AM28: =AVERAGE(N28,S28,X28,AC28,AH28) -> 4.66
A29: QAC_176 | B29: Interpretive | C29: Hard | D29: Constitutional | E29: Under what conditions can a Treaty or Agreement between Sri Lanka and a foreign government bind future Parliaments? | F29: Article 157 provides that where Parliament by resolution passed by not less than two-thirds of the whole number of Members of Parliament approves as being essential for the development of the national economy, any Treaty or Agreement between the Government of Sri Lanka and the Government of a foreign State or international organisation, such Treaty shall have the force of law in Sri Lanka. | G29: Article 157 | H29: Art. 157: Where Parliament by resolution passed by not Treaties and less than two-thirds of the whole number of Members of Agreements Parliament (including those not present) voting in its favour, approves as b | I29: Human Annotated | J29: =MAX(P29,U29,Z29,AE29,AJ29) -> 46170 | K29: LEGAL_EXPERT_1, LEGAL_EXPERT_2, LEGAL_EXPERT_3, LEGAL_EXPERT_4, LEGAL_EXPERT_5 | L29: 4.5 | M29: 4.3 | N29: 4.7 | P29: 2026.05.25 | Q29: 4.5 | R29: 4.7 | S29: 4.7 | U29: 2025.05.27 | V29: 4.8 | W29: 4.5 | X29: 4.5 | Z29: 46168 | AA29: 4.4 | AB29: 4.5 | AC29: 4.6 | AE29: 46170 | AF29: 4.6 | AG29: 4.5 | AH29: 4.5 | AJ29: 2026.05.28 | AK29: =AVERAGE(L29,Q29,V29,AA29,AF29) -> 4.56 | AL29: =AVERAGE(M29,R29,W29,AB29,AG29) -> 4.5 | AM29: =AVERAGE(N29,S29,X29,AC29,AH29) -> 4.6
A30: QAC_177 | B30: Interpretive | C30: Hard | D30: Constitutional | E30: What are the rules regarding delegation of constitutional powers? | F30: Article 158 provides that where any person is empowered under the provisions of the Constitution to delegate any power, duty or function to any other person, such person delegating the power may, notwithstanding such delegation, still exercise, perform or discharge such power, duty or function. Delegation under the Constitution does not extinguish the delegator's own authority. | G30: Article 158 | H30: Art. 158: Where any person is empowered under the Delegation provisions of the Constitution to delegate any power, duty or function to any other person, such person delegating such power, duty or function may, | I30: Human Annotated | J30: =MAX(P30,U30,Z30,AE30,AJ30) -> 46170 | K30: LEGAL_EXPERT_1, LEGAL_EXPERT_2, LEGAL_EXPERT_3, LEGAL_EXPERT_4, LEGAL_EXPERT_5 | L30: 4.5 | M30: 4.3 | N30: 4.7 | P30: 2026.05.25 | Q30: 4.5 | R30: 4.3 | S30: 4.7 | U30: 2025.05.27 | V30: 4.6 | W30: 4.3 | X30: 4.5 | Z30: 46168 | AA30: 4.5 | AB30: 4.5 | AC30: 4.5 | AE30: 46170 | AF30: 4.7 | AG30: 4.5 | AH30: 4.6 | AJ30: 2026.05.28 | AK30: =AVERAGE(L30,Q30,V30,AA30,AF30) -> 4.56 | AL30: =AVERAGE(M30,R30,W30,AB30,AG30) -> 4.38 | AM30: =AVERAGE(N30,S30,X30,AC30,AH30) -> 4.6
A31: QAC_178 | B31: Procedural | C31: Medium | D31: Constitutional | E31: What happens when the Speaker is unable to discharge the functions of office? | F31: Article 159 provides that where the Speaker is unable to discharge the functions of office, the powers, duties and functions conferred on or assigned to the Speaker by any provision of the Constitution (other than Articles 31(4), 37, 38(2)(b), 39(2), and 40) may be exercised by the Deputy Speaker. | G31: Article 159 | H31: Art. 159: Where the Speaker is unable to discharge the Deputy Speaker to act for functions of his office, the powers, duties and functions Speaker conferred or imposed on, or assigned to, the Speaker by any Pro | I31: Human Annotated | J31: =MAX(P31,U31,Z31,AE31,AJ31) -> 46170 | K31: LEGAL_EXPERT_1, LEGAL_EXPERT_2, LEGAL_EXPERT_3, LEGAL_EXPERT_4, LEGAL_EXPERT_5 | L31: 4.5 | M31: 4.3 | N31: 4.7 | P31: 2026.05.25 | Q31: 4.5 | R31: 4.6 | S31: 4.7 | U31: 2025.05.27 | V31: 4.8 | W31: 4.4 | X31: 4.6 | Z31: 46168 | AA31: 4.7 | AB31: 4.6 | AC31: 4.7 | AE31: 46170 | AF31: 4.5 | AG31: 4.7 | AH31: 4.6 | AJ31: 2026.05.28 | AK31: =AVERAGE(L31,Q31,V31,AA31,AF31) -> 4.6 | AL31: =AVERAGE(M31,R31,W31,AB31,AG31) -> 4.52 | AM31: =AVERAGE(N31,S31,X31,AC31,AH31) -> 4.66
... A53: QAC_200 | B53: Factual | C53: Easy | D53: Constitutional | E53: How are the expenses of the Constitutional Council funded? | F53: Article 41H provides that the expenses incurred by the Constitutional Council shall be charged on the Consolidated Fund. | G53: Article 41H | H53: Art. 41H: The expenses incurred by the Council shall be be charged charged on the Consolidated Fund. on the Consolidated Fund The Constitution of the Democratic Socialist Republic of Sri Lanka 49 | I53: Human Annotated | J53: =MAX(P53,U53,Z53,AE53,AJ53) -> 46170 | K53: LEGAL_EXPERT_1, LEGAL_EXPERT_2, LEGAL_EXPERT_3, LEGAL_EXPERT_4, LEGAL_EXPERT_5 | L53: 4.5 | M53: 4.3 | N53: 4.7 | P53: 2026.05.25 | Q53: 4.5 | R53: 4.3 | S53: 4.8 | U53: 2025.05.27 | V53: 4.7 | W53: 4.6 | X53: 4.6 | Z53: 46168 | AA53: 4.5 | AB53: 4.5 | AC53: 4.5 | AE53: 46170 | AF53: 4.5 | AG53: 4.7 | AH53: 4.6 | AJ53: 2026.05.28 | AK53: =AVERAGE(L53,Q53,V53,AA53,AF53) -> 4.54 | AL53: =AVERAGE(M53,R53,W53,AB53,AG53) -> 4.48 | AM53: =AVERAGE(N53,S53,X53,AC53,AH53) -> 4.64
A337: QAC_334 | B337: Procedural | C337: Hard | D337: Constitutional | E337: A Bill seeks to alter the provisions on the unitary status of Sri Lanka. What additional constitutional procedure applies? | F337: Article 2 declares Sri Lanka to be a Unitary State. Article 83(a) provides that a Bill for the amendment of or which is inconsistent with Article 2 requires not only a two-thirds majority of all Members of Parliament but also approval at a Referendum. This double-lock procedure applies because Article 2 is among the most entrenched provisions of the Constitution. | G337: Article 83, Article 85 | H337: Art. 83: Notwithstanding anything to the contrary in the of certain provisions of Article 82 Bills at a Referendum (a) a Bill for the amendment or for the repeal and replacement of or which is inconsistent wi || Art. 85: (1) The President shall submit to the People by of Bills to Referendum every Bill or any provision in any Bill people by Referendum which the Cabinet of Ministers has certified as being intended to be

Sheet 201-250
A1: Item ID | B1: Query Type | C1: Difficulty | D1: Legal Domain | E1: Question | F1: Reference Answer | G1: Constitutional Articles | H1: Supporting Passage(s) | I1: Annotattion Type | J1: Annotation Date | K1: Reviewer IDs | L1: Reviever 1: Chathuri Madushika (LLB ousl) | Q1: Reviever 2: Rohana Dasanayaka (LLB ousl) | V1: Reviever 3: Dulani Kulasooriya (LLB ousl) | AA1: Reviever 4: Dulshan Liyanaarachchi (LLB ousl) | AF1: Reviever 5: Inoshika Kodithuwakku (LLB ousl ) | AK1: Mean | AL1: Mean | AM1: Mean
L2: Reviewer ID: LEGAL_EXPERT_1 | Q2: Reviewer ID: LEGAL_EXPERT_2 | V2: Reviewer ID: LEGAL_EXPERT_3 | AA2: Reviewer ID: LEGAL_EXPERT_4 | AF2: Reviewer ID: LEGAL_EXPERT_5 | AK2: Reviewer IDs: LEGAL_EXPERT_1, LEGAL_EXPERT_2, LEGAL_EXPERT_3, LEGAL_EXPERT_4, LEGAL_EXPERT_5
L3: Correctness (1=Poor 5=Excellent) | M3: Completeness (1=Poor 5=Excellent) | N3: Clarity (1=Poor 5=Excellent) | O3: Expert Comments | P3: Review Date | Q3: Correctness (1=Poor 5=Excellent) | R3: Completeness (1=Poor 5=Excellent) | S3: Clarity (1=Poor 5=Excellent) | T3: Expert Comments | U3: Review Date | V3: Correctness (1=Poor 5=Excellent) | W3: Completeness (1=Poor 5=Excellent) | X3: Clarity (1=Poor 5=Excellent) | Y3: Expert Comments | Z3: Review Date | AA3: Correctness (1=Poor 5=Excellent) | AB3: Completeness (1=Poor 5=Excellent) | AC3: Clarity (1=Poor 5=Excellent) | AD3: Expert Comments | AE3: Review Date | AF3: Correctness (1=Poor 5=Excellent) | AG3: Completeness (1=Poor 5=Excellent) | AH3: Clarity (1=Poor 5=Excellent) | AI3: Expert Comments | AJ3: Review Date | AK3: Correctness (1=Poor 5=Excellent) | AL3: Completeness (1=Poor 5=Excellent) | AM3: Clarity (1=Poor 5=Excellent)
A4: QAC_201 | B4: Factual | C4: Hard | D4: Constitutional | E4: Can the decisions of the Constitutional Council be challenged in court? | F4: Article 41J provides that, subject to the jurisdiction conferred on the Supreme Court under Article 126, no court shall have the power or jurisdiction to entertain, hear, decide or call in question, on any ground whatsoever, any decision of the Council or any approval or recommendation made by the Council. | G4: Article 41J | H4: Art. 41J: Subject to the provisions of Article 126, no Finality of court shall have the power or jurisdiction to entertain, hear decisions of the Council or decide or call in question, on any ground whatsoever, | I4: Human Annotated | J4: =MAX(P4,U4,Z4,AE4,AJ4) -> 46170 | K4: LEGAL_EXPERT_1, LEGAL_EXPERT_2, LEGAL_EXPERT_3, LEGAL_EXPERT_4, LEGAL_EXPERT_5 | L4: 4.5 | M4: 4.4 | N4: 4.6 | P4: 2026.05.25 | Q4: 4.5 | R4: 4.3 | S4: 4.8 | U4: 2025.05.27 | V4: 4.7 | W4: 4.7 | X4: 4.6 | Z4: 46168 | AA4: 4.7 | AB4: 4.8 | AC4: 4.7 | AE4: 46170 | AF4: 4.5 | AG4: 4.7 | AH4: 4.6 | AJ4: 2026.05.28 | AK4: =AVERAGE(L4,Q4,V4,AA4,AF4) -> 4.58 | AL4: =AVERAGE(M4,R4,W4,AB4,AG4) -> 4.58 | AM4: =AVERAGE(N4,S4,X4,AC4,AH4) -> 4.66
A5: QAC_202 | B5: Procedural | C5: Medium | D5: Constitutional | E5: What happens to the Cabinet of Ministers when the Prime Minister ceases to hold office? | F5: Article 49 provides that on the Prime Minister ceasing to hold office by death, resignation or otherwise (except during the period between dissolution of Parliament and the conclusion of the General Election), the Cabinet of Ministers shall, unless the President has, in the exercise of his powers under Article 70, dissolved Parliament, stand dissolved. | G5: Article 49 | H5: Art. 49: (1) On the Prime Minister ceasing to hold Dissolution office by death, resignation or otherwise, except during the of the Cabinet of period intervening between the dissolution of Parliament Ministers | I5: Human Annotated | J5: =MAX(P5,U5,Z5,AE5,AJ5) -> 46170 | K5: LEGAL_EXPERT_1, LEGAL_EXPERT_2, LEGAL_EXPERT_3, LEGAL_EXPERT_4, LEGAL_EXPERT_5 | L5: 4.5 | M5: 4.4 | N5: 4.6 | P5: 2026.05.25 | Q5: 4.6 | R5: 4.3 | S5: 4.7 | U5: 2025.05.27 | V5: 4.3 | W5: 4.4 | X5: 4.6 | Z5: 46168 | AA5: 4.4 | AB5: 4.5 | AC5: 4.6 | AE5: 46170 | AF5: 4.6 | AG5: 4.8 | AH5: 4.7 | AJ5: 2026.05.28 | AK5: =AVERAGE(L5,Q5,V5,AA5,AF5) -> 4.48 | AL5: =AVERAGE(M5,R5,W5,AB5,AG5) -> 4.48 | AM5: =AVERAGE(N5,S5,X5,AC5,AH5) -> 4.64
A6: QAC_203 | B6: Factual | C6: Medium | D6: Constitutional | E6: What is the constitutional offence of interfering with the Public Service Commission? | F6: Article 61C provides that every person who, otherwise than in the course of such person's lawful duty, directly or indirectly by himself or by or with any other person, in any manner whatsoever influences or attempts to influence or interferes with any decision of the Public Service Commission, or a Committee or a public officer to whom the Commission has delegated any power, or to so influence any member of the Commission or a Committee, shall be guilty of an offence. | G6: Article 61C | H6: Art. 61C: (1) Every person who, otherwise than in the Interference with the course of such persons lawful duty, directly or indirectly Commission by himself or by or with any other person, in any manner whatsoe | I6: Human Annotated | J6: =MAX(P6,U6,Z6,AE6,AJ6) -> 46170 | K6: LEGAL_EXPERT_1, LEGAL_EXPERT_2, LEGAL_EXPERT_3, LEGAL_EXPERT_4, LEGAL_EXPERT_5 | L6: 4.5 | M6: 4.4 | N6: 4.6 | P6: 2026.05.25 | Q6: 4.5 | R6: 4.3 | S6: 4.6 | U6: 2025.05.27 | V6: 4.6 | W6: 4.4 | X6: 4.7 | Z6: 46168 | AA6: 4.6 | AB6: 4.7 | AC6: 4.5 | AE6: 46170 | AF6: 4.5 | AG6: 4.6 | AH6: 4.7 | AJ6: 2026.05.28 | AK6: =AVERAGE(L6,Q6,V6,AA6,AF6) -> 4.54 | AL6: =AVERAGE(M6,R6,W6,AB6,AG6) -> 4.48 | AM6: =AVERAGE(N6,S6,X6,AC6,AH6) -> 4.62
A7: QAC_204 | B7: Factual | C7: Easy | D7: Constitutional | E7: What oath or affirmation must a person take before assuming a public service office? | F7: Article 61D provides that a person appointed to any office in the public service shall not enter upon the duties of that office until they take and subscribe the oath or make and subscribe the affirmations set out in the Fourth and Seventh Schedules to the Constitution. | G7: Article 61D | H7: Art. 61D: A person appointed to any office referred to in affirmation this Chapter shall not enter upon the duties of his office of office until he takes and subscribes the oath or makes and subscribes 44[the a | I7: Human Annotated | J7: =MAX(P7,U7,Z7,AE7,AJ7) -> 46170 | K7: LEGAL_EXPERT_1, LEGAL_EXPERT_2, LEGAL_EXPERT_3, LEGAL_EXPERT_4, LEGAL_EXPERT_5 | L7: 4.5 | M7: 4.4 | N7: 4.6 | P7: 2026.05.25 | Q7: 4.4 | R7: 4.4 | S7: 4.7 | U7: 2025.05.27 | V7: 4.7 | W7: 4.4 | X7: 4.5 | Z7: 46168 | AA7: 4.9 | AB7: 4.8 | AC7: 4.7 | AE7: 46170 | AF7: 4.5 | AG7: 4.7 | AH7: 4.6 | AJ7: 2026.05.28 | AK7: =AVERAGE(L7,Q7,V7,AA7,AF7) -> 4.6 | AL7: =AVERAGE(M7,R7,W7,AB7,AG7) -> 4.54 | AM7: =AVERAGE(N7,S7,X7,AC7,AH7) -> 4.62
A8: QAC_205 | B8: Procedural | C8: Hard | D8: Constitutional | E8: How are the national list seats in Parliament allocated after a general election? | F8: Article 99A provides that after the 196 members referred to in Article 98 have been declared elected at a General Election, the Commissioner of Elections shall forthwith apportion the remaining 29 seats among the recognised political parties and independent groups on the basis of the total number of votes polled by each party or group at the General Election. | G8: Article 99A | H8: Art. 99A: After the one hundred and ninety six on the basis of the total members referred to in Article 98 have been declared number of elected at a General Election of Members of Parliament, votes polled the C | I8: Human Annotated | J8: =MAX(P8,U8,Z8,AE8,AJ8) -> 46170 | K8: LEGAL_EXPERT_1, LEGAL_EXPERT_2, LEGAL_EXPERT_3, LEGAL_EXPERT_4, LEGAL_EXPERT_5 | L8: 4.5 | M8: 4.4 | N8: 4.6 | P8: 2026.05.25 | Q8: 4.5 | R8: 4.3 | S8: 4.6 | U8: 2025.05.27 | V8: 4.6 | W8: 4.4 | X8: 4.7 | Z8: 46168 | AA8: 4.5 | AB8: 4.4 | AC8: 4.8 | AE8: 46170 | AF8: 4.6 | AG8: 4.8 | AH8: 4.7 | AJ8: 2026.05.28 | AK8: =AVERAGE(L8,Q8,V8,AA8,AF8) -> 4.54 | AL8: =AVERAGE(M8,R8,W8,AB8,AG8) -> 4.46 | AM8: =AVERAGE(N8,S8,X8,AC8,AH8) -> 4.68
A9: QAC_206 | B9: Factual | C9: Hard | D9: Constitutional | E9: Are the decisions of the Elections Commission subject to challenge in court? | F9: Article 104A provides that, subject to the jurisdiction of the Supreme Court under Article 126 and Article 130 and of the Court of Appeal under Article 144, the decisions of the Elections Commission and its members shall be final and the Commission and its members shall not be liable to any action or suit in any court in respect of anything done or omitted in good faith in the exercise of the Commission's powers. | G9: Article 104A | H9: Art. 104A: Subject to the jurisdiction conferred on the decisions Supreme Court under paragraph (1) of Article 126, Article and immunity from suit 104H and Article 130 and on the Court of Appeal by Article 144 a | I9: Human Annotated | J9: =MAX(P9,U9,Z9,AE9,AJ9) -> 46170 | K9: LEGAL_EXPERT_1, LEGAL_EXPERT_2, LEGAL_EXPERT_3, LEGAL_EXPERT_4, LEGAL_EXPERT_5 | L9: 4.5 | M9: 4.4 | N9: 4.6 | P9: 2026.05.25 | Q9: 4.5 | R9: 4.4 | S9: 4.8 | U9: 2025.05.27 | V9: 4.8 | W9: 4.4 | X9: 4.5 | Z9: 46168 | AA9: 4.7 | AB9: 4.5 | AC9: 4.5 | AE9: 46170 | AF9: 4.5 | AG9: 4.6 | AH9: 4.7 | AJ9: 2026.05.28 | AK9: =AVERAGE(L9,Q9,V9,AA9,AF9) -> 4.6 | AL9: =AVERAGE(M9,R9,W9,AB9,AG9) -> 4.46 | AM9: =AVERAGE(N9,S9,X9,AC9,AH9) -> 4.62
A10: QAC_207 | B10: Factual | C10: Medium | D10: Constitutional | E10: What are the powers, functions and duties of the Elections Commission? | F10: Article 104B provides that the Elections Commission shall exercise, perform and discharge all powers, duties and functions conferred or imposed on the Commission or on the Commissioner-General of Elections by the Constitution and by law for the time being in force, including superintendence, direction and control of the preparation of electoral registers and the conduct of elections and referendums. | G10: Article 104B | H10: Art. 104B: (1) The Commission shall exercise, perform Powers, functions and and discharge all such powers, duties and functions duties of the conferred or imposed on or assigned to Commission (a) the Commission | I10: Human Annotated | J10: =MAX(P10,U10,Z10,AE10,AJ10) -> 46170 | K10: LEGAL_EXPERT_1, LEGAL_EXPERT_2, LEGAL_EXPERT_3, LEGAL_EXPERT_4, LEGAL_EXPERT_5 | L10: 4.5 | M10: 4.4 | N10: 4.6 | P10: 2026.05.25 | Q10: 4.6 | R10: 4.3 | S10: 4.8 | U10: 2025.05.27 | V10: 4.9 | W10: 4.7 | X10: 4.6 | Z10: 46168 | AA10: 4.7 | AB10: 4.7 | AC10: 4.7 | AE10: 46170 | AF10: 4.5 | AG10: 4.7 | AH10: 4.6 | AJ10: 2026.05.28 | AK10: =AVERAGE(L10,Q10,V10,AA10,AF10) -> 4.64 | AL10: =AVERAGE(M10,R10,W10,AB10,AG10) -> 4.56 | AM10: =AVERAGE(N10,S10,X10,AC10,AH10) -> 4.66
A11: QAC_208 | B11: Factual | C11: Medium | D11: Constitutional | E11: What power does the Elections Commission have over the police during an election or referendum? | F11: Article 104C provides that upon the making of an Order for the holding of an election or a Proclamation requiring the conduct of a Referendum, the Elections Commission shall notify the Inspector-General of Police of the facilities and the number of police officers required, and the Inspector-General of Police shall comply with that notification. During this period the police shall be under the direction and control of the Commission for the purpose of ensuring a free and fair election or referendum. | G11: Article 104C | H11: Art. 104C: (1) Upon the making of an Order for the of Police holding of an election or the making of a Proclamation by the Commission requiring the conduct of a Referendum, as the case may be, the Commission sha | I11: Human Annotated | J11: =MAX(P11,U11,Z11,AE11,AJ11) -> 46170 | K11: LEGAL_EXPERT_1, LEGAL_EXPERT_2, LEGAL_EXPERT_3, LEGAL_EXPERT_4, LEGAL_EXPERT_5 | L11: 4.5 | M11: 4.4 | N11: 4.6 | P11: 2026.05.25 | Q11: 4.5 | R11: 4.3 | S11: 4.8 | U11: 2025.05.27 | V11: 4.8 | W11: 4.5 | X11: 4.6 | Z11: 46168 | AA11: 4.5 | AB11: 4.5 | AC11: 4.7 | AE11: 46170 | AF11: 4.6 | AG11: 4.8 | AH11: 4.7 | AJ11: 2026.05.28 | AK11: =AVERAGE(L11,Q11,V11,AA11,AF11) -> 4.58 | AL11: =AVERAGE(M11,R11,W11,AB11,AG11) -> 4.5 | AM11: =AVERAGE(N11,S11,X11,AC11,AH11) -> 4.68
A12: QAC_209 | B12: Factual | C12: Medium | D12: Constitutional | E12: Can the number of High Court judges be temporarily increased? | F12: Article 111A provides that where the Minister in charge of the subject of Justice represents to the President that it is expedient that the number of Judges exercising the jurisdiction and powers of the High Court in any judicial zone should be temporarily increased, the President may, on the recommendation of the Judicial Service Commission, by warrant appoint one or more Commissioners of the High Court to exercise the jurisdiction and powers of the High Court within such judicial zone. | G12: Article 111A | H12: Art. 111A: (1) Where the Minister in charge of the of the High subject of Justice represents to the President that it is Court expedient that the number of the Judges exercising the jurisdiction and powers of th | I12: Human Annotated | J12: =MAX(P12,U12,Z12,AE12,AJ12) -> 46170 | K12: LEGAL_EXPERT_1, LEGAL_EXPERT_2, LEGAL_EXPERT_3, LEGAL_EXPERT_4, LEGAL_EXPERT_5 | L12: 4.5 | M12: 4.4 | N12: 4.6 | P12: 2026.05.25 | Q12: 4.6 | R12: 4.3 | S12: 4.8 | U12: 2025.05.27 | V12: 4.5 | W12: 4.2 | X12: 4.5 | Z12: 46168 | AA12: 4.7 | AB12: 4.6 | AC12: 4.5 | AE12: 46170 | AF12: 4.5 | AG12: 4.6 | AH12: 4.7 | AJ12: 2026.05.28 | AK12: =AVERAGE(L12,Q12,V12,AA12,AF12) -> 4.56 | AL12: =AVERAGE(M12,R12,W12,AB12,AG12) -> 4.42 | AM12: =AVERAGE(N12,S12,X12,AC12,AH12) -> 4.62
A13: QAC_210 | B13: Factual | C13: Easy | D13: Constitutional | E13: What is the role of the Fiscal under the Constitution? | F13: Article 111B provides that there shall be a Fiscal, who shall be the Fiscal for the whole Island, and who shall exercise supervision and control over Deputy Fiscals attached to all Courts of First Instance. | G13: Article 111B | H13: Art. 111B: There shall be a Fiscal, who shall be the Fiscal for the Fiscal for the whole Island and who shall exercise whole Island supervision and control over Deputy Fiscals attached to all Courts of First Ins | I13: Human Annotated | J13: =MAX(P13,U13,Z13,AE13,AJ13) -> 46170 | K13: LEGAL_EXPERT_1, LEGAL_EXPERT_2, LEGAL_EXPERT_3, LEGAL_EXPERT_4, LEGAL_EXPERT_5 | L13: 4.5 | M13: 4.4 | N13: 4.6 | P13: 2026.05.25 | Q13: 4.5 | R13: 4.3 | S13: 4.7 | U13: 2025.05.27 | V13: 4.6 | W13: 4.5 | X13: 4.6 | Z13: 46168 | AA13: 4.5 | AB13: 4.5 | AC13: 4.5 | AE13: 46170 | AF13: 4.5 | AG13: 4.7 | AH13: 4.6 | AJ13: 2026.05.28 | AK13: =AVERAGE(L13,Q13,V13,AA13,AF13) -> 4.52 | AL13: =AVERAGE(M13,R13,W13,AB13,AG13) -> 4.48 | AM13: =AVERAGE(N13,S13,X13,AC13,AH13) -> 4.6
A14: QAC_211 | B14: Factual | C14: Medium | D14: Constitutional | E14: What powers does the Court of Appeal have when it allows an appeal? | F14: Article 139 provides that the Court of Appeal may, in the exercise of its jurisdiction, affirm, reverse, correct or modify any order, judgment, decree or sentence according to law, or it may give directions to such Court of First Instance, tribunal or other institution, or order a new trial or further hearing upon such terms and conditions as it thinks fit. | G14: Article 139 | H14: Art. 139: (1) The Court of Appeal may in the exercise appeal of its jurisdiction, affirm, reverse, correct or modify any order, judgment, decree or sentence according to law or it may give directions to such Co | I14: Human Annotated | J14: =MAX(P14,U14,Z14,AE14,AJ14) -> 46170 | K14: LEGAL_EXPERT_1, LEGAL_EXPERT_2, LEGAL_EXPERT_3, LEGAL_EXPERT_4, LEGAL_EXPERT_5 | L14: 4.5 | M14: 4.4 | N14: 4.6 | P14: 2026.05.25 | Q14: 4.5 | R14: 4.3 | S14: 4.8 | U14: 2025.05.27 | V14: 4.5 | W14: 4.4 | X14: 4.6 | Z14: 46168 | AA14: 4.4 | AB14: 4.6 | AC14: 4.6 | AE14: 46170 | AF14: 4.6 | AG14: 4.8 | AH14: 4.7 | AJ14: 2026.05.28 | AK14: =AVERAGE(L14,Q14,V14,AA14,AF14) -> 4.5 | AL14: =AVERAGE(M14,R14,W14,AB14,AG14) -> 4.5 | AM14: =AVERAGE(N14,S14,X14,AC14,AH14) -> 4.66
A15: QAC_212 | B15: Factual | C15: Medium | D15: Constitutional | E15: What does the Constitution define as 'civic rights'? | F15: Article 146 defines 'civic rights' to mean: (a) the right to obtain a passport; (b) the right to sit for any public examination; (c) the right to own any immovable property; (d) the right to engage in any trade or profession which requires a licence, registration or other authorization, by or under any written law. | G15: Article 146 | H15: Art. 146: (12) In this Article, civic rights means (a) the right to obtain a passport; The Constitution of the Democratic Socialist Republic of Sri Lanka 205 (b) the right to sit for any public examination; (c | I15: Human Annotated | J15: =MAX(P15,U15,Z15,AE15,AJ15) -> 46170 | K15: LEGAL_EXPERT_1, LEGAL_EXPERT_2, LEGAL_EXPERT_3, LEGAL_EXPERT_4, LEGAL_EXPERT_5 | L15: 4.5 | M15: 4.4 | N15: 4.6 | P15: 2026.05.25 | Q15: 4.5 | R15: 4.3 | S15: 4.7 | U15: 2025.05.27 | V15: 4.6 | W15: 4.5 | X15: 4.7 | Z15: 46168 | AA15: 4.7 | AB15: 4.6 | AC15: 4.5 | AE15: 46170 | AF15: 4.5 | AG15: 4.6 | AH15: 4.7 | AJ15: 2026.05.28 | AK15: =AVERAGE(L15,Q15,V15,AA15,AF15) -> 4.56 | AL15: =AVERAGE(M15,R15,W15,AB15,AG15) -> 4.48 | AM15: =AVERAGE(N15,S15,X15,AC15,AH15) -> 4.64
... A18: QAC_215 | B18: Factual | C18: Medium | D18: Constitutional | E18: What powers and functions does the Audit Service Commission exercise? | F18: Article 153C provides that the powers of appointment, promotion, transfer, disciplinary control and dismissal of members belonging to the Sri Lanka State Audit Service shall be vested in the Audit Service Commission. The Commission shall also exercise, perform and discharge such other functions in relation to the State Audit Service as are conferred or imposed on it by law. | G18: Article 153C | H18: Art. 153C: (1) The powers of appointment, promotion, Powers and functions transfer, disciplinary control and dismissal of the of the members belonging to the Sri Lanka State Audit Service, Commission shall be ve | I18: Human Annotated | J18: =MAX(P18,U18,Z18,AE18,AJ18) -> 46170 | K18: LEGAL_EXPERT_1, LEGAL_EXPERT_2, LEGAL_EXPERT_3, LEGAL_EXPERT_4, LEGAL_EXPERT_5 | L18: 4.5 | M18: 4.4 | N18: 4.6 | P18: 2026.05.25 | Q18: 4.4 | R18: 4.3 | S18: 4.8 | U18: 2025.05.27 | V18: 4.5 | W18: 4.4 | X18: 4.5 | Z18: 46168 | AA18: 4.4 | AB18: 4.5 | AC18: 4.4 | AE18: 46170 | AF18: 4.5 | AG18: 4.6 | AH18: 4.7 | AJ18: 2026.05.28 | AK18: =AVERAGE(L18,Q18,V18,AA18,AF18) -> 4.46 | AL18: =AVERAGE(M18,R18,W18,AB18,AG18) -> 4.44 | AM18: =AVERAGE(N18,S18,X18,AC18,AH18) -> 4.6
A19: QAC_216 | B19: Factual | C19: Medium | D19: Constitutional | E19: How is executive power exercised in the provinces under the Constitution? | F19: Article 154C provides that executive power extending to matters with respect to which a Provincial Council has power to make statutes shall be exercised by the Governor of the Province either directly or through Ministers of the Board of Ministers of the Province. | G19: Article 154C | H19: Art. 154C: Executive power extending to the matters executive powers with respect to which a Provincial Council has power to make by the statutes shall be exercised by the Governor of the Province Governor for w | I19: Human Annotated | J19: =MAX(P19,U19,Z19,AE19,AJ19) -> 46170 | K19: LEGAL_EXPERT_1, LEGAL_EXPERT_2, LEGAL_EXPERT_3, LEGAL_EXPERT_4, LEGAL_EXPERT_5 | L19: 4.5 | M19: 4.4 | N19: 4.6 | P19: 2026.05.25 | Q19: 4.5 | R19: 4.3 | S19: 4.7 | U19: 2025.05.27 | V19: .4.7 | W19: 4.3 | X19: 4.6 | Z19: 46168 | AA19: 4.8 | AB19: 4.5 | AC19: 4.5 | AE19: 46170 | AF19: 4.5 | AG19: 4.7 | AH19: 4.6 | AJ19: 2026.05.28 | AK19: =AVERAGE(L19,Q19,V19,AA19,AF19) -> 4.575 | AL19: =AVERAGE(M19,R19,W19,AB19,AG19) -> 4.44 | AM19: =AVERAGE(N19,S19,X19,AC19,AH19) -> 4.6
A20: QAC_217 | B20: Factual | C20: Easy | D20: Constitutional | E20: What is the term of office of a Provincial Council? | F20: Article 154E provides that a Provincial Council shall, unless sooner dissolved, continue for a period of five years from the date appointed for its first meeting. The expiration of that five-year period shall operate as a dissolution of the Council. | G20: Article 154E | H20: Art. 154E: A Provincial Council shall, unless sooner Term of office dissolved, continue for a period of five years from the date appointed for its first meeting and the expiration of the said period of five year | I20: Human Annotated | J20: =MAX(P20,U20,Z20,AE20,AJ20) -> 46170 | K20: LEGAL_EXPERT_1, LEGAL_EXPERT_2, LEGAL_EXPERT_3, LEGAL_EXPERT_4, LEGAL_EXPERT_5 | L20: 4.5 | M20: 4.4 | N20: 4.6 | P20: 2026.05.25 | Q20: 4.5 | R20: 4.3 | S20: 4.6 | U20: 2025.05.27 | V20: 4.8 | W20: 4.4 | X20: 4.6 | Z20: 46168 | AA20: 4.6 | AB20: 4.5 | AC20: 4.4 | AE20: 46170 | AF20: 4.6 | AG20: 4.8 | AH20: 4.7 | AJ20: 2026.05.28 | AK20: =AVERAGE(L20,Q20,V20,AA20,AF20) -> 4.6 | AL20: =AVERAGE(M20,R20,W20,AB20,AG20) -> 4.48 | AM20: =AVERAGE(N20,S20,X20,AC20,AH20) -> 4.58
A21: QAC_218 | B21: Factual | C21: Medium | D21: Constitutional | E21: What is the statute-making power of Provincial Councils? | F21: Article 154G provides that every Provincial Council may, subject to the provisions of the Constitution, make statutes applicable to the Province for which it is established with respect to any matter set out in List I of the Ninth Schedule (the Provincial Council List). The Governor shall reserve for the consideration of the President any statute which in his opinion would, if assented to, be inconsistent with the provisions of any law made by Parliament with respect to a matter in the Concurrent List. | G21: Article 154G | H21: Art. 154G: (1) Every Provincial Council may, subject to the Statutes of Provincial provisions of the Constitution, make statutes applicable to Councils the Province for which it is established, with respect to a | I21: Human Annotated | J21: =MAX(P21,U21,Z21,AE21,AJ21) -> 46170 | K21: LEGAL_EXPERT_1, LEGAL_EXPERT_2, LEGAL_EXPERT_3, LEGAL_EXPERT_4, LEGAL_EXPERT_5 | L21: 4.5 | M21: 4.4 | N21: 4.6 | P21: 2026.05.25 | Q21: 4.5 | R21: 4.3 | S21: 4.8 | U21: 2025.05.27 | V21: 4.7 | W21: 4.4 | X21: 4.7 | Z21: 46168 | AA21: 4.7 | AB21: 4.7 | AC21: 4.7 | AE21: 46170 | AF21: 4.5 | AG21: 4.6 | AH21: 4.7 | AJ21: 2026.05.28 | AK21: =AVERAGE(L21,Q21,V21,AA21,AF21) -> 4.58 | AL21: =AVERAGE(M21,R21,W21,AB21,AG21) -> 4.48 | AM21: =AVERAGE(N21,S21,X21,AC21,AH21) -> 4.7
A22: QAC_219 | B22: Procedural | C22: Easy | D22: Constitutional | E22: What is the quorum for a meeting of the National Police Commission? | F22: Article 155B provides that the quorum for a meeting of the National Police Commission shall be five members. The Chairman shall preside at all meetings, and in his absence a member elected from among those present shall preside. Decisions of the Commission shall be by majority vote. | G22: Article 155B | H22: Art. 155B: (1) The quorum for a meeting of the of the Commission shall be 158[five] members. Commission (2) The Chairman shall preside at all meetings of the Commission and in his absence a member elected by the | I22: Human Annotated | J22: =MAX(P22,U22,Z22,AE22,AJ22) -> 46170 | K22: LEGAL_EXPERT_1, LEGAL_EXPERT_2, LEGAL_EXPERT_3, LEGAL_EXPERT_4, LEGAL_EXPERT_5 | L22: 4.5 | M22: 4.4 | N22: 4.6 | P22: 2026.05.25 | Q22: 4.6 | R22: 4.4 | S22: 4.8 | U22: 2025.05.27 | V22: 4.6 | W22: 4.5 | X22: 4.6 | Z22: 46168 | AA22: 4.5 | AB22: 4.4 | AC22: 4.5 | AE22: 46170 | AF22: 4.5 | AG22: 4.7 | AH22: 4.6 | AJ22: 2026.05.28 | AK22: =AVERAGE(L22,Q22,V22,AA22,AF22) -> 4.54 | AL22: =AVERAGE(M22,R22,W22,AB22,AG22) -> 4.48 | AM22: =AVERAGE(N22,S22,X22,AC22,AH22) -> 4.62
A23: QAC_220 | B23: Factual | C23: Medium | D23: Constitutional | E23: What does the Constitution require Parliament to establish with respect to bribery and corruption? | F23: Article 156A requires Parliament to provide by law for the establishment of a Commission to investigate allegations of bribery or corruption. Such law shall provide for the appointment of Commission members by the President on the recommendation of the Constitutional Council, and shall define the powers and procedure of the Commission. | G23: Article 156A | H23: Art. 156A: (1) Parliament shall by law provide for the to investigate establishment of a Commission to investigate allegations bribery or corruption of bribery or corruption. Such law shall provide for - (a) the | I23: Human Annotated | J23: =MAX(P23,U23,Z23,AE23,AJ23) -> 46170 | K23: LEGAL_EXPERT_1, LEGAL_EXPERT_2, LEGAL_EXPERT_3, LEGAL_EXPERT_4, LEGAL_EXPERT_5 | L23: 4.5 | M23: 4.4 | N23: 4.6 | P23: 2026.05.25 | Q23: 4.5 | R23: 4.3 | S23: 4.8 | U23: 2025.05.27 | V23: 4.7 | W23: 4.3 | X23: 4.5 | Z23: 46168 | AA23: 4.4 | AB23: 4.3 | AC23: 4.3 | AE23: 46170 | AF23: 4.6 | AG23: 4.8 | AH23: 4.7 | AJ23: 2026.05.28 | AK23: =AVERAGE(L23,Q23,V23,AA23,AF23) -> 4.54 | AL23: =AVERAGE(M23,R23,W23,AB23,AG23) -> 4.42 | AM23: =AVERAGE(N23,S23,X23,AC23,AH23) -> 4.58
A24: QAC_221 | B24: Factual | C24: Medium | D24: Constitutional | E24: What is the National Procurement Commission and how is it composed? | F24: Article 156B establishes the National Procurement Commission, consisting of five members appointed by the President on the recommendation of the Constitutional Council, of whom at least three members shall be persons who have had proven experience in procurement, accountancy, law or public administration. The Commission supervises the procedure for the procurement of goods and services by the Government. | G24: Article 156B | H24: Art. 156B: (1) There shall be a National Procurement National Commission (in this Chapter referred to as the Commission) Procurement Commission consisting of five members appointed by the President on the recomm | I24: Human Annotated | J24: =MAX(P24,U24,Z24,AE24,AJ24) -> 46170 | K24: LEGAL_EXPERT_1, LEGAL_EXPERT_2, LEGAL_EXPERT_3, LEGAL_EXPERT_4, LEGAL_EXPERT_5 | L24: 4.5 | M24: 4.4 | N24: 4.6 | P24: 2026.05.25 | Q24: 4.5 | R24: 4.3 | S24: 4.8 | U24: 2025.05.27 | V24: 4.8 | W24: 4.3 | X24: 4.5 | Z24: 46168 | AA24: 4.5 | AB24: 4.5 | AC24: 4.5 | AE24: 46170 | AF24: 4.5 | AG24: 4.6 | AH24: 4.7 | AJ24: 2026.05.28 | AK24: =AVERAGE(L24,Q24,V24,AA24,AF24) -> 4.56 | AL24: =AVERAGE(M24,R24,W24,AB24,AG24) -> 4.42 | AM24: =AVERAGE(N24,S24,X24,AC24,AH24) -> 4.62
A25: QAC_222 | B25: Factual | C25: Medium | D25: Constitutional | E25: What powers and rights does Sri Lanka continue to possess from before the 1978 Constitution came into force? | F25: Article 166 provides that unless Parliament otherwise provides, the Republic of Sri Lanka shall continue to possess and exercise all powers, privileges, immunities and rights of whatever nature which it possessed, exercised or could have exercised immediately prior to the commencement of the Constitution. | G25: Article 166 | H25: Art. 166: Unless Parliament otherwise provides, the Powers, privileges, Republic of Sri Lanka shall continue to possess and i mmunities and rights exercise all powers, privileges, immunities and rights of the w | I25: Human Annotated | J25: =MAX(P25,U25,Z25,AE25,AJ25) -> 46170 | K25: LEGAL_EXPERT_1, LEGAL_EXPERT_2, LEGAL_EXPERT_3, LEGAL_EXPERT_4, LEGAL_EXPERT_5 | L25: 4.5 | M25: 4.4 | N25: 4.6 | P25: 2026.05.25 | Q25: 4.3 | R25: 4.4 | S25: 4.8 | U25: 2025.05.27 | V25: 4.8 | W25: 4.4 | X25: 4.6 | Z25: 46168 | AA25: 4.6 | AB25: 4.6 | AC25: 4.7 | AE25: 46170 | AF25: 4.5 | AG25: 4.7 | AH25: 4.6 | AJ25: 2026.05.28 | AK25: =AVERAGE(L25,Q25,V25,AA25,AF25) -> 4.54 | AL25: =AVERAGE(M25,R25,W25,AB25,AG25) -> 4.5 | AM25: =AVERAGE(N25,S25,X25,AC25,AH25) -> 4.66
A26: QAC_223 | B26: Interpretive | C26: Medium | D26: Constitutional | E26: What is the constitutional effect on laws that were in force before the 1978 Constitution commenced? | F26: Article 168 provides that unless Parliament otherwise provides, all laws, written laws and unwritten laws, in force immediately before the commencement of the Constitution shall, with necessary modifications and except as otherwise expressly provided in the Constitution, continue in force. All offences committed and legal proceedings pending immediately before commencement shall continue to be governed by the law applicable at the time. | G26: Article 168 | H26: Art. 168: (1) Unless Parliament otherwise provides, operation all laws, written laws and unwritten laws, in force of laws, previous acts, immediately before the commencement of the Constitution, offences and pe | I26: Human Annotated | J26: =MAX(P26,U26,Z26,AE26,AJ26) -> 46170 | K26: LEGAL_EXPERT_1, LEGAL_EXPERT_2, LEGAL_EXPERT_3, LEGAL_EXPERT_4, LEGAL_EXPERT_5 | L26: 4.5 | M26: 4.4 | N26: 4.6 | P26: 2026.05.25 | Q26: 4.5 | R26: 4.3 | S26: 4.8 | U26: 2025.05.27 | V26: 4.7 | W26: 4.4 | X26: 4.6 | Z26: 46168 | AA26: 4.5 | AB26: 4.6 | AC26: 4.6 | AE26: 46170 | AF26: 4.6 | AG26: 4.8 | AH26: 4.7 | AJ26: 2026.05.28 | AK26: =AVERAGE(L26,Q26,V26,AA26,AF26) -> 4.56 | AL26: =AVERAGE(M26,R26,W26,AB26,AG26) -> 4.5 | AM26: =AVERAGE(N26,S26,X26,AC26,AH26) -> 4.66
A27: QAC_224 | B27: Factual | C27: Easy | D27: Constitutional | E27: Which earlier Constitution did the 1978 Constitution repeal? | F27: Article 171 provides that the Constitution adopted and enacted on the 22nd day of May, 1972 is hereby repealed. This was the Republican Constitution of 1972 which had itself replaced the independence Constitution of 1948. | G27: Article 171 | H27: Art. 171: The Constitution adopted and enacted on the 22nd day of May, 1972, is hereby repealed. The Constitution of the Democratic Socialist Republic of Sri Lanka 233 CHAPTER XXIV PROMULGATION OF THE CONSTITUT | I27: Human Annotated | J27: =MAX(P27,U27,Z27,AE27,AJ27) -> 46170 | K27: LEGAL_EXPERT_1, LEGAL_EXPERT_2, LEGAL_EXPERT_3, LEGAL_EXPERT_4, LEGAL_EXPERT_5 | L27: 4.5 | M27: 4.4 | N27: 4.6 | P27: 2026.05.25 | Q27: 4.5 | R27: 4.3 | S27: 4.7 | U27: 2025.05.27 | V27: 4.7 | W27: 4.4 | X27: 4.6 | Z27: 46168 | AA27: 4.5 | AB27: 4.5 | AC27: 4.5 | AE27: 46170 | AF27: 4.5 | AG27: 4.6 | AH27: 4.7 | AJ27: 2026.05.28 | AK27: =AVERAGE(L27,Q27,V27,AA27,AF27) -> 4.54 | AL27: =AVERAGE(M27,R27,W27,AB27,AG27) -> 4.44 | AM27: =AVERAGE(N27,S27,X27,AC27,AH27) -> 4.62
A28: QAC_225 | B28: Procedural | C28: Easy | D28: Constitutional | E28: How and when did the provisions of the 1978 Constitution come into force? | F28: Article 172 provides that the provisions of Chapter I to Chapter XXIII shall come into force on the day appointed by the President by Proclamation. Parliament shall meet on the day so appointed and the President may in such Proclamation specify the time at which Parliament shall so meet. | G28: Article 172 | H28: Art. 172: (1) The provisions of Chapter I to Chapter Promulgation of XXIII shall come into force on the day appointed by the the Constitution President by Proclamation. (2) Parliament shall meet on the day so a | I28: Human Annotated | J28: =MAX(P28,U28,Z28,AE28,AJ28) -> 46170 | K28: LEGAL_EXPERT_1, LEGAL_EXPERT_2, LEGAL_EXPERT_3, LEGAL_EXPERT_4, LEGAL_EXPERT_5 | L28: 4.5 | M28: 4.4 | N28: 4.6 | P28: 2026.05.25 | Q28: 4.5 | R28: 4.3 | S28: 4.8 | U28: 2025.05.27 | V28: 4.7 | W28: 4.3 | X28: 4.6 | Z28: 46168 | AA28: 4.7 | AB28: 4.5 | AC28: 4.7 | AE28: 46170 | AF28: 4.5 | AG28: 4.7 | AH28: 4.6 | AJ28: 2026.05.28 | AK28: =AVERAGE(L28,Q28,V28,AA28,AF28) -> 4.58 | AL28: =AVERAGE(M28,R28,W28,AB28,AG28) -> 4.44 | AM28: =AVERAGE(N28,S28,X28,AC28,AH28) -> 4.66
A29: QAC_226 | B29: Factual | C29: Easy | D29: Constitutional | E29: How is the legislative power of the People exercised under the Constitution? | F29: Article 4(a) provides that the legislative power of the People shall be exercised by Parliament, consisting of elected representatives of the People, and by the People at a Referendum. | G29: Article 4 | H29: Art. 4: The Sovereignty of the People shall be exercised Exercise of Sovereignty and enjoyed in the following manner: (a) the legislative power of the People shall be exercised by Parliament, consisting of el | I29: Human Annotated | J29: =MAX(P29,U29,Z29,AE29,AJ29) -> 46170 | K29: LEGAL_EXPERT_1, LEGAL_EXPERT_2, LEGAL_EXPERT_3, LEGAL_EXPERT_4, LEGAL_EXPERT_5 | L29: 4.5 | M29: 4.4 | N29: 4.6 | P29: 2026.05.25 | Q29: 4.3 | R29: 4.3 | S29: 4.8 | U29: 2025.05.27 | V29: 4.8 | W29: 4.5 | X29: 4.5 | Z29: 46168 | AA29: 4.4 | AB29: 4.5 | AC29: 4.6 | AE29: 46170 | AF29: 4.6 | AG29: 4.8 | AH29: 4.7 | AJ29: 2026.05.28 | AK29: =AVERAGE(L29,Q29,V29,AA29,AF29) -> 4.52 | AL29: =AVERAGE(M29,R29,W29,AB29,AG29) -> 4.5 | AM29: =AVERAGE(N29,S29,X29,AC29,AH29) -> 4.64
A30: QAC_227 | B30: Factual | C30: Easy | D30: Constitutional | E30: Who exercises the executive power of the People under the Constitution? | F30: Article 4(b) provides that the executive power of the People, including the defence of Sri Lanka, shall be exercised by the President of the Republic elected by the People. | G30: Article 4 | H30: Art. 4: The Sovereignty of the People shall be exercised Exercise of Sovereignty and enjoyed in the following manner: (a) the legislative power of the People shall be exercised by Parliament, consisting of el | I30: Human Annotated | J30: =MAX(P30,U30,Z30,AE30,AJ30) -> 46170 | K30: LEGAL_EXPERT_1, LEGAL_EXPERT_2, LEGAL_EXPERT_3, LEGAL_EXPERT_4, LEGAL_EXPERT_5 | L30: 4.5 | M30: 4.4 | N30: 4.6 | P30: 2026.05.25 | Q30: 4.5 | R30: 4.3 | S30: 4.6 | U30: 2025.05.27 | V30: 4.6 | W30: 4.3 | X30: 4.5 | Z30: 46168 | AA30: 4.5 | AB30: 4.5 | AC30: 4.5 | AE30: 46170 | AF30: 4.5 | AG30: 4.6 | AH30: 4.7 | AJ30: 2026.05.28 | AK30: =AVERAGE(L30,Q30,V30,AA30,AF30) -> 4.52 | AL30: =AVERAGE(M30,R30,W30,AB30,AG30) -> 4.42 | AM30: =AVERAGE(N30,S30,X30,AC30,AH30) -> 4.58
A31: QAC_228 | B31: Factual | C31: Medium | D31: Constitutional | E31: Through whom is the judicial power of the People exercised? | F31: Article 4(c) provides that the judicial power of the People shall be exercised by Parliament through courts, tribunals and other institutions created and established by the Constitution or created and established by law, except in so far as Parliament itself has power under the Constitution to exercise judicial power. | G31: Article 4 | H31: Art. 4: The Sovereignty of the People shall be exercised Exercise of Sovereignty and enjoyed in the following manner: (a) the legislative power of the People shall be exercised by Parliament, consisting of el | I31: Human Annotated | J31: =MAX(P31,U31,Z31,AE31,AJ31) -> 46170 | K31: LEGAL_EXPERT_1, LEGAL_EXPERT_2, LEGAL_EXPERT_3, LEGAL_EXPERT_4, LEGAL_EXPERT_5 | L31: 4.5 | M31: 4.4 | N31: 4.6 | P31: 2026.05.25 | Q31: 4.5 | R31: 4.5 | S31: 4.8 | U31: 2025.05.27 | V31: 4.8 | W31: 4.4 | X31: 4.6 | Z31: 46168 | AA31: 4.7 | AB31: 4.6 | AC31: 4.7 | AE31: 46170 | AF31: 4.5 | AG31: 4.7 | AH31: 4.6 | AJ31: 2026.05.28 | AK31: =AVERAGE(L31,Q31,V31,AA31,AF31) -> 4.6 | AL31: =AVERAGE(M31,R31,W31,AB31,AG31) -> 4.52 | AM31: =AVERAGE(N31,S31,X31,AC31,AH31) -> 4.66
... A53: QAC_250 | B53: Factual | C53: Easy | D53: Constitutional | E53: What cultural rights are guaranteed to citizens under Article 14? | F53: Article 14(1)(f) provides that every citizen is entitled to the freedom, either by himself or in association with others, to enjoy and promote his own culture and to use his own language. | G53: Article 14 | H53: Art. 14: (1) Every citizen is entitled to speech, assembly, (a) the freedom of speech and expression association, including publication; occupation, movement, & c. (b) the freedom of peaceful assembly; (c) th | I53: Human Annotated | J53: =MAX(P53,U53,Z53,AE53,AJ53) -> 46170 | K53: LEGAL_EXPERT_1, LEGAL_EXPERT_2, LEGAL_EXPERT_3, LEGAL_EXPERT_4, LEGAL_EXPERT_5 | L53: 4.5 | M53: 4.4 | N53: 4.6 | P53: 2026.05.25 | Q53: 4.5 | R53: 4.3 | S53: 4.7 | U53: 2025.05.27 | V53: 4.7 | W53: 4.6 | X53: 4.6 | Z53: 46168 | AA53: 4.5 | AB53: 4.5 | AC53: 4.5 | AE53: 46170 | AF53: 4.5 | AG53: 4.6 | AH53: 4.7 | AJ53: 2026.05.28 | AK53: =AVERAGE(L53,Q53,V53,AA53,AF53) -> 4.54 | AL53: =AVERAGE(M53,R53,W53,AB53,AG53) -> 4.48 | AM53: =AVERAGE(N53,S53,X53,AC53,AH53) -> 4.62
A337: QAC_334 | B337: Procedural | C337: Hard | D337: Constitutional | E337: A Bill seeks to alter the provisions on the unitary status of Sri Lanka. What additional constitutional procedure applies? | F337: Article 2 declares Sri Lanka to be a Unitary State. Article 83(a) provides that a Bill for the amendment of or which is inconsistent with Article 2 requires not only a two-thirds majority of all Members of Parliament but also approval at a Referendum. This double-lock procedure applies because Article 2 is among the most entrenched provisions of the Constitution. | G337: Article 83, Article 85 | H337: Art. 83: Notwithstanding anything to the contrary in the of certain provisions of Article 82 Bills at a Referendum (a) a Bill for the amendment or for the repeal and replacement of or which is inconsistent wi || Art. 85: (1) The President shall submit to the People by of Bills to Referendum every Bill or any provision in any Bill people by Referendum which the Cabinet of Ministers has certified as being intended to be

Sheet 251-300
A1: Item ID | B1: Query Type | C1: Difficulty | D1: Legal Domain | E1: Question | F1: Reference Answer | G1: Constitutional Articles | H1: Supporting Passage(s) | I1: Annotattion Type | J1: Annotation Date | K1: Reviewer IDs | L1: Reviever 1: Chathuri Madushika (LLB ousl) | Q1: Reviever 2: Rohana Dasanayaka (LLB ousl) | V1: Reviever 3: Dulani Kulasooriya (LLB ousl) | AA1: Reviever 4: Dulshan Liyanaarachchi (LLB ousl) | AF1: Reviever 5: Inoshika Kodithuwakku (LLB ousl) | AK1: Mean | AL1: Mean | AM1: Mean
L2: Reviewer ID: LEGAL_EXPERT_1 | Q2: Reviewer ID: LEGAL_EXPERT_2 | V2: Reviewer ID: LEGAL_EXPERT_3 | AA2: Reviewer ID: LEGAL_EXPERT_4 | AF2: Reviewer ID: LEGAL_EXPERT_5 | AK2: Reviewer IDs: LEGAL_EXPERT_1, LEGAL_EXPERT_2, LEGAL_EXPERT_3, LEGAL_EXPERT_4, LEGAL_EXPERT_5
L3: Correctness (1=Poor 5=Excellent) | M3: Completeness (1=Poor 5=Excellent) | N3: Clarity (1=Poor 5=Excellent) | O3: Expert Comments | P3: Review Date | Q3: Correctness (1=Poor 5=Excellent) | R3: Completeness (1=Poor 5=Excellent) | S3: Clarity (1=Poor 5=Excellent) | T3: Expert Comments | U3: Review Date | V3: Correctness (1=Poor 5=Excellent) | W3: Completeness (1=Poor 5=Excellent) | X3: Clarity (1=Poor 5=Excellent) | Y3: Expert Comments | Z3: Review Date | AA3: Correctness (1=Poor 5=Excellent) | AB3: Completeness (1=Poor 5=Excellent) | AC3: Clarity (1=Poor 5=Excellent) | AD3: Expert Comments | AE3: Review Date | AF3: Correctness (1=Poor 5=Excellent) | AG3: Completeness (1=Poor 5=Excellent) | AH3: Clarity (1=Poor 5=Excellent) | AI3: Expert Comments | AJ3: Review Date | AK3: Correctness (1=Poor 5=Excellent) | AL3: Completeness (1=Poor 5=Excellent) | AM3: Clarity (1=Poor 5=Excellent)
A4: QAC_251 | B4: Factual | C4: Easy | D4: Constitutional | E4: Does the Constitution recognise a right to return to Sri Lanka? | F4: Article 14(1)(i) provides that every citizen is entitled to the freedom to return to Sri Lanka. | G4: Article 14 | H4: Art. 14: (1) Every citizen is entitled to speech, assembly, (a) the freedom of speech and expression association, including publication; occupation, movement, & c. (b) the freedom of peaceful assembly; (c) th | I4: Human Annotated | J4: =MAX(P4,U4,Z4,AE4,AJ4) -> 46170 | K4: LEGAL_EXPERT_1, LEGAL_EXPERT_2, LEGAL_EXPERT_3, LEGAL_EXPERT_4, LEGAL_EXPERT_5 | L4: 4.7 | M4: 4.5 | N4: 4.8 | P4: 2026.05.25 | Q4: 4.5 | R4: 4.3 | S4: 4.7 | U4: 2025.05.27 | V4: 4.7 | W4: 4.7 | X4: 4.6 | Z4: 46168 | AA4: 4.7 | AB4: 4.8 | AC4: 4.7 | AE4: 46170 | AF4: 4.7 | AG4: 4.6 | AH4: 4.5 | AJ4: 2026.05.28 | AK4: =AVERAGE(L4,Q4,V4,AA4,AF4) -> 4.66 | AL4: =AVERAGE(M4,R4,W4,AB4,AG4) -> 4.58 | AM4: =AVERAGE(N4,S4,X4,AC4,AH4) -> 4.66
A5: QAC_252 | B5: Interpretive | C5: Medium | D5: Constitutional | E5: Can the State restrict public assemblies in the interests of racial harmony? | F5: Article 15(3) provides that the exercise and operation of the fundamental right to freedom of peaceful assembly (Article 14(1)(b)) shall be subject to such restrictions as may be prescribed by law in the interests of racial and religious harmony only. | G5: Article 14, Article 15 | H5: Art. 14: (1) Every citizen is entitled to speech, assembly, (a) the freedom of speech and expression association, including publication; occupation, movement, & c. (b) the freedom of peaceful assembly; (c) th || Art. 15: (1) The exercise and operation of the fundamental fundamental rights declared and recognized by Articles rights 13(5) and 13(6) shall be subject only to such restrictions as may be prescribed by law i | I5: Human Annotated | J5: =MAX(P5,U5,Z5,AE5,AJ5) -> 46170 | K5: LEGAL_EXPERT_1, LEGAL_EXPERT_2, LEGAL_EXPERT_3, LEGAL_EXPERT_4, LEGAL_EXPERT_5 | L5: 4.7 | M5: 4.5 | N5: 4.8 | P5: 2026.05.25 | Q5: 4.5 | R5: 4.4 | S5: 4.8 | U5: 2025.05.27 | V5: 4.3 | W5: 4.4 | X5: 4.6 | Z5: 46168 | AA5: 4.4 | AB5: 4.5 | AC5: 4.6 | AE5: 46170 | AF5: 4.5 | AG5: 4.8 | AH5: 4.8 | AJ5: 2026.05.28 | AK5: =AVERAGE(L5,Q5,V5,AA5,AF5) -> 4.48 | AL5: =AVERAGE(M5,R5,W5,AB5,AG5) -> 4.52 | AM5: =AVERAGE(N5,S5,X5,AC5,AH5) -> 4.72
A6: QAC_253 | B6: Interpretive | C6: Hard | D6: Constitutional | E6: A journalist is prosecuted for criticism of Parliament. Which constitutional restrictions on freedom of speech may be relevant? | F6: Article 14(1)(a) guarantees freedom of speech and expression including publication. Article 15(2) permits restrictions on this freedom prescribed by law in the interests of racial and religious harmony, national security, public order, protection of public health or morality, parliamentary privilege, contempt of court, or for the purpose of securing recognition and respect for the rights and freedoms of others. A prosecution for parliamentary privilege-related speech would need to be assessed against these grounds. | G6: Article 14, Article 15 | H6: Art. 14: (1) Every citizen is entitled to speech, assembly, (a) the freedom of speech and expression association, including publication; occupation, movement, & c. (b) the freedom of peaceful assembly; (c) th || Art. 15: (1) The exercise and operation of the fundamental fundamental rights declared and recognized by Articles rights 13(5) and 13(6) shall be subject only to such restrictions as may be prescribed by law i | I6: Human Annotated | J6: =MAX(P6,U6,Z6,AE6,AJ6) -> 46170 | K6: LEGAL_EXPERT_1, LEGAL_EXPERT_2, LEGAL_EXPERT_3, LEGAL_EXPERT_4, LEGAL_EXPERT_5 | L6: 4.7 | M6: 4.5 | N6: 4.8 | P6: 2026.05.25 | Q6: 4.6 | R6: 4.3 | S6: 4.7 | U6: 2025.05.27 | V6: 4.6 | W6: 4.4 | X6: 4.7 | Z6: 46168 | AA6: 4.6 | AB6: 4.7 | AC6: 4.5 | AE6: 46170 | AF6: 4.6 | AG6: 4.5 | AH6: 4.7 | AJ6: 2026.05.28 | AK6: =AVERAGE(L6,Q6,V6,AA6,AF6) -> 4.62 | AL6: =AVERAGE(M6,R6,W6,AB6,AG6) -> 4.48 | AM6: =AVERAGE(N6,S6,X6,AC6,AH6) -> 4.68
A7: QAC_254 | B7: Factual | C7: Easy | D7: Constitutional | E7: Does the Constitution protect the freedom to conduct a business or trade? | F7: Article 14(1)(g) provides that every citizen is entitled to the freedom to engage in any lawful occupation, profession, trade, business or enterprise. This freedom is subject to restrictions under Article 15(5) prescribed by law in the interests of national economy or in relation to professional, technical, academic, financial and other qualifications necessary for the practice of the occupation. | G7: Article 14, Article 15 | H7: Art. 14: (1) Every citizen is entitled to speech, assembly, (a) the freedom of speech and expression association, including publication; occupation, movement, & c. (b) the freedom of peaceful assembly; (c) th || Art. 15: (1) The exercise and operation of the fundamental fundamental rights declared and recognized by Articles rights 13(5) and 13(6) shall be subject only to such restrictions as may be prescribed by law i | I7: Human Annotated | J7: =MAX(P7,U7,Z7,AE7,AJ7) -> 46170 | K7: LEGAL_EXPERT_1, LEGAL_EXPERT_2, LEGAL_EXPERT_3, LEGAL_EXPERT_4, LEGAL_EXPERT_5 | L7: 4.7 | M7: 4.5 | N7: 4.8 | P7: 2026.05.25 | Q7: 4.5 | R7: 4.4 | S7: 4.6 | U7: 2025.05.27 | V7: 4.7 | W7: 4.4 | X7: 4.5 | Z7: 46168 | AA7: 4.9 | AB7: 4.8 | AC7: 4.7 | AE7: 46170 | AF7: 4.7 | AG7: 4.6 | AH7: 4.5 | AJ7: 2026.05.28 | AK7: =AVERAGE(L7,Q7,V7,AA7,AF7) -> 4.7 | AL7: =AVERAGE(M7,R7,W7,AB7,AG7) -> 4.54 | AM7: =AVERAGE(N7,S7,X7,AC7,AH7) -> 4.62
A8: QAC_255 | B8: Factual | C8: Medium | D8: Constitutional | E8: Under what circumstances may the constitutional right to freedom of movement be restricted? | F8: Article 15(6) provides that the exercise and operation of the freedom of movement (Article 14(1)(h)) may be restricted by law in the interests of national economy. The freedom to return to Sri Lanka (Article 14(1)(i)) is subject to the broader restrictions applicable under Article 15(7), which covers all fundamental rights and permits restrictions in the interests of national security, public order, and the protection of public health or morality. | G8: Article 14, Article 15 | H8: Art. 14: (1) Every citizen is entitled to speech, assembly, (a) the freedom of speech and expression association, including publication; occupation, movement, & c. (b) the freedom of peaceful assembly; (c) th || Art. 15: (1) The exercise and operation of the fundamental fundamental rights declared and recognized by Articles rights 13(5) and 13(6) shall be subject only to such restrictions as may be prescribed by law i | I8: Human Annotated | J8: =MAX(P8,U8,Z8,AE8,AJ8) -> 46170 | K8: LEGAL_EXPERT_1, LEGAL_EXPERT_2, LEGAL_EXPERT_3, LEGAL_EXPERT_4, LEGAL_EXPERT_5 | L8: 4.7 | M8: 4.5 | N8: 4.8 | P8: 2026.05.25 | Q8: 4.5 | R8: 4.3 | S8: 4.7 | U8: 2025.05.27 | V8: 4.6 | W8: 4.4 | X8: 4.7 | Z8: 46168 | AA8: 4.5 | AB8: 4.4 | AC8: 4.8 | AE8: 46170 | AF8: 4.5 | AG8: 4.8 | AH8: 4.8 | AJ8: 2026.05.28 | AK8: =AVERAGE(L8,Q8,V8,AA8,AF8) -> 4.56 | AL8: =AVERAGE(M8,R8,W8,AB8,AG8) -> 4.48 | AM8: =AVERAGE(N8,S8,X8,AC8,AH8) -> 4.76
A9: QAC_256 | B9: Interpretive | C9: Hard | D9: Constitutional | E9: Can a citizen be permanently denied the right to return to Sri Lanka under the Constitution? | F9: Article 14(1)(i) recognises every citizen's freedom to return to Sri Lanka. Article 15(6) permits restrictions on the freedom of movement (Article 14(1)(h)) only in the interests of national economy, while Article 15(7) permits broader restrictions on all fundamental rights, including the freedom to return, in the interests of national security, public order, the protection of public health or morality, or to secure due recognition of the rights and freedoms of others; but all such restrictions must be prescribed by law. A permanent and absolute denial with no legal basis would be inconsistent with the constitutional guarantee. | G9: Article 14, Article 15 | H9: Art. 14: (1) Every citizen is entitled to speech, assembly, (a) the freedom of speech and expression association, including publication; occupation, movement, & c. (b) the freedom of peaceful assembly; (c) th || Art. 15: (1) The exercise and operation of the fundamental fundamental rights declared and recognized by Articles rights 13(5) and 13(6) shall be subject only to such restrictions as may be prescribed by law i | I9: Human Annotated | J9: =MAX(P9,U9,Z9,AE9,AJ9) -> 46170 | K9: LEGAL_EXPERT_1, LEGAL_EXPERT_2, LEGAL_EXPERT_3, LEGAL_EXPERT_4, LEGAL_EXPERT_5 | L9: 4.7 | M9: 4.5 | N9: 4.8 | P9: 2026.05.25 | Q9: 4.4 | R9: 4.3 | S9: 4.7 | U9: 2025.05.27 | V9: 4.8 | W9: 4.4 | X9: 4.5 | Z9: 46168 | AA9: 4.7 | AB9: 4.5 | AC9: 4.5 | AE9: 46170 | AF9: 4.6 | AG9: 4.5 | AH9: 4.7 | AJ9: 2026.05.28 | AK9: =AVERAGE(L9,Q9,V9,AA9,AF9) -> 4.64 | AL9: =AVERAGE(M9,R9,W9,AB9,AG9) -> 4.44 | AM9: =AVERAGE(N9,S9,X9,AC9,AH9) -> 4.64
A10: QAC_257 | B10: Factual | C10: Medium | D10: Constitutional | E10: What constitutional limitations apply to the freedom of association? | F10: Article 15(4) provides that the freedom of association (Article 14(1)(c)) and the freedom to form and join a trade union (Article 14(1)(d)) shall be subject to such restrictions as may be prescribed by law in the interests of racial and religious harmony or in relation to the national economy. | G10: Article 14, Article 15 | H10: Art. 14: (1) Every citizen is entitled to speech, assembly, (a) the freedom of speech and expression association, including publication; occupation, movement, & c. (b) the freedom of peaceful assembly; (c) th || Art. 15: (1) The exercise and operation of the fundamental fundamental rights declared and recognized by Articles rights 13(5) and 13(6) shall be subject only to such restrictions as may be prescribed by law i | I10: Human Annotated | J10: =MAX(P10,U10,Z10,AE10,AJ10) -> 46170 | K10: LEGAL_EXPERT_1, LEGAL_EXPERT_2, LEGAL_EXPERT_3, LEGAL_EXPERT_4, LEGAL_EXPERT_5 | L10: 4.7 | M10: 4.5 | N10: 4.8 | P10: 2026.05.25 | Q10: 4.5 | R10: 4.3 | S10: 4.8 | U10: 2025.05.27 | V10: 4.9 | W10: 4.7 | X10: 4.6 | Z10: 46168 | AA10: 4.7 | AB10: 4.7 | AC10: 4.7 | AE10: 46170 | AF10: 4.7 | AG10: 4.6 | AH10: 4.5 | AJ10: 2026.05.28 | AK10: =AVERAGE(L10,Q10,V10,AA10,AF10) -> 4.7 | AL10: =AVERAGE(M10,R10,W10,AB10,AG10) -> 4.56 | AM10: =AVERAGE(N10,S10,X10,AC10,AH10) -> 4.68
